Workbook

Sheet Summary
F1: EP Details (Grouped) | L1: Major Errors (Grouped) | T1: Minor Errors (Grouped) | AI1: Unclassified (Grouped)
A2: S. No. | B2: SHOW NAMES | C2: Show IDs | D2: DE title | E2: QC'd months (dump) | F2: Ep Count | G2: First EP with error | H2: Last EP with error | I2: Additional EPs | J2: Total Errors | K2: Total Errors Per Episode | L2: Major Errors | M2: Abrupt cut / Jerk | N2: Audio quality | O2: Gramatically incorrect (voa) | P2: Incorrect name | Q2: Mispronunciation | R2: Missed line / Word | S2: Script error | T2: Minor Errors | U2: Acting | V2: Audio Regenerated | W2: Background noise | X2: Breathing noise | Y2: Clarity of speech | Z2: Distorted sound | AA2: Fumble / Mumble | AB2: Modulation | AC2: Physical noise of VOA | AD2: Repetition | AE2: Sibilance | AF2: Tone change | AG2: Unusual gap / pause | AH2: Voice processing & editing | AI2: Unclassified | AJ2: BGM/SFX | AK2: Pending | AL2: Resolved | AM2: Ignore | AN2: Unique Ep with error | AO2: Unique Error Rate | AP2: Unique Ep with Major error | AQ2: Unique Error Major Rate | AR2: Unique Ep with Minor error | AS2: Unique Error Minor Rate
A3: 1 | B3: The Miracle Heiress | C3: 9a175f97e92a638a5697307799ea3b8b8f419aac | D3: Die Wundererbin | E3: Aug, Sept | F3: =IFERROR(VLOOKUP($C3,'Show IDs'!$A:$D,4,FALSE)+0,"") -> 304 | G3: =IFERROR(_xlfn.MINIFS('QC Dump (clean)'!$F:$F,'QC Dump (clean)'!$A:$A,$C3,'QC Dump (clean)'!$M:$M,"<>Not an error"),"") -> 1 | H3: =IFERROR(_xlfn.MAXIFS('QC Dump (clean)'!$F:$F,'QC Dump (clean)'!$A:$A,$C3,'QC Dump (clean)'!$M:$M,"<>Not an error"),"") -> 300 | J3: =L3+T3+AI3 -> 1340 | K3: =IFERROR(J3/$F3,"") -> 4.4078947 | L3: =COUNTIFS('QC Dump (clean)'!$A:$A,$C3,'QC Dump (clean)'!$M:$M,"Major") -> 1301 | M3: =COUNTIFS('QC Dump (clean)'!$A:$A,$C3,'QC Dump (clean)'!$L:$L,M$2,'QC Dump (clean)'!$M:$M,"Major") -> 3 | N3: =COUNTIFS('QC Dump (clean)'!$A:$A,$C3,'QC Dump (clean)'!$L:$L,N$2,'QC Dump (clean)'!$M:$M,"Major") -> 37 | O3: =COUNTIFS('QC Dump (clean)'!$A:$A,$C3,'QC Dump (clean)'!$L:$L,O$2,'QC Dump (clean)'!$M:$M,"Major") -> 0 | P3: =COUNTIFS('QC Dump (clean)'!$A:$A,$C3,'QC Dump (clean)'!$L:$L,P$2,'QC Dump (clean)'!$M:$M,"Major") -> 1 | Q3: =COUNTIFS('QC Dump (clean)'!$A:$A,$C3,'QC Dump (clean)'!$L:$L,Q$2,'QC Dump (clean)'!$M:$M,"Major") -> 152 | R3: =COUNTIFS('QC Dump (clean)'!$A:$A,$C3,'QC Dump (clean)'!$L:$L,R$2,'QC Dump (clean)'!$M:$M,"Major") -> 1 | S3: =COUNTIFS('QC Dump (clean)'!$A:$A,$C3,'QC Dump (clean)'!$L:$L,S$2,'QC Dump (clean)'!$M:$M,"Major") -> 1107 | T3: =COUNTIFS('QC Dump (clean)'!$A:$A,$C3,'QC Dump (clean)'!$M:$M,"Minor") -> 39 | U3: =COUNTIFS('QC Dump (clean)'!$A:$A,$C3,'QC Dump (clean)'!$L:$L,U$2,'QC Dump (clean)'!$M:$M,"Minor") -> 1 | V3: =COUNTIFS('QC Dump (clean)'!$A:$A,$C3,'QC Dump (clean)'!$L:$L,V$2,'QC Dump (clean)'!$M:$M,"Minor") -> 0 | W3: =COUNTIFS('QC Dump (clean)'!$A:$A,$C3,'QC Dump (clean)'!$L:$L,W$2,'QC Dump (clean)'!$M:$M,"Minor") -> 0 | X3: =COUNTIFS('QC Dump (clean)'!$A:$A,$C3,'QC Dump (clean)'!$L:$L,X$2,'QC Dump (clean)'!$M:$M,"Minor") -> 0 | Y3: =COUNTIFS('QC Dump (clean)'!$A:$A,$C3,'QC Dump (clean)'!$L:$L,Y$2,'QC Dump (clean)'!$M:$M,"Minor") -> 0 | Z3: =COUNTIFS('QC Dump (clean)'!$A:$A,$C3,'QC Dump (clean)'!$L:$L,Z$2,'QC Dump (clean)'!$M:$M,"Minor") -> 0 | AA3: =COUNTIFS('QC Dump (clean)'!$A:$A,$C3,'QC Dump (clean)'!$L:$L,AA$2,'QC Dump (clean)'!$M:$M,"Minor") -> 0 | AB3: =COUNTIFS('QC Dump (clean)'!$A:$A,$C3,'QC Dump (clean)'!$L:$L,AB$2,'QC Dump (clean)'!$M:$M,"Minor") -> 33 | ... AH3: =COUNTIFS('QC Dump (clean)'!$A:$A,$C3,'QC Dump (clean)'!$L:$L,AH$2,'QC Dump (clean)'!$M:$M,"Minor") -> 0 | AI3: =COUNTIFS('QC Dump (clean)'!$A:$A,$C3,'QC Dump (clean)'!$M:$M,"Unclassified") -> 0 | AJ3: =COUNTIFS('QC Dump (clean)'!$A:$A,$C3,'QC Dump (clean)'!$L:$L,AJ$2,'QC Dump (clean)'!$M:$M,"Unclassified") -> 0 | AK3: =COUNTIFS('QC Dump (clean)'!$A:$A,$C3,'QC Dump (clean)'!$H:$H,"Pending",'QC Dump (clean)'!$M:$M,"<>Not an error") -> 87 | AL3: =COUNTIFS('QC Dump (clean)'!$A:$A,$C3,'QC Dump (clean)'!$H:$H,"Resolved",'QC Dump (clean)'!$M:$M,"<>Not an error") -> 1116 | AM3: =COUNTIFS('QC Dump (clean)'!$A:$A,$C3,'QC Dump (clean)'!$H:$H,"Ignore",'QC Dump (clean)'!$M:$M,"<>Not an error") -> 137 | AN3: =SUMIFS('QC Dump (clean)'!$S:$S,'QC Dump (clean)'!$A:$A,$C3) -> 285 | AO3: =IFERROR(AN3/$F3,"") -> 0.9375 | AP3: =SUMIFS('QC Dump (clean)'!$T:$T,'QC Dump (clean)'!$A:$A,$C3) -> 280 | AQ3: =IFERROR(AP3/$F3,"") -> 0.92105263 | AR3: =SUMIFS('QC Dump (clean)'!$U:$U,'QC Dump (clean)'!$A:$A,$C3) -> 35 | AS3: =IFERROR(AR3/$F3,"") -> 0.11513158
A4: 2 | B4: Primal Partners | C4: 819eabfbd96880cd7f6d42202600e24bdb384108 | D4: Primal Partners (New) | E4: Sept | F4: =IFERROR(VLOOKUP($C4,'Show IDs'!$A:$D,4,FALSE)+0,"") -> 176 | G4: =IFERROR(_xlfn.MINIFS('QC Dump (clean)'!$F:$F,'QC Dump (clean)'!$A:$A,$C4,'QC Dump (clean)'!$M:$M,"<>Not an error"),"") -> 1 | H4: =IFERROR(_xlfn.MAXIFS('QC Dump (clean)'!$F:$F,'QC Dump (clean)'!$A:$A,$C4,'QC Dump (clean)'!$M:$M,"<>Not an error"),"") -> 151 | J4: =L4+T4+AI4 -> 839 | K4: =IFERROR(J4/$F4,"") -> 4.7670455 | L4: =COUNTIFS('QC Dump (clean)'!$A:$A,$C4,'QC Dump (clean)'!$M:$M,"Major") -> 825 | M4: =COUNTIFS('QC Dump (clean)'!$A:$A,$C4,'QC Dump (clean)'!$L:$L,M$2,'QC Dump (clean)'!$M:$M,"Major") -> 2 | N4: =COUNTIFS('QC Dump (clean)'!$A:$A,$C4,'QC Dump (clean)'!$L:$L,N$2,'QC Dump (clean)'!$M:$M,"Major") -> 11 | O4: =COUNTIFS('QC Dump (clean)'!$A:$A,$C4,'QC Dump (clean)'!$L:$L,O$2,'QC Dump (clean)'!$M:$M,"Major") -> 0 | P4: =COUNTIFS('QC Dump (clean)'!$A:$A,$C4,'QC Dump (clean)'!$L:$L,P$2,'QC Dump (clean)'!$M:$M,"Major") -> 0 | Q4: =COUNTIFS('QC Dump (clean)'!$A:$A,$C4,'QC Dump (clean)'!$L:$L,Q$2,'QC Dump (clean)'!$M:$M,"Major") -> 39 | R4: =COUNTIFS('QC Dump (clean)'!$A:$A,$C4,'QC Dump (clean)'!$L:$L,R$2,'QC Dump (clean)'!$M:$M,"Major") -> 0 | S4: =COUNTIFS('QC Dump (clean)'!$A:$A,$C4,'QC Dump (clean)'!$L:$L,S$2,'QC Dump (clean)'!$M:$M,"Major") -> 773 | T4: =COUNTIFS('QC Dump (clean)'!$A:$A,$C4,'QC Dump (clean)'!$M:$M,"Minor") -> 14 | U4: =COUNTIFS('QC Dump (clean)'!$A:$A,$C4,'QC Dump (clean)'!$L:$L,U$2,'QC Dump (clean)'!$M:$M,"Minor") -> 0 | V4: =COUNTIFS('QC Dump (clean)'!$A:$A,$C4,'QC Dump (clean)'!$L:$L,V$2,'QC Dump (clean)'!$M:$M,"Minor") -> 0 | W4: =COUNTIFS('QC Dump (clean)'!$A:$A,$C4,'QC Dump (clean)'!$L:$L,W$2,'QC Dump (clean)'!$M:$M,"Minor") -> 0 | X4: =COUNTIFS('QC Dump (clean)'!$A:$A,$C4,'QC Dump (clean)'!$L:$L,X$2,'QC Dump (clean)'!$M:$M,"Minor") -> 0 | Y4: =COUNTIFS('QC Dump (clean)'!$A:$A,$C4,'QC Dump (clean)'!$L:$L,Y$2,'QC Dump (clean)'!$M:$M,"Minor") -> 0 | Z4: =COUNTIFS('QC Dump (clean)'!$A:$A,$C4,'QC Dump (clean)'!$L:$L,Z$2,'QC Dump (clean)'!$M:$M,"Minor") -> 0 | AA4: =COUNTIFS('QC Dump (clean)'!$A:$A,$C4,'QC Dump (clean)'!$L:$L,AA$2,'QC Dump (clean)'!$M:$M,"Minor") -> 0 | AB4: =COUNTIFS('QC Dump (clean)'!$A:$A,$C4,'QC Dump (clean)'!$L:$L,AB$2,'QC Dump (clean)'!$M:$M,"Minor") -> 12 | ... AH4: =COUNTIFS('QC Dump (clean)'!$A:$A,$C4,'QC Dump (clean)'!$L:$L,AH$2,'QC Dump (clean)'!$M:$M,"Minor") -> 0 | AI4: =COUNTIFS('QC Dump (clean)'!$A:$A,$C4,'QC Dump (clean)'!$M:$M,"Unclassified") -> 0 | AJ4: =COUNTIFS('QC Dump (clean)'!$A:$A,$C4,'QC Dump (clean)'!$L:$L,AJ$2,'QC Dump (clean)'!$M:$M,"Unclassified") -> 0 | AK4: =COUNTIFS('QC Dump (clean)'!$A:$A,$C4,'QC Dump (clean)'!$H:$H,"Pending",'QC Dump (clean)'!$M:$M,"<>Not an error") -> 417 | AL4: =COUNTIFS('QC Dump (clean)'!$A:$A,$C4,'QC Dump (clean)'!$H:$H,"Resolved",'QC Dump (clean)'!$M:$M,"<>Not an error") -> 418 | AM4: =COUNTIFS('QC Dump (clean)'!$A:$A,$C4,'QC Dump (clean)'!$H:$H,"Ignore",'QC Dump (clean)'!$M:$M,"<>Not an error") -> 4 | AN4: =SUMIFS('QC Dump (clean)'!$S:$S,'QC Dump (clean)'!$A:$A,$C4) -> 129 | AO4: =IFERROR(AN4/$F4,"") -> 0.73295455 | AP4: =SUMIFS('QC Dump (clean)'!$T:$T,'QC Dump (clean)'!$A:$A,$C4) -> 129 | AQ4: =IFERROR(AP4/$F4,"") -> 0.73295455 | AR4: =SUMIFS('QC Dump (clean)'!$U:$U,'QC Dump (clean)'!$A:$A,$C4) -> 11 | AS4: =IFERROR(AR4/$F4,"") -> 0.0625
A5: 3 | B5: Zompirewolf | C5: 294cd7d130be8bb0326127c52ff2769fcf9a956d | D5: Zompirewolf: Die Geburt Einer Legende | E5: Aug, Sept | F5: =IFERROR(VLOOKUP($C5,'Show IDs'!$A:$D,4,FALSE)+0,"") -> 571 | G5: =IFERROR(_xlfn.MINIFS('QC Dump (clean)'!$F:$F,'QC Dump (clean)'!$A:$A,$C5,'QC Dump (clean)'!$M:$M,"<>Not an error"),"") -> 316 | H5: =IFERROR(_xlfn.MAXIFS('QC Dump (clean)'!$F:$F,'QC Dump (clean)'!$A:$A,$C5,'QC Dump (clean)'!$M:$M,"<>Not an error"),"") -> 569 | J5: =L5+T5+AI5 -> 666 | K5: =IFERROR(J5/$F5,"") -> 1.1663748 | L5: =COUNTIFS('QC Dump (clean)'!$A:$A,$C5,'QC Dump (clean)'!$M:$M,"Major") -> 660 | M5: =COUNTIFS('QC Dump (clean)'!$A:$A,$C5,'QC Dump (clean)'!$L:$L,M$2,'QC Dump (clean)'!$M:$M,"Major") -> 7 | N5: =COUNTIFS('QC Dump (clean)'!$A:$A,$C5,'QC Dump (clean)'!$L:$L,N$2,'QC Dump (clean)'!$M:$M,"Major") -> 0 | O5: =COUNTIFS('QC Dump (clean)'!$A:$A,$C5,'QC Dump (clean)'!$L:$L,O$2,'QC Dump (clean)'!$M:$M,"Major") -> 0 | P5: =COUNTIFS('QC Dump (clean)'!$A:$A,$C5,'QC Dump (clean)'!$L:$L,P$2,'QC Dump (clean)'!$M:$M,"Major") -> 0 | Q5: =COUNTIFS('QC Dump (clean)'!$A:$A,$C5,'QC Dump (clean)'!$L:$L,Q$2,'QC Dump (clean)'!$M:$M,"Major") -> 246 | R5: =COUNTIFS('QC Dump (clean)'!$A:$A,$C5,'QC Dump (clean)'!$L:$L,R$2,'QC Dump (clean)'!$M:$M,"Major") -> 0 | S5: =COUNTIFS('QC Dump (clean)'!$A:$A,$C5,'QC Dump (clean)'!$L:$L,S$2,'QC Dump (clean)'!$M:$M,"Major") -> 407 | T5: =COUNTIFS('QC Dump (clean)'!$A:$A,$C5,'QC Dump (clean)'!$M:$M,"Minor") -> 6 | U5: =COUNTIFS('QC Dump (clean)'!$A:$A,$C5,'QC Dump (clean)'!$L:$L,U$2,'QC Dump (clean)'!$M:$M,"Minor") -> 0 | V5: =COUNTIFS('QC Dump (clean)'!$A:$A,$C5,'QC Dump (clean)'!$L:$L,V$2,'QC Dump (clean)'!$M:$M,"Minor") -> 0 | W5: =COUNTIFS('QC Dump (clean)'!$A:$A,$C5,'QC Dump (clean)'!$L:$L,W$2,'QC Dump (clean)'!$M:$M,"Minor") -> 0 | X5: =COUNTIFS('QC Dump (clean)'!$A:$A,$C5,'QC Dump (clean)'!$L:$L,X$2,'QC Dump (clean)'!$M:$M,"Minor") -> 3 | Y5: =COUNTIFS('QC Dump (clean)'!$A:$A,$C5,'QC Dump (clean)'!$L:$L,Y$2,'QC Dump (clean)'!$M:$M,"Minor") -> 0 | Z5: =COUNTIFS('QC Dump (clean)'!$A:$A,$C5,'QC Dump (clean)'!$L:$L,Z$2,'QC Dump (clean)'!$M:$M,"Minor") -> 0 | AA5: =COUNTIFS('QC Dump (clean)'!$A:$A,$C5,'QC Dump (clean)'!$L:$L,AA$2,'QC Dump (clean)'!$M:$M,"Minor") -> 0 | AB5: =COUNTIFS('QC Dump (clean)'!$A:$A,$C5,'QC Dump (clean)'!$L:$L,AB$2,'QC Dump (clean)'!$M:$M,"Minor") -> 3 | ... AH5: =COUNTIFS('QC Dump (clean)'!$A:$A,$C5,'QC Dump (clean)'!$L:$L,AH$2,'QC Dump (clean)'!$M:$M,"Minor") -> 0 | AI5: =COUNTIFS('QC Dump (clean)'!$A:$A,$C5,'QC Dump (clean)'!$M:$M,"Unclassified") -> 0 | AJ5: =COUNTIFS('QC Dump (clean)'!$A:$A,$C5,'QC Dump (clean)'!$L:$L,AJ$2,'QC Dump (clean)'!$M:$M,"Unclassified") -> 0 | AK5: =COUNTIFS('QC Dump (clean)'!$A:$A,$C5,'QC Dump (clean)'!$H:$H,"Pending",'QC Dump (clean)'!$M:$M,"<>Not an error") -> 26 | AL5: =COUNTIFS('QC Dump (clean)'!$A:$A,$C5,'QC Dump (clean)'!$H:$H,"Resolved",'QC Dump (clean)'!$M:$M,"<>Not an error") -> 578 | AM5: =COUNTIFS('QC Dump (clean)'!$A:$A,$C5,'QC Dump (clean)'!$H:$H,"Ignore",'QC Dump (clean)'!$M:$M,"<>Not an error") -> 62 | AN5: =SUMIFS('QC Dump (clean)'!$S:$S,'QC Dump (clean)'!$A:$A,$C5) -> 164 | AO5: =IFERROR(AN5/$F5,"") -> 0.28721541 | AP5: =SUMIFS('QC Dump (clean)'!$T:$T,'QC Dump (clean)'!$A:$A,$C5) -> 164 | AQ5: =IFERROR(AP5/$F5,"") -> 0.28721541 | AR5: =SUMIFS('QC Dump (clean)'!$U:$U,'QC Dump (clean)'!$A:$A,$C5) -> 6 | AS5: =IFERROR(AR5/$F5,"") -> 0.010507881
A6: 4 | B6: The Silent Rebirth | C6: f855eae3dfc9aadc286f38e8d5e70cc6a599f238 | D6: Wiedergeboren Für Rache | E6: Sept | F6: =IFERROR(VLOOKUP($C6,'Show IDs'!$A:$D,4,FALSE)+0,"") -> 50 | G6: =IFERROR(_xlfn.MINIFS('QC Dump (clean)'!$F:$F,'QC Dump (clean)'!$A:$A,$C6,'QC Dump (clean)'!$M:$M,"<>Not an error"),"") -> 1 | H6: =IFERROR(_xlfn.MAXIFS('QC Dump (clean)'!$F:$F,'QC Dump (clean)'!$A:$A,$C6,'QC Dump (clean)'!$M:$M,"<>Not an error"),"") -> 50 | J6: =L6+T6+AI6 -> 390 | K6: =IFERROR(J6/$F6,"") -> 7.8 | L6: =COUNTIFS('QC Dump (clean)'!$A:$A,$C6,'QC Dump (clean)'!$M:$M,"Major") -> 362 | M6: =COUNTIFS('QC Dump (clean)'!$A:$A,$C6,'QC Dump (clean)'!$L:$L,M$2,'QC Dump (clean)'!$M:$M,"Major") -> 0 | N6: =COUNTIFS('QC Dump (clean)'!$A:$A,$C6,'QC Dump (clean)'!$L:$L,N$2,'QC Dump (clean)'!$M:$M,"Major") -> 0 | O6: =COUNTIFS('QC Dump (clean)'!$A:$A,$C6,'QC Dump (clean)'!$L:$L,O$2,'QC Dump (clean)'!$M:$M,"Major") -> 0 | P6: =COUNTIFS('QC Dump (clean)'!$A:$A,$C6,'QC Dump (clean)'!$L:$L,P$2,'QC Dump (clean)'!$M:$M,"Major") -> 0 | Q6: =COUNTIFS('QC Dump (clean)'!$A:$A,$C6,'QC Dump (clean)'!$L:$L,Q$2,'QC Dump (clean)'!$M:$M,"Major") -> 3 | R6: =COUNTIFS('QC Dump (clean)'!$A:$A,$C6,'QC Dump (clean)'!$L:$L,R$2,'QC Dump (clean)'!$M:$M,"Major") -> 0 | S6: =COUNTIFS('QC Dump (clean)'!$A:$A,$C6,'QC Dump (clean)'!$L:$L,S$2,'QC Dump (clean)'!$M:$M,"Major") -> 359 | T6: =COUNTIFS('QC Dump (clean)'!$A:$A,$C6,'QC Dump (clean)'!$M:$M,"Minor") -> 28 | U6: =COUNTIFS('QC Dump (clean)'!$A:$A,$C6,'QC Dump (clean)'!$L:$L,U$2,'QC Dump (clean)'!$M:$M,"Minor") -> 0 | V6: =COUNTIFS('QC Dump (clean)'!$A:$A,$C6,'QC Dump (clean)'!$L:$L,V$2,'QC Dump (clean)'!$M:$M,"Minor") -> 3 | W6: =COUNTIFS('QC Dump (clean)'!$A:$A,$C6,'QC Dump (clean)'!$L:$L,W$2,'QC Dump (clean)'!$M:$M,"Minor") -> 0 | X6: =COUNTIFS('QC Dump (clean)'!$A:$A,$C6,'QC Dump (clean)'!$L:$L,X$2,'QC Dump (clean)'!$M:$M,"Minor") -> 0 | Y6: =COUNTIFS('QC Dump (clean)'!$A:$A,$C6,'QC Dump (clean)'!$L:$L,Y$2,'QC Dump (clean)'!$M:$M,"Minor") -> 0 | Z6: =COUNTIFS('QC Dump (clean)'!$A:$A,$C6,'QC Dump (clean)'!$L:$L,Z$2,'QC Dump (clean)'!$M:$M,"Minor") -> 23 | AA6: =COUNTIFS('QC Dump (clean)'!$A:$A,$C6,'QC Dump (clean)'!$L:$L,AA$2,'QC Dump (clean)'!$M:$M,"Minor") -> 0 | AB6: =COUNTIFS('QC Dump (clean)'!$A:$A,$C6,'QC Dump (clean)'!$L:$L,AB$2,'QC Dump (clean)'!$M:$M,"Minor") -> 2 | ... AH6: =COUNTIFS('QC Dump (clean)'!$A:$A,$C6,'QC Dump (clean)'!$L:$L,AH$2,'QC Dump (clean)'!$M:$M,"Minor") -> 0 | AI6: =COUNTIFS('QC Dump (clean)'!$A:$A,$C6,'QC Dump (clean)'!$M:$M,"Unclassified") -> 0 | AJ6: =COUNTIFS('QC Dump (clean)'!$A:$A,$C6,'QC Dump (clean)'!$L:$L,AJ$2,'QC Dump (clean)'!$M:$M,"Unclassified") -> 0 | AK6: =COUNTIFS('QC Dump (clean)'!$A:$A,$C6,'QC Dump (clean)'!$H:$H,"Pending",'QC Dump (clean)'!$M:$M,"<>Not an error") -> 3 | AL6: =COUNTIFS('QC Dump (clean)'!$A:$A,$C6,'QC Dump (clean)'!$H:$H,"Resolved",'QC Dump (clean)'!$M:$M,"<>Not an error") -> 341 | AM6: =COUNTIFS('QC Dump (clean)'!$A:$A,$C6,'QC Dump (clean)'!$H:$H,"Ignore",'QC Dump (clean)'!$M:$M,"<>Not an error") -> 46 | AN6: =SUMIFS('QC Dump (clean)'!$S:$S,'QC Dump (clean)'!$A:$A,$C6) -> 50 | AO6: =IFERROR(AN6/$F6,"") -> 1 | AP6: =SUMIFS('QC Dump (clean)'!$T:$T,'QC Dump (clean)'!$A:$A,$C6) -> 50 | AQ6: =IFERROR(AP6/$F6,"") -> 1 | AR6: =SUMIFS('QC Dump (clean)'!$U:$U,'QC Dump (clean)'!$A:$A,$C6) -> 22 | AS6: =IFERROR(AR6/$F6,"") -> 0.44
A7: 5 | B7: The Secret Life of an Accidental Heiress | C7: 806152088c4f0f13e40c0788e7bc440106d13b1a | D7: The Secret Life of an Accidental Heiress | E7: Sept | F7: =IFERROR(VLOOKUP($C7,'Show IDs'!$A:$D,4,FALSE)+0,"") -> 42 | G7: =IFERROR(_xlfn.MINIFS('QC Dump (clean)'!$F:$F,'QC Dump (clean)'!$A:$A,$C7,'QC Dump (clean)'!$M:$M,"<>Not an error"),"") -> 1 | H7: =IFERROR(_xlfn.MAXIFS('QC Dump (clean)'!$F:$F,'QC Dump (clean)'!$A:$A,$C7,'QC Dump (clean)'!$M:$M,"<>Not an error"),"") -> 42 | J7: =L7+T7+AI7 -> 376 | K7: =IFERROR(J7/$F7,"") -> 8.952381 | L7: =COUNTIFS('QC Dump (clean)'!$A:$A,$C7,'QC Dump (clean)'!$M:$M,"Major") -> 350 | M7: =COUNTIFS('QC Dump (clean)'!$A:$A,$C7,'QC Dump (clean)'!$L:$L,M$2,'QC Dump (clean)'!$M:$M,"Major") -> 0 | N7: =COUNTIFS('QC Dump (clean)'!$A:$A,$C7,'QC Dump (clean)'!$L:$L,N$2,'QC Dump (clean)'!$M:$M,"Major") -> 0 | O7: =COUNTIFS('QC Dump (clean)'!$A:$A,$C7,'QC Dump (clean)'!$L:$L,O$2,'QC Dump (clean)'!$M:$M,"Major") -> 0 | P7: =COUNTIFS('QC Dump (clean)'!$A:$A,$C7,'QC Dump (clean)'!$L:$L,P$2,'QC Dump (clean)'!$M:$M,"Major") -> 0 | Q7: =COUNTIFS('QC Dump (clean)'!$A:$A,$C7,'QC Dump (clean)'!$L:$L,Q$2,'QC Dump (clean)'!$M:$M,"Major") -> 157 | R7: =COUNTIFS('QC Dump (clean)'!$A:$A,$C7,'QC Dump (clean)'!$L:$L,R$2,'QC Dump (clean)'!$M:$M,"Major") -> 0 | S7: =COUNTIFS('QC Dump (clean)'!$A:$A,$C7,'QC Dump (clean)'!$L:$L,S$2,'QC Dump (clean)'!$M:$M,"Major") -> 193 | T7: =COUNTIFS('QC Dump (clean)'!$A:$A,$C7,'QC Dump (clean)'!$M:$M,"Minor") -> 26 | U7: =COUNTIFS('QC Dump (clean)'!$A:$A,$C7,'QC Dump (clean)'!$L:$L,U$2,'QC Dump (clean)'!$M:$M,"Minor") -> 0 | V7: =COUNTIFS('QC Dump (clean)'!$A:$A,$C7,'QC Dump (clean)'!$L:$L,V$2,'QC Dump (clean)'!$M:$M,"Minor") -> 0 | W7: =COUNTIFS('QC Dump (clean)'!$A:$A,$C7,'QC Dump (clean)'!$L:$L,W$2,'QC Dump (clean)'!$M:$M,"Minor") -> 0 | X7: =COUNTIFS('QC Dump (clean)'!$A:$A,$C7,'QC Dump (clean)'!$L:$L,X$2,'QC Dump (clean)'!$M:$M,"Minor") -> 0 | Y7: =COUNTIFS('QC Dump (clean)'!$A:$A,$C7,'QC Dump (clean)'!$L:$L,Y$2,'QC Dump (clean)'!$M:$M,"Minor") -> 0 | Z7: =COUNTIFS('QC Dump (clean)'!$A:$A,$C7,'QC Dump (clean)'!$L:$L,Z$2,'QC Dump (clean)'!$M:$M,"Minor") -> 0 | AA7: =COUNTIFS('QC Dump (clean)'!$A:$A,$C7,'QC Dump (clean)'!$L:$L,AA$2,'QC Dump (clean)'!$M:$M,"Minor") -> 0 | AB7: =COUNTIFS('QC Dump (clean)'!$A:$A,$C7,'QC Dump (clean)'!$L:$L,AB$2,'QC Dump (clean)'!$M:$M,"Minor") -> 2 | ... AH7: =COUNTIFS('QC Dump (clean)'!$A:$A,$C7,'QC Dump (clean)'!$L:$L,AH$2,'QC Dump (clean)'!$M:$M,"Minor") -> 24 | AI7: =COUNTIFS('QC Dump (clean)'!$A:$A,$C7,'QC Dump (clean)'!$M:$M,"Unclassified") -> 0 | AJ7: =COUNTIFS('QC Dump (clean)'!$A:$A,$C7,'QC Dump (clean)'!$L:$L,AJ$2,'QC Dump (clean)'!$M:$M,"Unclassified") -> 0 | AK7: =COUNTIFS('QC Dump (clean)'!$A:$A,$C7,'QC Dump (clean)'!$H:$H,"Pending",'QC Dump (clean)'!$M:$M,"<>Not an error") -> 376 | AL7: =COUNTIFS('QC Dump (clean)'!$A:$A,$C7,'QC Dump (clean)'!$H:$H,"Resolved",'QC Dump (clean)'!$M:$M,"<>Not an error") -> 0 | AM7: =COUNTIFS('QC Dump (clean)'!$A:$A,$C7,'QC Dump (clean)'!$H:$H,"Ignore",'QC Dump (clean)'!$M:$M,"<>Not an error") -> 0 | AN7: =SUMIFS('QC Dump (clean)'!$S:$S,'QC Dump (clean)'!$A:$A,$C7) -> 41 | AO7: =IFERROR(AN7/$F7,"") -> 0.97619048 | AP7: =SUMIFS('QC Dump (clean)'!$T:$T,'QC Dump (clean)'!$A:$A,$C7) -> 41 | AQ7: =IFERROR(AP7/$F7,"") -> 0.97619048 | AR7: =SUMIFS('QC Dump (clean)'!$U:$U,'QC Dump (clean)'!$A:$A,$C7) -> 18 | AS7: =IFERROR(AR7/$F7,"") -> 0.42857143
A8: 6 | B8: Thorns and Thrones | C8: 60392f2f8a29ae2294a4d279a3033aeaa01affa7 | D8: Fluch Und Krone | E8: Aug, Sept | F8: =IFERROR(VLOOKUP($C8,'Show IDs'!$A:$D,4,FALSE)+0,"") -> 81 | G8: =IFERROR(_xlfn.MINIFS('QC Dump (clean)'!$F:$F,'QC Dump (clean)'!$A:$A,$C8,'QC Dump (clean)'!$M:$M,"<>Not an error"),"") -> 3 | H8: =IFERROR(_xlfn.MAXIFS('QC Dump (clean)'!$F:$F,'QC Dump (clean)'!$A:$A,$C8,'QC Dump (clean)'!$M:$M,"<>Not an error"),"") -> 81 | J8: =L8+T8+AI8 -> 240 | K8: =IFERROR(J8/$F8,"") -> 2.962963 | L8: =COUNTIFS('QC Dump (clean)'!$A:$A,$C8,'QC Dump (clean)'!$M:$M,"Major") -> 235 | M8: =COUNTIFS('QC Dump (clean)'!$A:$A,$C8,'QC Dump (clean)'!$L:$L,M$2,'QC Dump (clean)'!$M:$M,"Major") -> 0 | N8: =COUNTIFS('QC Dump (clean)'!$A:$A,$C8,'QC Dump (clean)'!$L:$L,N$2,'QC Dump (clean)'!$M:$M,"Major") -> 0 | O8: =COUNTIFS('QC Dump (clean)'!$A:$A,$C8,'QC Dump (clean)'!$L:$L,O$2,'QC Dump (clean)'!$M:$M,"Major") -> 0 | P8: =COUNTIFS('QC Dump (clean)'!$A:$A,$C8,'QC Dump (clean)'!$L:$L,P$2,'QC Dump (clean)'!$M:$M,"Major") -> 0 | Q8: =COUNTIFS('QC Dump (clean)'!$A:$A,$C8,'QC Dump (clean)'!$L:$L,Q$2,'QC Dump (clean)'!$M:$M,"Major") -> 169 | R8: =COUNTIFS('QC Dump (clean)'!$A:$A,$C8,'QC Dump (clean)'!$L:$L,R$2,'QC Dump (clean)'!$M:$M,"Major") -> 0 | S8: =COUNTIFS('QC Dump (clean)'!$A:$A,$C8,'QC Dump (clean)'!$L:$L,S$2,'QC Dump (clean)'!$M:$M,"Major") -> 66 | T8: =COUNTIFS('QC Dump (clean)'!$A:$A,$C8,'QC Dump (clean)'!$M:$M,"Minor") -> 5 | U8: =COUNTIFS('QC Dump (clean)'!$A:$A,$C8,'QC Dump (clean)'!$L:$L,U$2,'QC Dump (clean)'!$M:$M,"Minor") -> 4 | V8: =COUNTIFS('QC Dump (clean)'!$A:$A,$C8,'QC Dump (clean)'!$L:$L,V$2,'QC Dump (clean)'!$M:$M,"Minor") -> 0 | W8: =COUNTIFS('QC Dump (clean)'!$A:$A,$C8,'QC Dump (clean)'!$L:$L,W$2,'QC Dump (clean)'!$M:$M,"Minor") -> 0 | X8: =COUNTIFS('QC Dump (clean)'!$A:$A,$C8,'QC Dump (clean)'!$L:$L,X$2,'QC Dump (clean)'!$M:$M,"Minor") -> 0 | Y8: =COUNTIFS('QC Dump (clean)'!$A:$A,$C8,'QC Dump (clean)'!$L:$L,Y$2,'QC Dump (clean)'!$M:$M,"Minor") -> 1 | Z8: =COUNTIFS('QC Dump (clean)'!$A:$A,$C8,'QC Dump (clean)'!$L:$L,Z$2,'QC Dump (clean)'!$M:$M,"Minor") -> 0 | AA8: =COUNTIFS('QC Dump (clean)'!$A:$A,$C8,'QC Dump (clean)'!$L:$L,AA$2,'QC Dump (clean)'!$M:$M,"Minor") -> 0 | AB8: =COUNTIFS('QC Dump (clean)'!$A:$A,$C8,'QC Dump (clean)'!$L:$L,AB$2,'QC Dump (clean)'!$M:$M,"Minor") -> 0 | ... AH8: =COUNTIFS('QC Dump (clean)'!$A:$A,$C8,'QC Dump (clean)'!$L:$L,AH$2,'QC Dump (clean)'!$M:$M,"Minor") -> 0 | AI8: =COUNTIFS('QC Dump (clean)'!$A:$A,$C8,'QC Dump (clean)'!$M:$M,"Unclassified") -> 0 | AJ8: =COUNTIFS('QC Dump (clean)'!$A:$A,$C8,'QC Dump (clean)'!$L:$L,AJ$2,'QC Dump (clean)'!$M:$M,"Unclassified") -> 0 | AK8: =COUNTIFS('QC Dump (clean)'!$A:$A,$C8,'QC Dump (clean)'!$H:$H,"Pending",'QC Dump (clean)'!$M:$M,"<>Not an error") -> 240 | AL8: =COUNTIFS('QC Dump (clean)'!$A:$A,$C8,'QC Dump (clean)'!$H:$H,"Resolved",'QC Dump (clean)'!$M:$M,"<>Not an error") -> 0 | AM8: =COUNTIFS('QC Dump (clean)'!$A:$A,$C8,'QC Dump (clean)'!$H:$H,"Ignore",'QC Dump (clean)'!$M:$M,"<>Not an error") -> 0 | AN8: =SUMIFS('QC Dump (clean)'!$S:$S,'QC Dump (clean)'!$A:$A,$C8) -> 69 | AO8: =IFERROR(AN8/$F8,"") -> 0.85185185 | AP8: =SUMIFS('QC Dump (clean)'!$T:$T,'QC Dump (clean)'!$A:$A,$C8) -> 66 | AQ8: =IFERROR(AP8/$F8,"") -> 0.81481481 | AR8: =SUMIFS('QC Dump (clean)'!$U:$U,'QC Dump (clean)'!$A:$A,$C8) -> 5 | AS8: =IFERROR(AR8/$F8,"") -> 0.061728395
A9: 7 | B9: Bride of a dragon | C9: 4baec2ac0f23302985d2ad577e111504bd88c99c | D9: Die Braut Des Drachenkönigs | E9: Aug, Sept | F9: =IFERROR(VLOOKUP($C9,'Show IDs'!$A:$D,4,FALSE)+0,"") -> 71 | G9: =IFERROR(_xlfn.MINIFS('QC Dump (clean)'!$F:$F,'QC Dump (clean)'!$A:$A,$C9,'QC Dump (clean)'!$M:$M,"<>Not an error"),"") -> 1 | H9: =IFERROR(_xlfn.MAXIFS('QC Dump (clean)'!$F:$F,'QC Dump (clean)'!$A:$A,$C9,'QC Dump (clean)'!$M:$M,"<>Not an error"),"") -> 71 | J9: =L9+T9+AI9 -> 221 | K9: =IFERROR(J9/$F9,"") -> 3.1126761 | L9: =COUNTIFS('QC Dump (clean)'!$A:$A,$C9,'QC Dump (clean)'!$M:$M,"Major") -> 203 | M9: =COUNTIFS('QC Dump (clean)'!$A:$A,$C9,'QC Dump (clean)'!$L:$L,M$2,'QC Dump (clean)'!$M:$M,"Major") -> 0 | N9: =COUNTIFS('QC Dump (clean)'!$A:$A,$C9,'QC Dump (clean)'!$L:$L,N$2,'QC Dump (clean)'!$M:$M,"Major") -> 0 | O9: =COUNTIFS('QC Dump (clean)'!$A:$A,$C9,'QC Dump (clean)'!$L:$L,O$2,'QC Dump (clean)'!$M:$M,"Major") -> 0 | P9: =COUNTIFS('QC Dump (clean)'!$A:$A,$C9,'QC Dump (clean)'!$L:$L,P$2,'QC Dump (clean)'!$M:$M,"Major") -> 0 | Q9: =COUNTIFS('QC Dump (clean)'!$A:$A,$C9,'QC Dump (clean)'!$L:$L,Q$2,'QC Dump (clean)'!$M:$M,"Major") -> 180 | R9: =COUNTIFS('QC Dump (clean)'!$A:$A,$C9,'QC Dump (clean)'!$L:$L,R$2,'QC Dump (clean)'!$M:$M,"Major") -> 0 | S9: =COUNTIFS('QC Dump (clean)'!$A:$A,$C9,'QC Dump (clean)'!$L:$L,S$2,'QC Dump (clean)'!$M:$M,"Major") -> 23 | T9: =COUNTIFS('QC Dump (clean)'!$A:$A,$C9,'QC Dump (clean)'!$M:$M,"Minor") -> 18 | U9: =COUNTIFS('QC Dump (clean)'!$A:$A,$C9,'QC Dump (clean)'!$L:$L,U$2,'QC Dump (clean)'!$M:$M,"Minor") -> 15 | V9: =COUNTIFS('QC Dump (clean)'!$A:$A,$C9,'QC Dump (clean)'!$L:$L,V$2,'QC Dump (clean)'!$M:$M,"Minor") -> 0 | W9: =COUNTIFS('QC Dump (clean)'!$A:$A,$C9,'QC Dump (clean)'!$L:$L,W$2,'QC Dump (clean)'!$M:$M,"Minor") -> 0 | X9: =COUNTIFS('QC Dump (clean)'!$A:$A,$C9,'QC Dump (clean)'!$L:$L,X$2,'QC Dump (clean)'!$M:$M,"Minor") -> 0 | Y9: =COUNTIFS('QC Dump (clean)'!$A:$A,$C9,'QC Dump (clean)'!$L:$L,Y$2,'QC Dump (clean)'!$M:$M,"Minor") -> 0 | Z9: =COUNTIFS('QC Dump (clean)'!$A:$A,$C9,'QC Dump (clean)'!$L:$L,Z$2,'QC Dump (clean)'!$M:$M,"Minor") -> 0 | AA9: =COUNTIFS('QC Dump (clean)'!$A:$A,$C9,'QC Dump (clean)'!$L:$L,AA$2,'QC Dump (clean)'!$M:$M,"Minor") -> 0 | AB9: =COUNTIFS('QC Dump (clean)'!$A:$A,$C9,'QC Dump (clean)'!$L:$L,AB$2,'QC Dump (clean)'!$M:$M,"Minor") -> 3 | ... AH9: =COUNTIFS('QC Dump (clean)'!$A:$A,$C9,'QC Dump (clean)'!$L:$L,AH$2,'QC Dump (clean)'!$M:$M,"Minor") -> 0 | AI9: =COUNTIFS('QC Dump (clean)'!$A:$A,$C9,'QC Dump (clean)'!$M:$M,"Unclassified") -> 0 | AJ9: =COUNTIFS('QC Dump (clean)'!$A:$A,$C9,'QC Dump (clean)'!$L:$L,AJ$2,'QC Dump (clean)'!$M:$M,"Unclassified") -> 0 | AK9: =COUNTIFS('QC Dump (clean)'!$A:$A,$C9,'QC Dump (clean)'!$H:$H,"Pending",'QC Dump (clean)'!$M:$M,"<>Not an error") -> 0 | AL9: =COUNTIFS('QC Dump (clean)'!$A:$A,$C9,'QC Dump (clean)'!$H:$H,"Resolved",'QC Dump (clean)'!$M:$M,"<>Not an error") -> 218 | AM9: =COUNTIFS('QC Dump (clean)'!$A:$A,$C9,'QC Dump (clean)'!$H:$H,"Ignore",'QC Dump (clean)'!$M:$M,"<>Not an error") -> 3 | AN9: =SUMIFS('QC Dump (clean)'!$S:$S,'QC Dump (clean)'!$A:$A,$C9) -> 56 | AO9: =IFERROR(AN9/$F9,"") -> 0.78873239 | AP9: =SUMIFS('QC Dump (clean)'!$T:$T,'QC Dump (clean)'!$A:$A,$C9) -> 54 | AQ9: =IFERROR(AP9/$F9,"") -> 0.76056338 | AR9: =SUMIFS('QC Dump (clean)'!$U:$U,'QC Dump (clean)'!$A:$A,$C9) -> 10 | AS9: =IFERROR(AR9/$F9,"") -> 0.14084507
A10: 8 | B10: His Secret Fortune | C10: edb3d0a58ac95f5ef497da24336396e996c6e7e9 | D10: Liebe Nach Vertrag | E10: Aug, Sept | F10: =IFERROR(VLOOKUP($C10,'Show IDs'!$A:$D,4,FALSE)+0,"") -> 200 | G10: =IFERROR(_xlfn.MINIFS('QC Dump (clean)'!$F:$F,'QC Dump (clean)'!$A:$A,$C10,'QC Dump (clean)'!$M:$M,"<>Not an error"),"") -> 2 | H10: =IFERROR(_xlfn.MAXIFS('QC Dump (clean)'!$F:$F,'QC Dump (clean)'!$A:$A,$C10,'QC Dump (clean)'!$M:$M,"<>Not an error"),"") -> 190 | J10: =L10+T10+AI10 -> 209 | K10: =IFERROR(J10/$F10,"") -> 1.045 | L10: =COUNTIFS('QC Dump (clean)'!$A:$A,$C10,'QC Dump (clean)'!$M:$M,"Major") -> 207 | M10: =COUNTIFS('QC Dump (clean)'!$A:$A,$C10,'QC Dump (clean)'!$L:$L,M$2,'QC Dump (clean)'!$M:$M,"Major") -> 0 | N10: =COUNTIFS('QC Dump (clean)'!$A:$A,$C10,'QC Dump (clean)'!$L:$L,N$2,'QC Dump (clean)'!$M:$M,"Major") -> 0 | O10: =COUNTIFS('QC Dump (clean)'!$A:$A,$C10,'QC Dump (clean)'!$L:$L,O$2,'QC Dump (clean)'!$M:$M,"Major") -> 6 | P10: =COUNTIFS('QC Dump (clean)'!$A:$A,$C10,'QC Dump (clean)'!$L:$L,P$2,'QC Dump (clean)'!$M:$M,"Major") -> 118 | Q10: =COUNTIFS('QC Dump (clean)'!$A:$A,$C10,'QC Dump (clean)'!$L:$L,Q$2,'QC Dump (clean)'!$M:$M,"Major") -> 75 | R10: =COUNTIFS('QC Dump (clean)'!$A:$A,$C10,'QC Dump (clean)'!$L:$L,R$2,'QC Dump (clean)'!$M:$M,"Major") -> 2 | S10: =COUNTIFS('QC Dump (clean)'!$A:$A,$C10,'QC Dump (clean)'!$L:$L,S$2,'QC Dump (clean)'!$M:$M,"Major") -> 6 | T10: =COUNTIFS('QC Dump (clean)'!$A:$A,$C10,'QC Dump (clean)'!$M:$M,"Minor") -> 2 | U10: =COUNTIFS('QC Dump (clean)'!$A:$A,$C10,'QC Dump (clean)'!$L:$L,U$2,'QC Dump (clean)'!$M:$M,"Minor") -> 0 | V10: =COUNTIFS('QC Dump (clean)'!$A:$A,$C10,'QC Dump (clean)'!$L:$L,V$2,'QC Dump (clean)'!$M:$M,"Minor") -> 0 | W10: =COUNTIFS('QC Dump (clean)'!$A:$A,$C10,'QC Dump (clean)'!$L:$L,W$2,'QC Dump (clean)'!$M:$M,"Minor") -> 0 | X10: =COUNTIFS('QC Dump (clean)'!$A:$A,$C10,'QC Dump (clean)'!$L:$L,X$2,'QC Dump (clean)'!$M:$M,"Minor") -> 0 | Y10: =COUNTIFS('QC Dump (clean)'!$A:$A,$C10,'QC Dump (clean)'!$L:$L,Y$2,'QC Dump (clean)'!$M:$M,"Minor") -> 0 | Z10: =COUNTIFS('QC Dump (clean)'!$A:$A,$C10,'QC Dump (clean)'!$L:$L,Z$2,'QC Dump (clean)'!$M:$M,"Minor") -> 0 | AA10: =COUNTIFS('QC Dump (clean)'!$A:$A,$C10,'QC Dump (clean)'!$L:$L,AA$2,'QC Dump (clean)'!$M:$M,"Minor") -> 1 | AB10: =COUNTIFS('QC Dump (clean)'!$A:$A,$C10,'QC Dump (clean)'!$L:$L,AB$2,'QC Dump (clean)'!$M:$M,"Minor") -> 0 | ... AH10: =COUNTIFS('QC Dump (clean)'!$A:$A,$C10,'QC Dump (clean)'!$L:$L,AH$2,'QC Dump (clean)'!$M:$M,"Minor") -> 1 | AI10: =COUNTIFS('QC Dump (clean)'!$A:$A,$C10,'QC Dump (clean)'!$M:$M,"Unclassified") -> 0 | AJ10: =COUNTIFS('QC Dump (clean)'!$A:$A,$C10,'QC Dump (clean)'!$L:$L,AJ$2,'QC Dump (clean)'!$M:$M,"Unclassified") -> 0 | AK10: =COUNTIFS('QC Dump (clean)'!$A:$A,$C10,'QC Dump (clean)'!$H:$H,"Pending",'QC Dump (clean)'!$M:$M,"<>Not an error") -> 0 | AL10: =COUNTIFS('QC Dump (clean)'!$A:$A,$C10,'QC Dump (clean)'!$H:$H,"Resolved",'QC Dump (clean)'!$M:$M,"<>Not an error") -> 111 | AM10: =COUNTIFS('QC Dump (clean)'!$A:$A,$C10,'QC Dump (clean)'!$H:$H,"Ignore",'QC Dump (clean)'!$M:$M,"<>Not an error") -> 98 | AN10: =SUMIFS('QC Dump (clean)'!$S:$S,'QC Dump (clean)'!$A:$A,$C10) -> 65 | AO10: =IFERROR(AN10/$F10,"") -> 0.325 | AP10: =SUMIFS('QC Dump (clean)'!$T:$T,'QC Dump (clean)'!$A:$A,$C10) -> 64 | AQ10: =IFERROR(AP10/$F10,"") -> 0.32 | AR10: =SUMIFS('QC Dump (clean)'!$U:$U,'QC Dump (clean)'!$A:$A,$C10) -> 2 | AS10: =IFERROR(AR10/$F10,"") -> 0.01
A11: 9 | B11: Bride of a dragon - BGM + SFX | C11: 2480d4767331b6a7bbbc4f588c705dd813a76a8d | D11: Bride of a Dragon (With BGM-SFX) | E11: Aug, Sept | F11: =IFERROR(VLOOKUP($C11,'Show IDs'!$A:$D,4,FALSE)+0,"") -> 100 | G11: =IFERROR(_xlfn.MINIFS('QC Dump (clean)'!$F:$F,'QC Dump (clean)'!$A:$A,$C11,'QC Dump (clean)'!$M:$M,"<>Not an error"),"") -> 1 | H11: =IFERROR(_xlfn.MAXIFS('QC Dump (clean)'!$F:$F,'QC Dump (clean)'!$A:$A,$C11,'QC Dump (clean)'!$M:$M,"<>Not an error"),"") -> 100 | J11: =L11+T11+AI11 -> 177 | K11: =IFERROR(J11/$F11,"") -> 1.77 | L11: =COUNTIFS('QC Dump (clean)'!$A:$A,$C11,'QC Dump (clean)'!$M:$M,"Major") -> 164 | M11: =COUNTIFS('QC Dump (clean)'!$A:$A,$C11,'QC Dump (clean)'!$L:$L,M$2,'QC Dump (clean)'!$M:$M,"Major") -> 0 | N11: =COUNTIFS('QC Dump (clean)'!$A:$A,$C11,'QC Dump (clean)'!$L:$L,N$2,'QC Dump (clean)'!$M:$M,"Major") -> 0 | O11: =COUNTIFS('QC Dump (clean)'!$A:$A,$C11,'QC Dump (clean)'!$L:$L,O$2,'QC Dump (clean)'!$M:$M,"Major") -> 0 | P11: =COUNTIFS('QC Dump (clean)'!$A:$A,$C11,'QC Dump (clean)'!$L:$L,P$2,'QC Dump (clean)'!$M:$M,"Major") -> 0 | Q11: =COUNTIFS('QC Dump (clean)'!$A:$A,$C11,'QC Dump (clean)'!$L:$L,Q$2,'QC Dump (clean)'!$M:$M,"Major") -> 127 | R11: =COUNTIFS('QC Dump (clean)'!$A:$A,$C11,'QC Dump (clean)'!$L:$L,R$2,'QC Dump (clean)'!$M:$M,"Major") -> 0 | S11: =COUNTIFS('QC Dump (clean)'!$A:$A,$C11,'QC Dump (clean)'!$L:$L,S$2,'QC Dump (clean)'!$M:$M,"Major") -> 37 | T11: =COUNTIFS('QC Dump (clean)'!$A:$A,$C11,'QC Dump (clean)'!$M:$M,"Minor") -> 13 | U11: =COUNTIFS('QC Dump (clean)'!$A:$A,$C11,'QC Dump (clean)'!$L:$L,U$2,'QC Dump (clean)'!$M:$M,"Minor") -> 12 | V11: =COUNTIFS('QC Dump (clean)'!$A:$A,$C11,'QC Dump (clean)'!$L:$L,V$2,'QC Dump (clean)'!$M:$M,"Minor") -> 0 | W11: =COUNTIFS('QC Dump (clean)'!$A:$A,$C11,'QC Dump (clean)'!$L:$L,W$2,'QC Dump (clean)'!$M:$M,"Minor") -> 0 | X11: =COUNTIFS('QC Dump (clean)'!$A:$A,$C11,'QC Dump (clean)'!$L:$L,X$2,'QC Dump (clean)'!$M:$M,"Minor") -> 0 | Y11: =COUNTIFS('QC Dump (clean)'!$A:$A,$C11,'QC Dump (clean)'!$L:$L,Y$2,'QC Dump (clean)'!$M:$M,"Minor") -> 0 | Z11: =COUNTIFS('QC Dump (clean)'!$A:$A,$C11,'QC Dump (clean)'!$L:$L,Z$2,'QC Dump (clean)'!$M:$M,"Minor") -> 0 | AA11: =COUNTIFS('QC Dump (clean)'!$A:$A,$C11,'QC Dump (clean)'!$L:$L,AA$2,'QC Dump (clean)'!$M:$M,"Minor") -> 0 | AB11: =COUNTIFS('QC Dump (clean)'!$A:$A,$C11,'QC Dump (clean)'!$L:$L,AB$2,'QC Dump (clean)'!$M:$M,"Minor") -> 1 | ... AH11: =COUNTIFS('QC Dump (clean)'!$A:$A,$C11,'QC Dump (clean)'!$L:$L,AH$2,'QC Dump (clean)'!$M:$M,"Minor") -> 0 | AI11: =COUNTIFS('QC Dump (clean)'!$A:$A,$C11,'QC Dump (clean)'!$M:$M,"Unclassified") -> 0 | AJ11: =COUNTIFS('QC Dump (clean)'!$A:$A,$C11,'QC Dump (clean)'!$L:$L,AJ$2,'QC Dump (clean)'!$M:$M,"Unclassified") -> 0 | AK11: =COUNTIFS('QC Dump (clean)'!$A:$A,$C11,'QC Dump (clean)'!$H:$H,"Pending",'QC Dump (clean)'!$M:$M,"<>Not an error") -> 177 | AL11: =COUNTIFS('QC Dump (clean)'!$A:$A,$C11,'QC Dump (clean)'!$H:$H,"Resolved",'QC Dump (clean)'!$M:$M,"<>Not an error") -> 0 | AM11: =COUNTIFS('QC Dump (clean)'!$A:$A,$C11,'QC Dump (clean)'!$H:$H,"Ignore",'QC Dump (clean)'!$M:$M,"<>Not an error") -> 0 | AN11: =SUMIFS('QC Dump (clean)'!$S:$S,'QC Dump (clean)'!$A:$A,$C11) -> 69 | AO11: =IFERROR(AN11/$F11,"") -> 0.69 | AP11: =SUMIFS('QC Dump (clean)'!$T:$T,'QC Dump (clean)'!$A:$A,$C11) -> 68 | AQ11: =IFERROR(AP11/$F11,"") -> 0.68 | AR11: =SUMIFS('QC Dump (clean)'!$U:$U,'QC Dump (clean)'!$A:$A,$C11) -> 10 | AS11: =IFERROR(AR11/$F11,"") -> 0.1
A12: 10 | B12: Rise of the Beastmaster | C12: af2d64963a0b2a4ae6e1645ebec6e6220c089166 | D12: Der Aufstieg Des Beastmasters | E12: Aug, Sept | F12: =IFERROR(VLOOKUP($C12,'Show IDs'!$A:$D,4,FALSE)+0,"") -> 75 | G12: =IFERROR(_xlfn.MINIFS('QC Dump (clean)'!$F:$F,'QC Dump (clean)'!$A:$A,$C12,'QC Dump (clean)'!$M:$M,"<>Not an error"),"") -> 1 | H12: =IFERROR(_xlfn.MAXIFS('QC Dump (clean)'!$F:$F,'QC Dump (clean)'!$A:$A,$C12,'QC Dump (clean)'!$M:$M,"<>Not an error"),"") -> 73 | J12: =L12+T12+AI12 -> 171 | K12: =IFERROR(J12/$F12,"") -> 2.28 | L12: =COUNTIFS('QC Dump (clean)'!$A:$A,$C12,'QC Dump (clean)'!$M:$M,"Major") -> 169 | M12: =COUNTIFS('QC Dump (clean)'!$A:$A,$C12,'QC Dump (clean)'!$L:$L,M$2,'QC Dump (clean)'!$M:$M,"Major") -> 0 | N12: =COUNTIFS('QC Dump (clean)'!$A:$A,$C12,'QC Dump (clean)'!$L:$L,N$2,'QC Dump (clean)'!$M:$M,"Major") -> 0 | O12: =COUNTIFS('QC Dump (clean)'!$A:$A,$C12,'QC Dump (clean)'!$L:$L,O$2,'QC Dump (clean)'!$M:$M,"Major") -> 0 | P12: =COUNTIFS('QC Dump (clean)'!$A:$A,$C12,'QC Dump (clean)'!$L:$L,P$2,'QC Dump (clean)'!$M:$M,"Major") -> 0 | Q12: =COUNTIFS('QC Dump (clean)'!$A:$A,$C12,'QC Dump (clean)'!$L:$L,Q$2,'QC Dump (clean)'!$M:$M,"Major") -> 12 | R12: =COUNTIFS('QC Dump (clean)'!$A:$A,$C12,'QC Dump (clean)'!$L:$L,R$2,'QC Dump (clean)'!$M:$M,"Major") -> 0 | S12: =COUNTIFS('QC Dump (clean)'!$A:$A,$C12,'QC Dump (clean)'!$L:$L,S$2,'QC Dump (clean)'!$M:$M,"Major") -> 157 | T12: =COUNTIFS('QC Dump (clean)'!$A:$A,$C12,'QC Dump (clean)'!$M:$M,"Minor") -> 2 | U12: =COUNTIFS('QC Dump (clean)'!$A:$A,$C12,'QC Dump (clean)'!$L:$L,U$2,'QC Dump (clean)'!$M:$M,"Minor") -> 0 | V12: =COUNTIFS('QC Dump (clean)'!$A:$A,$C12,'QC Dump (clean)'!$L:$L,V$2,'QC Dump (clean)'!$M:$M,"Minor") -> 1 | W12: =COUNTIFS('QC Dump (clean)'!$A:$A,$C12,'QC Dump (clean)'!$L:$L,W$2,'QC Dump (clean)'!$M:$M,"Minor") -> 0 | X12: =COUNTIFS('QC Dump (clean)'!$A:$A,$C12,'QC Dump (clean)'!$L:$L,X$2,'QC Dump (clean)'!$M:$M,"Minor") -> 0 | Y12: =COUNTIFS('QC Dump (clean)'!$A:$A,$C12,'QC Dump (clean)'!$L:$L,Y$2,'QC Dump (clean)'!$M:$M,"Minor") -> 0 | Z12: =COUNTIFS('QC Dump (clean)'!$A:$A,$C12,'QC Dump (clean)'!$L:$L,Z$2,'QC Dump (clean)'!$M:$M,"Minor") -> 0 | AA12: =COUNTIFS('QC Dump (clean)'!$A:$A,$C12,'QC Dump (clean)'!$L:$L,AA$2,'QC Dump (clean)'!$M:$M,"Minor") -> 0 | AB12: =COUNTIFS('QC Dump (clean)'!$A:$A,$C12,'QC Dump (clean)'!$L:$L,AB$2,'QC Dump (clean)'!$M:$M,"Minor") -> 1 | ... AH12: =COUNTIFS('QC Dump (clean)'!$A:$A,$C12,'QC Dump (clean)'!$L:$L,AH$2,'QC Dump (clean)'!$M:$M,"Minor") -> 0 | AI12: =COUNTIFS('QC Dump (clean)'!$A:$A,$C12,'QC Dump (clean)'!$M:$M,"Unclassified") -> 0 | AJ12: =COUNTIFS('QC Dump (clean)'!$A:$A,$C12,'QC Dump (clean)'!$L:$L,AJ$2,'QC Dump (clean)'!$M:$M,"Unclassified") -> 0 | AK12: =COUNTIFS('QC Dump (clean)'!$A:$A,$C12,'QC Dump (clean)'!$H:$H,"Pending",'QC Dump (clean)'!$M:$M,"<>Not an error") -> 3 | AL12: =COUNTIFS('QC Dump (clean)'!$A:$A,$C12,'QC Dump (clean)'!$H:$H,"Resolved",'QC Dump (clean)'!$M:$M,"<>Not an error") -> 167 | AM12: =COUNTIFS('QC Dump (clean)'!$A:$A,$C12,'QC Dump (clean)'!$H:$H,"Ignore",'QC Dump (clean)'!$M:$M,"<>Not an error") -> 1 | AN12: =SUMIFS('QC Dump (clean)'!$S:$S,'QC Dump (clean)'!$A:$A,$C12) -> 60 | AO12: =IFERROR(AN12/$F12,"") -> 0.8 | AP12: =SUMIFS('QC Dump (clean)'!$T:$T,'QC Dump (clean)'!$A:$A,$C12) -> 60 | AQ12: =IFERROR(AP12/$F12,"") -> 0.8 | AR12: =SUMIFS('QC Dump (clean)'!$U:$U,'QC Dump (clean)'!$A:$A,$C12) -> 2 | AS12: =IFERROR(AR12/$F12,"") -> 0.026666667
A13: 11 | B13: Ashes to crown | C13: 783983a98fe2613f15770fa78630e1d8965712e2 | D13: Aus Der Asche Zur Krone | E13: Aug | F13: =IFERROR(VLOOKUP($C13,'Show IDs'!$A:$D,4,FALSE)+0,"") -> 80 | G13: =IFERROR(_xlfn.MINIFS('QC Dump (clean)'!$F:$F,'QC Dump (clean)'!$A:$A,$C13,'QC Dump (clean)'!$M:$M,"<>Not an error"),"") -> 1 | H13: =IFERROR(_xlfn.MAXIFS('QC Dump (clean)'!$F:$F,'QC Dump (clean)'!$A:$A,$C13,'QC Dump (clean)'!$M:$M,"<>Not an error"),"") -> 80 | J13: =L13+T13+AI13 -> 141 | K13: =IFERROR(J13/$F13,"") -> 1.7625 | L13: =COUNTIFS('QC Dump (clean)'!$A:$A,$C13,'QC Dump (clean)'!$M:$M,"Major") -> 141 | M13: =COUNTIFS('QC Dump (clean)'!$A:$A,$C13,'QC Dump (clean)'!$L:$L,M$2,'QC Dump (clean)'!$M:$M,"Major") -> 1 | N13: =COUNTIFS('QC Dump (clean)'!$A:$A,$C13,'QC Dump (clean)'!$L:$L,N$2,'QC Dump (clean)'!$M:$M,"Major") -> 0 | O13: =COUNTIFS('QC Dump (clean)'!$A:$A,$C13,'QC Dump (clean)'!$L:$L,O$2,'QC Dump (clean)'!$M:$M,"Major") -> 0 | P13: =COUNTIFS('QC Dump (clean)'!$A:$A,$C13,'QC Dump (clean)'!$L:$L,P$2,'QC Dump (clean)'!$M:$M,"Major") -> 0 | Q13: =COUNTIFS('QC Dump (clean)'!$A:$A,$C13,'QC Dump (clean)'!$L:$L,Q$2,'QC Dump (clean)'!$M:$M,"Major") -> 123 | R13: =COUNTIFS('QC Dump (clean)'!$A:$A,$C13,'QC Dump (clean)'!$L:$L,R$2,'QC Dump (clean)'!$M:$M,"Major") -> 0 | S13: =COUNTIFS('QC Dump (clean)'!$A:$A,$C13,'QC Dump (clean)'!$L:$L,S$2,'QC Dump (clean)'!$M:$M,"Major") -> 17 | T13: =COUNTIFS('QC Dump (clean)'!$A:$A,$C13,'QC Dump (clean)'!$M:$M,"Minor") -> 0 | U13: =COUNTIFS('QC Dump (clean)'!$A:$A,$C13,'QC Dump (clean)'!$L:$L,U$2,'QC Dump (clean)'!$M:$M,"Minor") -> 0 | V13: =COUNTIFS('QC Dump (clean)'!$A:$A,$C13,'QC Dump (clean)'!$L:$L,V$2,'QC Dump (clean)'!$M:$M,"Minor") -> 0 | W13: =COUNTIFS('QC Dump (clean)'!$A:$A,$C13,'QC Dump (clean)'!$L:$L,W$2,'QC Dump (clean)'!$M:$M,"Minor") -> 0 | X13: =COUNTIFS('QC Dump (clean)'!$A:$A,$C13,'QC Dump (clean)'!$L:$L,X$2,'QC Dump (clean)'!$M:$M,"Minor") -> 0 | Y13: =COUNTIFS('QC Dump (clean)'!$A:$A,$C13,'QC Dump (clean)'!$L:$L,Y$2,'QC Dump (clean)'!$M:$M,"Minor") -> 0 | Z13: =COUNTIFS('QC Dump (clean)'!$A:$A,$C13,'QC Dump (clean)'!$L:$L,Z$2,'QC Dump (clean)'!$M:$M,"Minor") -> 0 | AA13: =COUNTIFS('QC Dump (clean)'!$A:$A,$C13,'QC Dump (clean)'!$L:$L,AA$2,'QC Dump (clean)'!$M:$M,"Minor") -> 0 | AB13: =COUNTIFS('QC Dump (clean)'!$A:$A,$C13,'QC Dump (clean)'!$L:$L,AB$2,'QC Dump (clean)'!$M:$M,"Minor") -> 0 | ... AH13: =COUNTIFS('QC Dump (clean)'!$A:$A,$C13,'QC Dump (clean)'!$L:$L,AH$2,'QC Dump (clean)'!$M:$M,"Minor") -> 0 | AI13: =COUNTIFS('QC Dump (clean)'!$A:$A,$C13,'QC Dump (clean)'!$M:$M,"Unclassified") -> 0 | AJ13: =COUNTIFS('QC Dump (clean)'!$A:$A,$C13,'QC Dump (clean)'!$L:$L,AJ$2,'QC Dump (clean)'!$M:$M,"Unclassified") -> 0 | AK13: =COUNTIFS('QC Dump (clean)'!$A:$A,$C13,'QC Dump (clean)'!$H:$H,"Pending",'QC Dump (clean)'!$M:$M,"<>Not an error") -> 1 | AL13: =COUNTIFS('QC Dump (clean)'!$A:$A,$C13,'QC Dump (clean)'!$H:$H,"Resolved",'QC Dump (clean)'!$M:$M,"<>Not an error") -> 139 | AM13: =COUNTIFS('QC Dump (clean)'!$A:$A,$C13,'QC Dump (clean)'!$H:$H,"Ignore",'QC Dump (clean)'!$M:$M,"<>Not an error") -> 1 | AN13: =SUMIFS('QC Dump (clean)'!$S:$S,'QC Dump (clean)'!$A:$A,$C13) -> 52 | AO13: =IFERROR(AN13/$F13,"") -> 0.65 | AP13: =SUMIFS('QC Dump (clean)'!$T:$T,'QC Dump (clean)'!$A:$A,$C13) -> 52 | AQ13: =IFERROR(AP13/$F13,"") -> 0.65 | AR13: =SUMIFS('QC Dump (clean)'!$U:$U,'QC Dump (clean)'!$A:$A,$C13) -> 0 | AS13: =IFERROR(AR13/$F13,"") -> 0
A14: 12 | B14: Mad Vampire Lord's Bride | C14: 9540fa0b0f0a4e67296efcd05e977d34ff2d48cc | D14: Die Braut Des Wahnsinnigen Vampirfürsten | E14: Aug, Sept | F14: =IFERROR(VLOOKUP($C14,'Show IDs'!$A:$D,4,FALSE)+0,"") -> 564 | G14: =IFERROR(_xlfn.MINIFS('QC Dump (clean)'!$F:$F,'QC Dump (clean)'!$A:$A,$C14,'QC Dump (clean)'!$M:$M,"<>Not an error"),"") -> 28 | H14: =IFERROR(_xlfn.MAXIFS('QC Dump (clean)'!$F:$F,'QC Dump (clean)'!$A:$A,$C14,'QC Dump (clean)'!$M:$M,"<>Not an error"),"") -> 563 | J14: =L14+T14+AI14 -> 122 | K14: =IFERROR(J14/$F14,"") -> 0.21631206 | L14: =COUNTIFS('QC Dump (clean)'!$A:$A,$C14,'QC Dump (clean)'!$M:$M,"Major") -> 122 | M14: =COUNTIFS('QC Dump (clean)'!$A:$A,$C14,'QC Dump (clean)'!$L:$L,M$2,'QC Dump (clean)'!$M:$M,"Major") -> 0 | N14: =COUNTIFS('QC Dump (clean)'!$A:$A,$C14,'QC Dump (clean)'!$L:$L,N$2,'QC Dump (clean)'!$M:$M,"Major") -> 0 | O14: =COUNTIFS('QC Dump (clean)'!$A:$A,$C14,'QC Dump (clean)'!$L:$L,O$2,'QC Dump (clean)'!$M:$M,"Major") -> 0 | P14: =COUNTIFS('QC Dump (clean)'!$A:$A,$C14,'QC Dump (clean)'!$L:$L,P$2,'QC Dump (clean)'!$M:$M,"Major") -> 0 | Q14: =COUNTIFS('QC Dump (clean)'!$A:$A,$C14,'QC Dump (clean)'!$L:$L,Q$2,'QC Dump (clean)'!$M:$M,"Major") -> 56 | R14: =COUNTIFS('QC Dump (clean)'!$A:$A,$C14,'QC Dump (clean)'!$L:$L,R$2,'QC Dump (clean)'!$M:$M,"Major") -> 0 | S14: =COUNTIFS('QC Dump (clean)'!$A:$A,$C14,'QC Dump (clean)'!$L:$L,S$2,'QC Dump (clean)'!$M:$M,"Major") -> 66 | T14: =COUNTIFS('QC Dump (clean)'!$A:$A,$C14,'QC Dump (clean)'!$M:$M,"Minor") -> 0 | U14: =COUNTIFS('QC Dump (clean)'!$A:$A,$C14,'QC Dump (clean)'!$L:$L,U$2,'QC Dump (clean)'!$M:$M,"Minor") -> 0 | V14: =COUNTIFS('QC Dump (clean)'!$A:$A,$C14,'QC Dump (clean)'!$L:$L,V$2,'QC Dump (clean)'!$M:$M,"Minor") -> 0 | W14: =COUNTIFS('QC Dump (clean)'!$A:$A,$C14,'QC Dump (clean)'!$L:$L,W$2,'QC Dump (clean)'!$M:$M,"Minor") -> 0 | X14: =COUNTIFS('QC Dump (clean)'!$A:$A,$C14,'QC Dump (clean)'!$L:$L,X$2,'QC Dump (clean)'!$M:$M,"Minor") -> 0 | Y14: =COUNTIFS('QC Dump (clean)'!$A:$A,$C14,'QC Dump (clean)'!$L:$L,Y$2,'QC Dump (clean)'!$M:$M,"Minor") -> 0 | Z14: =COUNTIFS('QC Dump (clean)'!$A:$A,$C14,'QC Dump (clean)'!$L:$L,Z$2,'QC Dump (clean)'!$M:$M,"Minor") -> 0 | AA14: =COUNTIFS('QC Dump (clean)'!$A:$A,$C14,'QC Dump (clean)'!$L:$L,AA$2,'QC Dump (clean)'!$M:$M,"Minor") -> 0 | AB14: =COUNTIFS('QC Dump (clean)'!$A:$A,$C14,'QC Dump (clean)'!$L:$L,AB$2,'QC Dump (clean)'!$M:$M,"Minor") -> 0 | ... AH14: =COUNTIFS('QC Dump (clean)'!$A:$A,$C14,'QC Dump (clean)'!$L:$L,AH$2,'QC Dump (clean)'!$M:$M,"Minor") -> 0 | AI14: =COUNTIFS('QC Dump (clean)'!$A:$A,$C14,'QC Dump (clean)'!$M:$M,"Unclassified") -> 0 | AJ14: =COUNTIFS('QC Dump (clean)'!$A:$A,$C14,'QC Dump (clean)'!$L:$L,AJ$2,'QC Dump (clean)'!$M:$M,"Unclassified") -> 0 | AK14: =COUNTIFS('QC Dump (clean)'!$A:$A,$C14,'QC Dump (clean)'!$H:$H,"Pending",'QC Dump (clean)'!$M:$M,"<>Not an error") -> 0 | AL14: =COUNTIFS('QC Dump (clean)'!$A:$A,$C14,'QC Dump (clean)'!$H:$H,"Resolved",'QC Dump (clean)'!$M:$M,"<>Not an error") -> 117 | AM14: =COUNTIFS('QC Dump (clean)'!$A:$A,$C14,'QC Dump (clean)'!$H:$H,"Ignore",'QC Dump (clean)'!$M:$M,"<>Not an error") -> 5 | AN14: =SUMIFS('QC Dump (clean)'!$S:$S,'QC Dump (clean)'!$A:$A,$C14) -> 51 | AO14: =IFERROR(AN14/$F14,"") -> 0.090425532 | AP14: =SUMIFS('QC Dump (clean)'!$T:$T,'QC Dump (clean)'!$A:$A,$C14) -> 51 | AQ14: =IFERROR(AP14/$F14,"") -> 0.090425532 | AR14: =SUMIFS('QC Dump (clean)'!$U:$U,'QC Dump (clean)'!$A:$A,$C14) -> 0 | AS14: =IFERROR(AR14/$F14,"") -> 0
... A41: 39 | B41: The Outcast's Rise | C41: 7b1f3211cfdfae355799078a0b675eb572c9f339 | D41: Der Aufstieg Des Verstoßenen | E41: Sept | F41: =IFERROR(VLOOKUP($C41,'Show IDs'!$A:$D,4,FALSE)+0,"") -> 130 | G41: =IFERROR(_xlfn.MINIFS('QC Dump (clean)'!$F:$F,'QC Dump (clean)'!$A:$A,$C41,'QC Dump (clean)'!$M:$M,"<>Not an error"),"") -> 50 | H41: =IFERROR(_xlfn.MAXIFS('QC Dump (clean)'!$F:$F,'QC Dump (clean)'!$A:$A,$C41,'QC Dump (clean)'!$M:$M,"<>Not an error"),"") -> 50 | J41: =L41+T41+AI41 -> 1 | K41: =IFERROR(J41/$F41,"") -> 0.0076923077 | L41: =COUNTIFS('QC Dump (clean)'!$A:$A,$C41,'QC Dump (clean)'!$M:$M,"Major") -> 1 | M41: =COUNTIFS('QC Dump (clean)'!$A:$A,$C41,'QC Dump (clean)'!$L:$L,M$2,'QC Dump (clean)'!$M:$M,"Major") -> 0 | N41: =COUNTIFS('QC Dump (clean)'!$A:$A,$C41,'QC Dump (clean)'!$L:$L,N$2,'QC Dump (clean)'!$M:$M,"Major") -> 0 | O41: =COUNTIFS('QC Dump (clean)'!$A:$A,$C41,'QC Dump (clean)'!$L:$L,O$2,'QC Dump (clean)'!$M:$M,"Major") -> 0 | P41: =COUNTIFS('QC Dump (clean)'!$A:$A,$C41,'QC Dump (clean)'!$L:$L,P$2,'QC Dump (clean)'!$M:$M,"Major") -> 0 | Q41: =COUNTIFS('QC Dump (clean)'!$A:$A,$C41,'QC Dump (clean)'!$L:$L,Q$2,'QC Dump (clean)'!$M:$M,"Major") -> 1 | R41: =COUNTIFS('QC Dump (clean)'!$A:$A,$C41,'QC Dump (clean)'!$L:$L,R$2,'QC Dump (clean)'!$M:$M,"Major") -> 0 | S41: =COUNTIFS('QC Dump (clean)'!$A:$A,$C41,'QC Dump (clean)'!$L:$L,S$2,'QC Dump (clean)'!$M:$M,"Major") -> 0 | T41: =COUNTIFS('QC Dump (clean)'!$A:$A,$C41,'QC Dump (clean)'!$M:$M,"Minor") -> 0 | U41: =COUNTIFS('QC Dump (clean)'!$A:$A,$C41,'QC Dump (clean)'!$L:$L,U$2,'QC Dump (clean)'!$M:$M,"Minor") -> 0 | V41: =COUNTIFS('QC Dump (clean)'!$A:$A,$C41,'QC Dump (clean)'!$L:$L,V$2,'QC Dump (clean)'!$M:$M,"Minor") -> 0 | W41: =COUNTIFS('QC Dump (clean)'!$A:$A,$C41,'QC Dump (clean)'!$L:$L,W$2,'QC Dump (clean)'!$M:$M,"Minor") -> 0 | X41: =COUNTIFS('QC Dump (clean)'!$A:$A,$C41,'QC Dump (clean)'!$L:$L,X$2,'QC Dump (clean)'!$M:$M,"Minor") -> 0 | Y41: =COUNTIFS('QC Dump (clean)'!$A:$A,$C41,'QC Dump (clean)'!$L:$L,Y$2,'QC Dump (clean)'!$M:$M,"Minor") -> 0 | Z41: =COUNTIFS('QC Dump (clean)'!$A:$A,$C41,'QC Dump (clean)'!$L:$L,Z$2,'QC Dump (clean)'!$M:$M,"Minor") -> 0 | AA41: =COUNTIFS('QC Dump (clean)'!$A:$A,$C41,'QC Dump (clean)'!$L:$L,AA$2,'QC Dump (clean)'!$M:$M,"Minor") -> 0 | AB41: =COUNTIFS('QC Dump (clean)'!$A:$A,$C41,'QC Dump (clean)'!$L:$L,AB$2,'QC Dump (clean)'!$M:$M,"Minor") -> 0 | ... AH41: =COUNTIFS('QC Dump (clean)'!$A:$A,$C41,'QC Dump (clean)'!$L:$L,AH$2,'QC Dump (clean)'!$M:$M,"Minor") -> 0 | AI41: =COUNTIFS('QC Dump (clean)'!$A:$A,$C41,'QC Dump (clean)'!$M:$M,"Unclassified") -> 0 | AJ41: =COUNTIFS('QC Dump (clean)'!$A:$A,$C41,'QC Dump (clean)'!$L:$L,AJ$2,'QC Dump (clean)'!$M:$M,"Unclassified") -> 0 | AK41: =COUNTIFS('QC Dump (clean)'!$A:$A,$C41,'QC Dump (clean)'!$H:$H,"Pending",'QC Dump (clean)'!$M:$M,"<>Not an error") -> 1 | AL41: =COUNTIFS('QC Dump (clean)'!$A:$A,$C41,'QC Dump (clean)'!$H:$H,"Resolved",'QC Dump (clean)'!$M:$M,"<>Not an error") -> 0 | AM41: =COUNTIFS('QC Dump (clean)'!$A:$A,$C41,'QC Dump (clean)'!$H:$H,"Ignore",'QC Dump (clean)'!$M:$M,"<>Not an error") -> 0 | AN41: =SUMIFS('QC Dump (clean)'!$S:$S,'QC Dump (clean)'!$A:$A,$C41) -> 1 | AO41: =IFERROR(AN41/$F41,"") -> 0.0076923077 | AP41: =SUMIFS('QC Dump (clean)'!$T:$T,'QC Dump (clean)'!$A:$A,$C41) -> 1 | AQ41: =IFERROR(AP41/$F41,"") -> 0.0076923077 | AR41: =SUMIFS('QC Dump (clean)'!$U:$U,'QC Dump (clean)'!$A:$A,$C41) -> 0 | AS41: =IFERROR(AR41/$F41,"") -> 0
B42: Total | F42: =SUM(F3:F41) -> 4226 | J42: =SUM(J3:J41) -> 5838 | K42: =IFERROR(SUMIFS(J3:J41,$F3:$F41,">0")/F42,"") | L42: =SUM(L3:L41) -> 5584 | M42: =SUM(M3:M41) -> 16 | N42: =SUM(N3:N41) -> 49 | O42: =SUM(O3:O41) -> 14 | P42: =SUM(P3:P41) -> 169 | Q42: =SUM(Q3:Q41) -> 1776 | R42: =SUM(R3:R41) -> 8 | S42: =SUM(S3:S41) -> 3552 | ... AN42: =SUM(AN3:AN41) -> 1541 | AO42: =IFERROR(SUMIFS(AN3:AN41,$F3:$F41,">0")/F42,"") | AP42: =SUM(AP3:AP41) -> 1463 | AQ42: =IFERROR(SUMIFS(AP3:AP41,$F3:$F41,">0")/F42,"") | AR42: =SUM(AR3:AR41) -> 209 | AS42: =IFERROR(SUMIFS(AR3:AR41,$F3:$F41,">0")/F42,"")

Sheet Monthly
A1: Severity | B1: Issue type | C1: 2026-08 (Aug) | D1: 2026-09 (Sept) | E1: Total
A2: Major | B2: All Major | C2: =COUNTIFS('QC Dump (clean)'!$M:$M,$A2,'QC Dump (clean)'!$R:$R,C$1) -> 1863 | D2: =COUNTIFS('QC Dump (clean)'!$M:$M,$A2,'QC Dump (clean)'!$R:$R,D$1) -> 3721 | E2: =SUM(C2:D2)
A3: Major | B3: Abrupt cut / Jerk | C3: =COUNTIFS('QC Dump (clean)'!$L:$L,$B3,'QC Dump (clean)'!$M:$M,$A3,'QC Dump (clean)'!$R:$R,C$1) -> 6 | D3: =COUNTIFS('QC Dump (clean)'!$L:$L,$B3,'QC Dump (clean)'!$M:$M,$A3,'QC Dump (clean)'!$R:$R,D$1) -> 10 | E3: =SUM(C3:D3)
A4: Major | B4: Audio quality | C4: =COUNTIFS('QC Dump (clean)'!$L:$L,$B4,'QC Dump (clean)'!$M:$M,$A4,'QC Dump (clean)'!$R:$R,C$1) -> 29 | D4: =COUNTIFS('QC Dump (clean)'!$L:$L,$B4,'QC Dump (clean)'!$M:$M,$A4,'QC Dump (clean)'!$R:$R,D$1) -> 20 | E4: =SUM(C4:D4)
A5: Major | B5: Gramatically incorrect (voa) | C5: =COUNTIFS('QC Dump (clean)'!$L:$L,$B5,'QC Dump (clean)'!$M:$M,$A5,'QC Dump (clean)'!$R:$R,C$1) -> 4 | D5: =COUNTIFS('QC Dump (clean)'!$L:$L,$B5,'QC Dump (clean)'!$M:$M,$A5,'QC Dump (clean)'!$R:$R,D$1) -> 10 | E5: =SUM(C5:D5)
A6: Major | B6: Incorrect name | C6: =COUNTIFS('QC Dump (clean)'!$L:$L,$B6,'QC Dump (clean)'!$M:$M,$A6,'QC Dump (clean)'!$R:$R,C$1) -> 100 | D6: =COUNTIFS('QC Dump (clean)'!$L:$L,$B6,'QC Dump (clean)'!$M:$M,$A6,'QC Dump (clean)'!$R:$R,D$1) -> 69 | E6: =SUM(C6:D6)
A7: Major | B7: Mispronunciation | C7: =COUNTIFS('QC Dump (clean)'!$L:$L,$B7,'QC Dump (clean)'!$M:$M,$A7,'QC Dump (clean)'!$R:$R,C$1) -> 688 | D7: =COUNTIFS('QC Dump (clean)'!$L:$L,$B7,'QC Dump (clean)'!$M:$M,$A7,'QC Dump (clean)'!$R:$R,D$1) -> 1088 | E7: =SUM(C7:D7)
A8: Major | B8: Missed line / Word | C8: =COUNTIFS('QC Dump (clean)'!$L:$L,$B8,'QC Dump (clean)'!$M:$M,$A8,'QC Dump (clean)'!$R:$R,C$1) -> 3 | D8: =COUNTIFS('QC Dump (clean)'!$L:$L,$B8,'QC Dump (clean)'!$M:$M,$A8,'QC Dump (clean)'!$R:$R,D$1) -> 5 | E8: =SUM(C8:D8)
A9: Major | B9: Script error | C9: =COUNTIFS('QC Dump (clean)'!$L:$L,$B9,'QC Dump (clean)'!$M:$M,$A9,'QC Dump (clean)'!$R:$R,C$1) -> 1033 | D9: =COUNTIFS('QC Dump (clean)'!$L:$L,$B9,'QC Dump (clean)'!$M:$M,$A9,'QC Dump (clean)'!$R:$R,D$1) -> 2519 | E9: =SUM(C9:D9)
A10: Minor | B10: All Minor | C10: =COUNTIFS('QC Dump (clean)'!$M:$M,$A10,'QC Dump (clean)'!$R:$R,C$1) -> 72 | D10: =COUNTIFS('QC Dump (clean)'!$M:$M,$A10,'QC Dump (clean)'!$R:$R,D$1) -> 180 | E10: =SUM(C10:D10)
A11: Minor | B11: Acting | C11: =COUNTIFS('QC Dump (clean)'!$L:$L,$B11,'QC Dump (clean)'!$M:$M,$A11,'QC Dump (clean)'!$R:$R,C$1) -> 30 | D11: =COUNTIFS('QC Dump (clean)'!$L:$L,$B11,'QC Dump (clean)'!$M:$M,$A11,'QC Dump (clean)'!$R:$R,D$1) -> 19 | E11: =SUM(C11:D11)
A12: Minor | B12: Audio Regenerated | C12: =COUNTIFS('QC Dump (clean)'!$L:$L,$B12,'QC Dump (clean)'!$M:$M,$A12,'QC Dump (clean)'!$R:$R,C$1) -> 1 | D12: =COUNTIFS('QC Dump (clean)'!$L:$L,$B12,'QC Dump (clean)'!$M:$M,$A12,'QC Dump (clean)'!$R:$R,D$1) -> 5 | E12: =SUM(C12:D12)
A13: Minor | B13: Background noise | C13: =COUNTIFS('QC Dump (clean)'!$L:$L,$B13,'QC Dump (clean)'!$M:$M,$A13,'QC Dump (clean)'!$R:$R,C$1) -> 0 | D13: =COUNTIFS('QC Dump (clean)'!$L:$L,$B13,'QC Dump (clean)'!$M:$M,$A13,'QC Dump (clean)'!$R:$R,D$1) -> 10 | E13: =SUM(C13:D13)
A14: Minor | B14: Breathing noise | C14: =COUNTIFS('QC Dump (clean)'!$L:$L,$B14,'QC Dump (clean)'!$M:$M,$A14,'QC Dump (clean)'!$R:$R,C$1) -> 0 | D14: =COUNTIFS('QC Dump (clean)'!$L:$L,$B14,'QC Dump (clean)'!$M:$M,$A14,'QC Dump (clean)'!$R:$R,D$1) -> 3 | E14: =SUM(C14:D14)
A15: Minor | B15: Clarity of speech | C15: =COUNTIFS('QC Dump (clean)'!$L:$L,$B15,'QC Dump (clean)'!$M:$M,$A15,'QC Dump (clean)'!$R:$R,C$1) -> 0 | D15: =COUNTIFS('QC Dump (clean)'!$L:$L,$B15,'QC Dump (clean)'!$M:$M,$A15,'QC Dump (clean)'!$R:$R,D$1) -> 1 | E15: =SUM(C15:D15)
A16: Minor | B16: Distorted sound | C16: =COUNTIFS('QC Dump (clean)'!$L:$L,$B16,'QC Dump (clean)'!$M:$M,$A16,'QC Dump (clean)'!$R:$R,C$1) -> 0 | D16: =COUNTIFS('QC Dump (clean)'!$L:$L,$B16,'QC Dump (clean)'!$M:$M,$A16,'QC Dump (clean)'!$R:$R,D$1) -> 26 | E16: =SUM(C16:D16)
A17: Minor | B17: Fumble / Mumble | C17: =COUNTIFS('QC Dump (clean)'!$L:$L,$B17,'QC Dump (clean)'!$M:$M,$A17,'QC Dump (clean)'!$R:$R,C$1) -> 1 | D17: =COUNTIFS('QC Dump (clean)'!$L:$L,$B17,'QC Dump (clean)'!$M:$M,$A17,'QC Dump (clean)'!$R:$R,D$1) -> 1 | E17: =SUM(C17:D17)
A18: Minor | B18: Modulation | C18: =COUNTIFS('QC Dump (clean)'!$L:$L,$B18,'QC Dump (clean)'!$M:$M,$A18,'QC Dump (clean)'!$R:$R,C$1) -> 33 | D18: =COUNTIFS('QC Dump (clean)'!$L:$L,$B18,'QC Dump (clean)'!$M:$M,$A18,'QC Dump (clean)'!$R:$R,D$1) -> 52 | E18: =SUM(C18:D18)
A19: Minor | B19: Physical noise of VOA | C19: =COUNTIFS('QC Dump (clean)'!$L:$L,$B19,'QC Dump (clean)'!$M:$M,$A19,'QC Dump (clean)'!$R:$R,C$1) -> 1 | D19: =COUNTIFS('QC Dump (clean)'!$L:$L,$B19,'QC Dump (clean)'!$M:$M,$A19,'QC Dump (clean)'!$R:$R,D$1) -> 3 | E19: =SUM(C19:D19)
A20: Minor | B20: Repetition | C20: =COUNTIFS('QC Dump (clean)'!$L:$L,$B20,'QC Dump (clean)'!$M:$M,$A20,'QC Dump (clean)'!$R:$R,C$1) -> 1 | D20: =COUNTIFS('QC Dump (clean)'!$L:$L,$B20,'QC Dump (clean)'!$M:$M,$A20,'QC Dump (clean)'!$R:$R,D$1) -> 3 | E20: =SUM(C20:D20)
A21: Minor | B21: Sibilance | C21: =COUNTIFS('QC Dump (clean)'!$L:$L,$B21,'QC Dump (clean)'!$M:$M,$A21,'QC Dump (clean)'!$R:$R,C$1) -> 0 | D21: =COUNTIFS('QC Dump (clean)'!$L:$L,$B21,'QC Dump (clean)'!$M:$M,$A21,'QC Dump (clean)'!$R:$R,D$1) -> 1 | E21: =SUM(C21:D21)
A22: Minor | B22: Tone change | C22: =COUNTIFS('QC Dump (clean)'!$L:$L,$B22,'QC Dump (clean)'!$M:$M,$A22,'QC Dump (clean)'!$R:$R,C$1) -> 3 | D22: =COUNTIFS('QC Dump (clean)'!$L:$L,$B22,'QC Dump (clean)'!$M:$M,$A22,'QC Dump (clean)'!$R:$R,D$1) -> 15 | E22: =SUM(C22:D22)
... A24: Minor | B24: Voice processing & editing | C24: =COUNTIFS('QC Dump (clean)'!$L:$L,$B24,'QC Dump (clean)'!$M:$M,$A24,'QC Dump (clean)'!$R:$R,C$1) -> 1 | D24: =COUNTIFS('QC Dump (clean)'!$L:$L,$B24,'QC Dump (clean)'!$M:$M,$A24,'QC Dump (clean)'!$R:$R,D$1) -> 29 | E24: =SUM(C24:D24)
A25: Unclassified | B25: All Unclassified | C25: =COUNTIFS('QC Dump (clean)'!$M:$M,$A25,'QC Dump (clean)'!$R:$R,C$1) -> 0 | D25: =COUNTIFS('QC Dump (clean)'!$M:$M,$A25,'QC Dump (clean)'!$R:$R,D$1) -> 2 | E25: =SUM(C25:D25)
A26: Unclassified | B26: BGM/SFX | C26: =COUNTIFS('QC Dump (clean)'!$L:$L,$B26,'QC Dump (clean)'!$M:$M,$A26,'QC Dump (clean)'!$R:$R,C$1) -> 0 | D26: =COUNTIFS('QC Dump (clean)'!$L:$L,$B26,'QC Dump (clean)'!$M:$M,$A26,'QC Dump (clean)'!$R:$R,D$1) -> 2 | E26: =SUM(C26:D26)
B27: Total errors | C27: =COUNTIFS('QC Dump (clean)'!$M:$M,"<>Not an error",'QC Dump (clean)'!$R:$R,C$1) -> 1935 | D27: =COUNTIFS('QC Dump (clean)'!$M:$M,"<>Not an error",'QC Dump (clean)'!$R:$R,D$1) -> 3903 | E27: =SUM(C27:D27)
B28: Pending | C28: =COUNTIFS('QC Dump (clean)'!$H:$H,"Pending",'QC Dump (clean)'!$M:$M,"<>Not an error",'QC Dump (clean)'!$R:$R,C$1) -> 348 | D28: =COUNTIFS('QC Dump (clean)'!$H:$H,"Pending",'QC Dump (clean)'!$M:$M,"<>Not an error",'QC Dump (clean)'!$R:$R,D$1) -> 1361 | E28: =SUM(C28:D28)

Sheet QC Dump (clean)
A1: Show ID | B1: Show name | C1: DE title | D1: Chapter ID | E1: Episode title | F1: Ep No | G1: Time | H1: Status | I1: Remarks | J1: Category | K1: Issue type (QC tool) | L1: Issue type | M1: Severity | N1: Reviewer | O1: Audio status | P1: Stage | Q1: Logged | R1: Month | S1: Unique ep (error) | T1: Unique ep (Major) | U1: Unique ep (Minor)
A2: 341e3264241ee949f8140798461d1a30ee308d63 | B2: A Sacrifice That Lived | C2: Die Opferbraut Des Bestienkönigs | D2: 706035395dd365ecb054558169485e9e371afbfc | E2: Episode 3: Kians Sturm | F2: 3 | G2: 0:19-0:28 | H2: Resolved | I2: formal -> informal - „Ihr tut ja so, als hättet Ihr sie noch nie gesehen. Ihr seid die Erste Prinzessin von Heilachaten. Ihr müsst das doch jeden Frühling sehen.“ | J2: AI | K2: Script error | L2: Script error | M2: =IFERROR(IF(VLOOKUP(L2,'Quantification'!$A:$B,2,FALSE)&""="","Unclassified",VLOOKUP(L2,'Quantification'!$A:$B,2,FALSE)),"Unclassified") -> Major | N2: frl-denis.sobol@pocketfm.com | O2: Issues found in raw | P2: =IF(OR(O2="Issues found in master",O2="Final master"),"Master",IF(OR(O2="Ready for Master",O2="Issues found in raw",O2="Raw under QC",O2="Issues resolved in raw"),"Raw","-")) -> Raw | Q2: 46280.615 | R2: 2026-09 (Sept) | S2: =IF(M2="Not an error",0,IF(COUNTIFS($A$2:$A2,$A2,$D$2:$D2,$D2,$M$2:$M2,"<>Not an error")=1,1,0)) -> 1 | T2: =IF(M2<>"Major",0,IF(COUNTIFS($A$2:$A2,$A2,$D$2:$D2,$D2,$M$2:$M2,"Major")=1,1,0)) -> 1 | U2: =IF(M2<>"Minor",0,IF(COUNTIFS($A$2:$A2,$A2,$D$2:$D2,$D2,$M$2:$M2,"Minor")=1,1,0)) -> 0
A3: 341e3264241ee949f8140798461d1a30ee308d63 | B3: A Sacrifice That Lived | C3: Die Opferbraut Des Bestienkönigs | D3: 706035395dd365ecb054558169485e9e371afbfc | E3: Episode 3: Kians Sturm | F3: 3 | G3: 1:10-1:13 | H3: Resolved | I3: formal -> informal - „Hat Eure Mutter Euch meinen Namen nicht gesagt?“ | J3: AI | K3: Script error | L3: Script error | M3: =IFERROR(IF(VLOOKUP(L3,'Quantification'!$A:$B,2,FALSE)&""="","Unclassified",VLOOKUP(L3,'Quantification'!$A:$B,2,FALSE)),"Unclassified") -> Major | N3: frl-denis.sobol@pocketfm.com | O3: Issues found in raw | P3: =IF(OR(O3="Issues found in master",O3="Final master"),"Master",IF(OR(O3="Ready for Master",O3="Issues found in raw",O3="Raw under QC",O3="Issues resolved in raw"),"Raw","-")) -> Raw | Q3: 46280.615 | R3: 2026-09 (Sept) | S3: =IF(M3="Not an error",0,IF(COUNTIFS($A$2:$A3,$A3,$D$2:$D3,$D3,$M$2:$M3,"<>Not an error")=1,1,0)) -> 0 | T3: =IF(M3<>"Major",0,IF(COUNTIFS($A$2:$A3,$A3,$D$2:$D3,$D3,$M$2:$M3,"Major")=1,1,0)) -> 0 | U3: =IF(M3<>"Minor",0,IF(COUNTIFS($A$2:$A3,$A3,$D$2:$D3,$D3,$M$2:$M3,"Minor")=1,1,0)) -> 0
A4: 341e3264241ee949f8140798461d1a30ee308d63 | B4: A Sacrifice That Lived | C4: Die Opferbraut Des Bestienkönigs | D4: 706035395dd365ecb054558169485e9e371afbfc | E4: Episode 3: Kians Sturm | F4: 3 | G4: 1:38-1:56 | H4: Resolved | I4: formal -> informal - „Ihr seid unklug“, sagte er, und obwohl sie seine Augen nicht sehen konnte, spürte sie, wie sein Blick sie förmlich durchbohrte. „Ich habe mir die Zeit genommen, Euren Namen zu lernen, Prinzessin Liona von Heilachaten. Ihr jedoch hegt keinerlei Verlangen, meinen zu kennen.“ | J4: AI | K4: Script error | L4: Script error | M4: =IFERROR(IF(VLOOKUP(L4,'Quantification'!$A:$B,2,FALSE)&""="","Unclassified",VLOOKUP(L4,'Quantification'!$A:$B,2,FALSE)),"Unclassified") -> Major | N4: frl-denis.sobol@pocketfm.com | O4: Issues found in raw | P4: =IF(OR(O4="Issues found in master",O4="Final master"),"Master",IF(OR(O4="Ready for Master",O4="Issues found in raw",O4="Raw under QC",O4="Issues resolved in raw"),"Raw","-")) -> Raw | Q4: 46280.615 | R4: 2026-09 (Sept) | S4: =IF(M4="Not an error",0,IF(COUNTIFS($A$2:$A4,$A4,$D$2:$D4,$D4,$M$2:$M4,"<>Not an error")=1,1,0)) -> 0 | T4: =IF(M4<>"Major",0,IF(COUNTIFS($A$2:$A4,$A4,$D$2:$D4,$D4,$M$2:$M4,"Major")=1,1,0)) -> 0 | U4: =IF(M4<>"Minor",0,IF(COUNTIFS($A$2:$A4,$A4,$D$2:$D4,$D4,$M$2:$M4,"Minor")=1,1,0)) -> 0
A5: 341e3264241ee949f8140798461d1a30ee308d63 | B5: A Sacrifice That Lived | C5: Die Opferbraut Des Bestienkönigs | D5: 706035395dd365ecb054558169485e9e371afbfc | E5: Episode 3: Kians Sturm | F5: 3 | G5: 2:13-2:19 | H5: Resolved | I5: formal -> informal - „Kian“, sagte die Bestie mit leiser Stimme. „Unter vier Augen könnt Ihr mich Kian nennen.“ | J5: AI | K5: Script error | L5: Script error | M5: =IFERROR(IF(VLOOKUP(L5,'Quantification'!$A:$B,2,FALSE)&""="","Unclassified",VLOOKUP(L5,'Quantification'!$A:$B,2,FALSE)),"Unclassified") -> Major | N5: frl-denis.sobol@pocketfm.com | O5: Issues found in raw | P5: =IF(OR(O5="Issues found in master",O5="Final master"),"Master",IF(OR(O5="Ready for Master",O5="Issues found in raw",O5="Raw under QC",O5="Issues resolved in raw"),"Raw","-")) -> Raw | Q5: 46280.615 | R5: 2026-09 (Sept) | S5: =IF(M5="Not an error",0,IF(COUNTIFS($A$2:$A5,$A5,$D$2:$D5,$D5,$M$2:$M5,"<>Not an error")=1,1,0)) -> 0 | T5: =IF(M5<>"Major",0,IF(COUNTIFS($A$2:$A5,$A5,$D$2:$D5,$D5,$M$2:$M5,"Major")=1,1,0)) -> 0 | U5: =IF(M5<>"Minor",0,IF(COUNTIFS($A$2:$A5,$A5,$D$2:$D5,$D5,$M$2:$M5,"Minor")=1,1,0)) -> 0
A6: 341e3264241ee949f8140798461d1a30ee308d63 | B6: A Sacrifice That Lived | C6: Die Opferbraut Des Bestienkönigs | D6: 706035395dd365ecb054558169485e9e371afbfc | E6: Episode 3: Kians Sturm | F6: 3 | G6: 2:38-2:42 | H6: Resolved | I6: formal -> informal - „Nur Kian. Ich bin nicht Euer Meister und Ihr seid nicht meine Dienerin“, sagte er schroff. | J6: AI | K6: Script error | L6: Script error | M6: =IFERROR(IF(VLOOKUP(L6,'Quantification'!$A:$B,2,FALSE)&""="","Unclassified",VLOOKUP(L6,'Quantification'!$A:$B,2,FALSE)),"Unclassified") -> Major | N6: frl-denis.sobol@pocketfm.com | O6: Issues found in raw | P6: =IF(OR(O6="Issues found in master",O6="Final master"),"Master",IF(OR(O6="Ready for Master",O6="Issues found in raw",O6="Raw under QC",O6="Issues resolved in raw"),"Raw","-")) -> Raw | Q6: 46280.615 | R6: 2026-09 (Sept) | S6: =IF(M6="Not an error",0,IF(COUNTIFS($A$2:$A6,$A6,$D$2:$D6,$D6,$M$2:$M6,"<>Not an error")=1,1,0)) -> 0 | T6: =IF(M6<>"Major",0,IF(COUNTIFS($A$2:$A6,$A6,$D$2:$D6,$D6,$M$2:$M6,"Major")=1,1,0)) -> 0 | U6: =IF(M6<>"Minor",0,IF(COUNTIFS($A$2:$A6,$A6,$D$2:$D6,$D6,$M$2:$M6,"Minor")=1,1,0)) -> 0
A7: 341e3264241ee949f8140798461d1a30ee308d63 | B7: A Sacrifice That Lived | C7: Die Opferbraut Des Bestienkönigs | D7: 706035395dd365ecb054558169485e9e371afbfc | E7: Episode 3: Kians Sturm | F7: 3 | G7: 2:13-2:20 | H7: Resolved | I7: formal -> informal - „Zwingt mich nicht, mich zu wiederholen. Nennt mich Kian.“ „König.“ „Kian! Seid Ihr taub?“ | J7: AI | K7: Script error | L7: Script error | M7: =IFERROR(IF(VLOOKUP(L7,'Quantification'!$A:$B,2,FALSE)&""="","Unclassified",VLOOKUP(L7,'Quantification'!$A:$B,2,FALSE)),"Unclassified") -> Major | N7: frl-denis.sobol@pocketfm.com | O7: Issues found in raw | P7: =IF(OR(O7="Issues found in master",O7="Final master"),"Master",IF(OR(O7="Ready for Master",O7="Issues found in raw",O7="Raw under QC",O7="Issues resolved in raw"),"Raw","-")) -> Raw | Q7: 46280.615 | R7: 2026-09 (Sept) | S7: =IF(M7="Not an error",0,IF(COUNTIFS($A$2:$A7,$A7,$D$2:$D7,$D7,$M$2:$M7,"<>Not an error")=1,1,0)) -> 0 | T7: =IF(M7<>"Major",0,IF(COUNTIFS($A$2:$A7,$A7,$D$2:$D7,$D7,$M$2:$M7,"Major")=1,1,0)) -> 0 | U7: =IF(M7<>"Minor",0,IF(COUNTIFS($A$2:$A7,$A7,$D$2:$D7,$D7,$M$2:$M7,"Minor")=1,1,0)) -> 0
A8: 341e3264241ee949f8140798461d1a30ee308d63 | B8: A Sacrifice That Lived | C8: Die Opferbraut Des Bestienkönigs | D8: 706035395dd365ecb054558169485e9e371afbfc | E8: Episode 3: Kians Sturm | F8: 3 | G8: 3:35-3:45 | H8: Resolved | I8: formal -> informal - Der Bestienkönig schnaubte. „Die Fahrt in mein Reich dauert zwei Stunden, also macht es Euch bequem. Ich will keine zartbesaitete Prinzessin hören, die sich über Langeweile beschwert.“ | J8: AI | K8: Script error | L8: Script error | M8: =IFERROR(IF(VLOOKUP(L8,'Quantification'!$A:$B,2,FALSE)&""="","Unclassified",VLOOKUP(L8,'Quantification'!$A:$B,2,FALSE)),"Unclassified") -> Major | N8: frl-denis.sobol@pocketfm.com | O8: Issues found in raw | P8: =IF(OR(O8="Issues found in master",O8="Final master"),"Master",IF(OR(O8="Ready for Master",O8="Issues found in raw",O8="Raw under QC",O8="Issues resolved in raw"),"Raw","-")) -> Raw | Q8: 46280.615 | R8: 2026-09 (Sept) | S8: =IF(M8="Not an error",0,IF(COUNTIFS($A$2:$A8,$A8,$D$2:$D8,$D8,$M$2:$M8,"<>Not an error")=1,1,0)) -> 0 | T8: =IF(M8<>"Major",0,IF(COUNTIFS($A$2:$A8,$A8,$D$2:$D8,$D8,$M$2:$M8,"Major")=1,1,0)) -> 0 | U8: =IF(M8<>"Minor",0,IF(COUNTIFS($A$2:$A8,$A8,$D$2:$D8,$D8,$M$2:$M8,"Minor")=1,1,0)) -> 0
A9: 341e3264241ee949f8140798461d1a30ee308d63 | B9: A Sacrifice That Lived | C9: Die Opferbraut Des Bestienkönigs | D9: 706035395dd365ecb054558169485e9e371afbfc | E9: Episode 3: Kians Sturm | F9: 3 | G9: 6:29-6:30 | H9: Resolved | I9: „Was tut Ihr da?“ -> „Was tust du da?“ | J9: AI | K9: Script error | L9: Script error | M9: =IFERROR(IF(VLOOKUP(L9,'Quantification'!$A:$B,2,FALSE)&""="","Unclassified",VLOOKUP(L9,'Quantification'!$A:$B,2,FALSE)),"Unclassified") -> Major | N9: frl-denis.sobol@pocketfm.com | O9: Issues found in raw | P9: =IF(OR(O9="Issues found in master",O9="Final master"),"Master",IF(OR(O9="Ready for Master",O9="Issues found in raw",O9="Raw under QC",O9="Issues resolved in raw"),"Raw","-")) -> Raw | Q9: 46280.615 | R9: 2026-09 (Sept) | S9: =IF(M9="Not an error",0,IF(COUNTIFS($A$2:$A9,$A9,$D$2:$D9,$D9,$M$2:$M9,"<>Not an error")=1,1,0)) -> 0 | T9: =IF(M9<>"Major",0,IF(COUNTIFS($A$2:$A9,$A9,$D$2:$D9,$D9,$M$2:$M9,"Major")=1,1,0)) -> 0 | U9: =IF(M9<>"Minor",0,IF(COUNTIFS($A$2:$A9,$A9,$D$2:$D9,$D9,$M$2:$M9,"Minor")=1,1,0)) -> 0
A10: 341e3264241ee949f8140798461d1a30ee308d63 | B10: A Sacrifice That Lived | C10: Die Opferbraut Des Bestienkönigs | D10: 706035395dd365ecb054558169485e9e371afbfc | E10: Episode 3: Kians Sturm | F10: 3 | G10: 6:56-6:59 | H10: Resolved | I10: formal -> informal - „Ich habe Euch eine Frage gestellt. Was habt Ihr da getan?“ | J10: AI | K10: Script error | L10: Script error | M10: =IFERROR(IF(VLOOKUP(L10,'Quantification'!$A:$B,2,FALSE)&""="","Unclassified",VLOOKUP(L10,'Quantification'!$A:$B,2,FALSE)),"Unclassified") -> Major | N10: frl-denis.sobol@pocketfm.com | O10: Issues found in raw | P10: =IF(OR(O10="Issues found in master",O10="Final master"),"Master",IF(OR(O10="Ready for Master",O10="Issues found in raw",O10="Raw under QC",O10="Issues resolved in raw"),"Raw","-")) -> Raw | Q10: 46280.615 | R10: 2026-09 (Sept) | S10: =IF(M10="Not an error",0,IF(COUNTIFS($A$2:$A10,$A10,$D$2:$D10,$D10,$M$2:$M10,"<>Not an error")=1,1,0)) -> 0 | T10: =IF(M10<>"Major",0,IF(COUNTIFS($A$2:$A10,$A10,$D$2:$D10,$D10,$M$2:$M10,"Major")=1,1,0)) -> 0 | U10: =IF(M10<>"Minor",0,IF(COUNTIFS($A$2:$A10,$A10,$D$2:$D10,$D10,$M$2:$M10,"Minor")=1,1,0)) -> 0
A11: 341e3264241ee949f8140798461d1a30ee308d63 | B11: A Sacrifice That Lived | C11: Die Opferbraut Des Bestienkönigs | D11: 706035395dd365ecb054558169485e9e371afbfc | E11: Episode 3: Kians Sturm | F11: 3 | G11: 7:44-7:47 | H11: Resolved | I11: formal -> informal - „Hat Eure Mutter Euch diese kleinen Tricks beigebracht?“ | J11: AI | K11: Script error | L11: Script error | M11: =IFERROR(IF(VLOOKUP(L11,'Quantification'!$A:$B,2,FALSE)&""="","Unclassified",VLOOKUP(L11,'Quantification'!$A:$B,2,FALSE)),"Unclassified") -> Major | N11: frl-denis.sobol@pocketfm.com | O11: Issues found in raw | P11: =IF(OR(O11="Issues found in master",O11="Final master"),"Master",IF(OR(O11="Ready for Master",O11="Issues found in raw",O11="Raw under QC",O11="Issues resolved in raw"),"Raw","-")) -> Raw | Q11: 46280.615 | R11: 2026-09 (Sept) | S11: =IF(M11="Not an error",0,IF(COUNTIFS($A$2:$A11,$A11,$D$2:$D11,$D11,$M$2:$M11,"<>Not an error")=1,1,0)) -> 0 | T11: =IF(M11<>"Major",0,IF(COUNTIFS($A$2:$A11,$A11,$D$2:$D11,$D11,$M$2:$M11,"Major")=1,1,0)) -> 0 | U11: =IF(M11<>"Minor",0,IF(COUNTIFS($A$2:$A11,$A11,$D$2:$D11,$D11,$M$2:$M11,"Minor")=1,1,0)) -> 0
A12: 341e3264241ee949f8140798461d1a30ee308d63 | B12: A Sacrifice That Lived | C12: Die Opferbraut Des Bestienkönigs | D12: 706035395dd365ecb054558169485e9e371afbfc | E12: Episode 3: Kians Sturm | F12: 3 | G12: 8:15-8:32 | H12: Resolved | I12: formal -> informal - „Den halben Körper aus einer fahrenden Kutsche hängen, dieses fadenscheinige Kleid tragen, dieses Gesicht machen. Sie haben es Euch gut beigebracht“, höhnte Kian. „Ich muss zugeben, die Vorstellung ist überzeugend. Weit besser als bei den meisten anderen, die es bei mir versucht haben.“ | J12: AI | K12: Script error | L12: Script error | M12: =IFERROR(IF(VLOOKUP(L12,'Quantification'!$A:$B,2,FALSE)&""="","Unclassified",VLOOKUP(L12,'Quantification'!$A:$B,2,FALSE)),"Unclassified") -> Major | N12: frl-denis.sobol@pocketfm.com | O12: Issues found in raw | P12: =IF(OR(O12="Issues found in master",O12="Final master"),"Master",IF(OR(O12="Ready for Master",O12="Issues found in raw",O12="Raw under QC",O12="Issues resolved in raw"),"Raw","-")) -> Raw | Q12: 46280.615 | R12: 2026-09 (Sept) | S12: =IF(M12="Not an error",0,IF(COUNTIFS($A$2:$A12,$A12,$D$2:$D12,$D12,$M$2:$M12,"<>Not an error")=1,1,0)) -> 0 | T12: =IF(M12<>"Major",0,IF(COUNTIFS($A$2:$A12,$A12,$D$2:$D12,$D12,$M$2:$M12,"Major")=1,1,0)) -> 0 | U12: =IF(M12<>"Minor",0,IF(COUNTIFS($A$2:$A12,$A12,$D$2:$D12,$D12,$M$2:$M12,"Minor")=1,1,0)) -> 0
A13: 341e3264241ee949f8140798461d1a30ee308d63 | B13: A Sacrifice That Lived | C13: Die Opferbraut Des Bestienkönigs | D13: 706035395dd365ecb054558169485e9e371afbfc | E13: Episode 3: Kians Sturm | F13: 3 | G13: 8:59-9:10 | H13: Resolved | I13: formal -> informal - „Haltet still“, befahl er mit leiser, gefährlicher Stimme. „Ihr braucht diese Spielchen mit mir nicht zu spielen. Ihr seid bereits meine Frau.“ | J13: AI | K13: Script error | L13: Script error | M13: =IFERROR(IF(VLOOKUP(L13,'Quantification'!$A:$B,2,FALSE)&""="","Unclassified",VLOOKUP(L13,'Quantification'!$A:$B,2,FALSE)),"Unclassified") -> Major | N13: frl-denis.sobol@pocketfm.com | O13: Issues found in raw | P13: =IF(OR(O13="Issues found in master",O13="Final master"),"Master",IF(OR(O13="Ready for Master",O13="Issues found in raw",O13="Raw under QC",O13="Issues resolved in raw"),"Raw","-")) -> Raw | Q13: 46280.615 | R13: 2026-09 (Sept) | S13: =IF(M13="Not an error",0,IF(COUNTIFS($A$2:$A13,$A13,$D$2:$D13,$D13,$M$2:$M13,"<>Not an error")=1,1,0)) -> 0 | T13: =IF(M13<>"Major",0,IF(COUNTIFS($A$2:$A13,$A13,$D$2:$D13,$D13,$M$2:$M13,"Major")=1,1,0)) -> 0 | U13: =IF(M13<>"Minor",0,IF(COUNTIFS($A$2:$A13,$A13,$D$2:$D13,$D13,$M$2:$M13,"Minor")=1,1,0)) -> 0
... A20: 341e3264241ee949f8140798461d1a30ee308d63 | B20: A Sacrifice That Lived | C20: Die Opferbraut Des Bestienkönigs | D20: d9c8b084fbacb5286c7e4cb2995c5089520c2fe3 | E20: Episode 6: Ein Sanftes Monster | F20: 6 | G20: 8:17:8:22 | H20: Resolved | I20: formal -> informal - „Euch so behandeln? Was meint Ihr damit?“, fragte Kian, ohne es zu leugnen. | J20: AI | K20: Script error | L20: Script error | M20: =IFERROR(IF(VLOOKUP(L20,'Quantification'!$A:$B,2,FALSE)&""="","Unclassified",VLOOKUP(L20,'Quantification'!$A:$B,2,FALSE)),"Unclassified") -> Major | N20: frl-denis.sobol@pocketfm.com | O20: Issues found in raw | P20: =IF(OR(O20="Issues found in master",O20="Final master"),"Master",IF(OR(O20="Ready for Master",O20="Issues found in raw",O20="Raw under QC",O20="Issues resolved in raw"),"Raw","-")) -> Raw | Q20: 46280.615 | R20: 2026-09 (Sept) | S20: =IF(M20="Not an error",0,IF(COUNTIFS($A$2:$A20,$A20,$D$2:$D20,$D20,$M$2:$M20,"<>Not an error")=1,1,0)) -> 0 | T20: =IF(M20<>"Major",0,IF(COUNTIFS($A$2:$A20,$A20,$D$2:$D20,$D20,$M$2:$M20,"Major")=1,1,0)) -> 0 | U20: =IF(M20<>"Minor",0,IF(COUNTIFS($A$2:$A20,$A20,$D$2:$D20,$D20,$M$2:$M20,"Minor")=1,1,0)) -> 0
A21: 341e3264241ee949f8140798461d1a30ee308d63 | B21: A Sacrifice That Lived | C21: Die Opferbraut Des Bestienkönigs | D21: 14992cae62cf25109776b4b680b8e17565bfccbd | E21: Episode 7: Unerwartetes Vergnügen | F21: 7 | H21: Ignore | I21: There seems to be a persistent issue regarding the use of formal/informal speech. Up to this point, Liona, the female protagonist, has only addressed Kian formally, but for the first time in Ep. 7, she addresses him informally. Kian, the male protagonist, also seems to switch back and forth between formal and informal address: Ep. 2: informal; Ep. 3: formal; Ep. 4: informal; Ep. 5: formal; Ep. 6: formal; Ep. 7: both address each other informally. I’m assuming this inconsistency will continue, so I’ll need to make a decision on which form to stick to for consistency. Given that they both use the informal form in Ep. 7, it might make sense to have them address each other informally from this point onward. | J21: AI | K21: Script error | L21: Script error | M21: =IFERROR(IF(VLOOKUP(L21,'Quantification'!$A:$B,2,FALSE)&""="","Unclassified",VLOOKUP(L21,'Quantification'!$A:$B,2,FALSE)),"Unclassified") -> Major | N21: frl-denis.sobol@pocketfm.com | O21: Issues found in raw | P21: =IF(OR(O21="Issues found in master",O21="Final master"),"Master",IF(OR(O21="Ready for Master",O21="Issues found in raw",O21="Raw under QC",O21="Issues resolved in raw"),"Raw","-")) -> Raw | Q21: 46280.615 | R21: 2026-09 (Sept) | S21: =IF(M21="Not an error",0,IF(COUNTIFS($A$2:$A21,$A21,$D$2:$D21,$D21,$M$2:$M21,"<>Not an error")=1,1,0)) -> 1 | T21: =IF(M21<>"Major",0,IF(COUNTIFS($A$2:$A21,$A21,$D$2:$D21,$D21,$M$2:$M21,"Major")=1,1,0)) -> 1 | U21: =IF(M21<>"Minor",0,IF(COUNTIFS($A$2:$A21,$A21,$D$2:$D21,$D21,$M$2:$M21,"Minor")=1,1,0)) -> 0
A22: 341e3264241ee949f8140798461d1a30ee308d63 | B22: A Sacrifice That Lived | C22: Die Opferbraut Des Bestienkönigs | D22: d29c1a304f7523955531b2f75dd0905c462b63b3 | E22: Episode 12: Ein Blutbeflecktes Biest | F22: 12 | G22: 2:32-3:54 | H22: Resolved | I22: kian is suddenly given a surname and referred to as "kian sturm" in this episode, this is the first time and there is no explanation or reason provided. I suspect that this is a mistake but I don't know for sure | J22: AI | K22: Script error | L22: Script error | M22: =IFERROR(IF(VLOOKUP(L22,'Quantification'!$A:$B,2,FALSE)&""="","Unclassified",VLOOKUP(L22,'Quantification'!$A:$B,2,FALSE)),"Unclassified") -> Major | N22: frl-denis.sobol@pocketfm.com | O22: Issues found in raw | P22: =IF(OR(O22="Issues found in master",O22="Final master"),"Master",IF(OR(O22="Ready for Master",O22="Issues found in raw",O22="Raw under QC",O22="Issues resolved in raw"),"Raw","-")) -> Raw | Q22: 46280.616 | R22: 2026-09 (Sept) | S22: =IF(M22="Not an error",0,IF(COUNTIFS($A$2:$A22,$A22,$D$2:$D22,$D22,$M$2:$M22,"<>Not an error")=1,1,0)) -> 1 | T22: =IF(M22<>"Major",0,IF(COUNTIFS($A$2:$A22,$A22,$D$2:$D22,$D22,$M$2:$M22,"Major")=1,1,0)) -> 1 | U22: =IF(M22<>"Minor",0,IF(COUNTIFS($A$2:$A22,$A22,$D$2:$D22,$D22,$M$2:$M22,"Minor")=1,1,0)) -> 0
A23: 341e3264241ee949f8140798461d1a30ee308d63 | B23: A Sacrifice That Lived | C23: Die Opferbraut Des Bestienkönigs | D23: d29c1a304f7523955531b2f75dd0905c462b63b3 | E23: Episode 12: Ein Blutbeflecktes Biest | F23: 12 | G23: 2:32-3:54 | H23: Resolved | I23: kian is suddenly given a surname and referred to as "kian sturm" in this episode, this is the first time and there is no explanation or reason provided. I suspect that this is a mistake but I don't know for sure - "Kian Sturm hatte ihr zwar gesagt, dass das Bestienvolk Stärke über alles stellte, aber sie hatte sich nie vorstellen können, dass es so extrem war. „Wenn ihr also einen Fehler macht, würde er euch dann töten?“, fragte Liona. Hayley und Bailey sahen sich an. „Wir sind uns nicht sicher, Prinzessin“, antwortete Hayley. „Aber selbst wenn Seine Majestät uns nicht tötet, tun es unsere Eltern, sobald wir entlassen und in unser Dorf zurückgeschickt werden. Dafür, dass wir darin versagt hätten, Seiner Majestät zu dienen.“ „Wurdet ihr gezwungen, hier zu arbeiten, oder habt ihr euch freiwillig gemeldet?“ „Natürlich haben wir uns freiwillig gemeldet, Prinzessin!“, erwiderte Hayley und ihre Angst wich einem Anflug von Stolz. „Es ist eine riesige Ehre, Seiner Majestät dienen zu dürfen. Uns wurde beigebracht, dass Stärke alles ist. Solange er unbesiegbar ist, werden wir ihm für den Rest unseres Lebens dienen!“ Liona fand das faszinierend, aber auch erschreckend. Was, wenn Kian Sturm verletzt würde? Oder wenn er zu alt zum Kämpfen wäre? Würden sie ihn dann einfach töten? Liona erinnerte sich an ihren Vater, der jahrzehntelang mächtig und ungeschlagen gewesen war. Und am Ende hatte Kian Sturm ihn getötet." | J23: AI | K23: Script error | L23: Script error | M23: =IFERROR(IF(VLOOKUP(L23,'Quantification'!$A:$B,2,FALSE)&""="","Unclassified",VLOOKUP(L23,'Quantification'!$A:$B,2,FALSE)),"Unclassified") -> Major | N23: frl-denis.sobol@pocketfm.com | O23: Issues found in raw | P23: =IF(OR(O23="Issues found in master",O23="Final master"),"Master",IF(OR(O23="Ready for Master",O23="Issues found in raw",O23="Raw under QC",O23="Issues resolved in raw"),"Raw","-")) -> Raw | Q23: 46280.616 | R23: 2026-09 (Sept) | S23: =IF(M23="Not an error",0,IF(COUNTIFS($A$2:$A23,$A23,$D$2:$D23,$D23,$M$2:$M23,"<>Not an error")=1,1,0)) -> 0 | T23: =IF(M23<>"Major",0,IF(COUNTIFS($A$2:$A23,$A23,$D$2:$D23,$D23,$M$2:$M23,"Major")=1,1,0)) -> 0 | U23: =IF(M23<>"Minor",0,IF(COUNTIFS($A$2:$A23,$A23,$D$2:$D23,$D23,$M$2:$M23,"Minor")=1,1,0)) -> 0
A24: 341e3264241ee949f8140798461d1a30ee308d63 | B24: A Sacrifice That Lived | C24: Die Opferbraut Des Bestienkönigs | D24: 70b139de96f5c7baf85c950d2b2bfa60231df2d8 | E24: Episode 13: Bring Sie Mit Einem Kuss Zum Schweigen | F24: 13 | G24: 1:35-1:40 | H24: Resolved | I24: „Kian“, sagte sie sanft. „Seid Ihr verletzt?“ -> „Kian“, sagte sie sanft. „Bist du verletzt?“ | J24: AI | K24: Script error | L24: Script error | M24: =IFERROR(IF(VLOOKUP(L24,'Quantification'!$A:$B,2,FALSE)&""="","Unclassified",VLOOKUP(L24,'Quantification'!$A:$B,2,FALSE)),"Unclassified") -> Major | N24: frl-denis.sobol@pocketfm.com | O24: Issues found in raw | P24: =IF(OR(O24="Issues found in master",O24="Final master"),"Master",IF(OR(O24="Ready for Master",O24="Issues found in raw",O24="Raw under QC",O24="Issues resolved in raw"),"Raw","-")) -> Raw | Q24: 46280.616 | R24: 2026-09 (Sept) | S24: =IF(M24="Not an error",0,IF(COUNTIFS($A$2:$A24,$A24,$D$2:$D24,$D24,$M$2:$M24,"<>Not an error")=1,1,0)) -> 1 | T24: =IF(M24<>"Major",0,IF(COUNTIFS($A$2:$A24,$A24,$D$2:$D24,$D24,$M$2:$M24,"Major")=1,1,0)) -> 1 | U24: =IF(M24<>"Minor",0,IF(COUNTIFS($A$2:$A24,$A24,$D$2:$D24,$D24,$M$2:$M24,"Minor")=1,1,0)) -> 0
A25: 341e3264241ee949f8140798461d1a30ee308d63 | B25: A Sacrifice That Lived | C25: Die Opferbraut Des Bestienkönigs | D25: 70b139de96f5c7baf85c950d2b2bfa60231df2d8 | E25: Episode 13: Bring Sie Mit Einem Kuss Zum Schweigen | F25: 13 | G25: 2:36-2:49 | H25: Resolved | I25: „Oh. Verzeihung“, murmelte Liona. „Ich dachte nur, Ihr seht aus, als hättet Ihr große Schmerzen. Man kann es in Eurem Gesicht ablesen. Aber vielleicht interpretiere ich auch zu viel hinein.“ -> „Oh. verzeih mir“, murmelte Liona. „Ich dachte nur, du siehst aus, als hättest du große Schmerzen. Man kann es in deinem Gesicht ablesen. Aber vielleicht interpretiere ich auch zu viel hinein.“ | J25: AI | K25: Script error | L25: Script error | M25: =IFERROR(IF(VLOOKUP(L25,'Quantification'!$A:$B,2,FALSE)&""="","Unclassified",VLOOKUP(L25,'Quantification'!$A:$B,2,FALSE)),"Unclassified") -> Major | N25: frl-denis.sobol@pocketfm.com | O25: Issues found in raw | P25: =IF(OR(O25="Issues found in master",O25="Final master"),"Master",IF(OR(O25="Ready for Master",O25="Issues found in raw",O25="Raw under QC",O25="Issues resolved in raw"),"Raw","-")) -> Raw | Q25: 46280.616 | R25: 2026-09 (Sept) | S25: =IF(M25="Not an error",0,IF(COUNTIFS($A$2:$A25,$A25,$D$2:$D25,$D25,$M$2:$M25,"<>Not an error")=1,1,0)) -> 0 | T25: =IF(M25<>"Major",0,IF(COUNTIFS($A$2:$A25,$A25,$D$2:$D25,$D25,$M$2:$M25,"Major")=1,1,0)) -> 0 | U25: =IF(M25<>"Minor",0,IF(COUNTIFS($A$2:$A25,$A25,$D$2:$D25,$D25,$M$2:$M25,"Minor")=1,1,0)) -> 0
A26: 341e3264241ee949f8140798461d1a30ee308d63 | B26: A Sacrifice That Lived | C26: Die Opferbraut Des Bestienkönigs | D26: 70b139de96f5c7baf85c950d2b2bfa60231df2d8 | E26: Episode 13: Bring Sie Mit Einem Kuss Zum Schweigen | F26: 13 | G26: 3:16-3:25 | H26: Resolved | I26: „Ich wurde gesandt, um Euch zu dienen. Wenn ich irgendetwas tun kann, damit es Euch besser geht, sagt es mir bitte. Ich werde alles tun, was nötig ist!“ -> „Ich wurde gesandt, um dir zu dienen. Wenn ich irgendetwas tun kann, damit es dir besser geht, sag es mir bitte. Ich werde alles tun, was nötig ist!“ | J26: AI | K26: Script error | L26: Script error | M26: =IFERROR(IF(VLOOKUP(L26,'Quantification'!$A:$B,2,FALSE)&""="","Unclassified",VLOOKUP(L26,'Quantification'!$A:$B,2,FALSE)),"Unclassified") -> Major | N26: frl-denis.sobol@pocketfm.com | O26: Issues found in raw | P26: =IF(OR(O26="Issues found in master",O26="Final master"),"Master",IF(OR(O26="Ready for Master",O26="Issues found in raw",O26="Raw under QC",O26="Issues resolved in raw"),"Raw","-")) -> Raw | Q26: 46280.616 | R26: 2026-09 (Sept) | S26: =IF(M26="Not an error",0,IF(COUNTIFS($A$2:$A26,$A26,$D$2:$D26,$D26,$M$2:$M26,"<>Not an error")=1,1,0)) -> 0 | T26: =IF(M26<>"Major",0,IF(COUNTIFS($A$2:$A26,$A26,$D$2:$D26,$D26,$M$2:$M26,"Major")=1,1,0)) -> 0 | U26: =IF(M26<>"Minor",0,IF(COUNTIFS($A$2:$A26,$A26,$D$2:$D26,$D26,$M$2:$M26,"Minor")=1,1,0)) -> 0
A27: 341e3264241ee949f8140798461d1a30ee308d63 | B27: A Sacrifice That Lived | C27: Die Opferbraut Des Bestienkönigs | D27: 70b139de96f5c7baf85c950d2b2bfa60231df2d8 | E27: Episode 13: Bring Sie Mit Einem Kuss Zum Schweigen | F27: 13 | G27: 4:47-4:57 | H27: Resolved | I27: formal speech -> informal speech (euch -> dich) - „Aber ich will es“, beharrte Liona mit zitternder, aber fester Stimme. „Ich will von Nutzen sein. Ich will nur etwas tun, das Euch vielleicht glücklich macht.“ | J27: AI | K27: Script error | L27: Script error | M27: =IFERROR(IF(VLOOKUP(L27,'Quantification'!$A:$B,2,FALSE)&""="","Unclassified",VLOOKUP(L27,'Quantification'!$A:$B,2,FALSE)),"Unclassified") -> Major | N27: frl-denis.sobol@pocketfm.com | O27: Issues found in raw | P27: =IF(OR(O27="Issues found in master",O27="Final master"),"Master",IF(OR(O27="Ready for Master",O27="Issues found in raw",O27="Raw under QC",O27="Issues resolved in raw"),"Raw","-")) -> Raw | Q27: 46280.616 | R27: 2026-09 (Sept) | S27: =IF(M27="Not an error",0,IF(COUNTIFS($A$2:$A27,$A27,$D$2:$D27,$D27,$M$2:$M27,"<>Not an error")=1,1,0)) -> 0 | T27: =IF(M27<>"Major",0,IF(COUNTIFS($A$2:$A27,$A27,$D$2:$D27,$D27,$M$2:$M27,"Major")=1,1,0)) -> 0 | U27: =IF(M27<>"Minor",0,IF(COUNTIFS($A$2:$A27,$A27,$D$2:$D27,$D27,$M$2:$M27,"Minor")=1,1,0)) -> 0
A28: 341e3264241ee949f8140798461d1a30ee308d63 | B28: A Sacrifice That Lived | C28: Die Opferbraut Des Bestienkönigs | D28: 70b139de96f5c7baf85c950d2b2bfa60231df2d8 | E28: Episode 13: Bring Sie Mit Einem Kuss Zum Schweigen | F28: 13 | G28: 6:09-6:14 | H28: Resolved | I28: formal -> informal (eure -> deine) - „Wenn mein Leben Eure Schmerzen lindern kann, dann bin ich bereit zu sterben.“ | J28: AI | K28: Script error | L28: Script error | M28: =IFERROR(IF(VLOOKUP(L28,'Quantification'!$A:$B,2,FALSE)&""="","Unclassified",VLOOKUP(L28,'Quantification'!$A:$B,2,FALSE)),"Unclassified") -> Major | N28: frl-denis.sobol@pocketfm.com | O28: Issues found in raw | P28: =IF(OR(O28="Issues found in master",O28="Final master"),"Master",IF(OR(O28="Ready for Master",O28="Issues found in raw",O28="Raw under QC",O28="Issues resolved in raw"),"Raw","-")) -> Raw | Q28: 46280.616 | R28: 2026-09 (Sept) | S28: =IF(M28="Not an error",0,IF(COUNTIFS($A$2:$A28,$A28,$D$2:$D28,$D28,$M$2:$M28,"<>Not an error")=1,1,0)) -> 0 | T28: =IF(M28<>"Major",0,IF(COUNTIFS($A$2:$A28,$A28,$D$2:$D28,$D28,$M$2:$M28,"Major")=1,1,0)) -> 0 | U28: =IF(M28<>"Minor",0,IF(COUNTIFS($A$2:$A28,$A28,$D$2:$D28,$D28,$M$2:$M28,"Minor")=1,1,0)) -> 0
A29: 341e3264241ee949f8140798461d1a30ee308d63 | B29: A Sacrifice That Lived | C29: Die Opferbraut Des Bestienkönigs | D29: 70b139de96f5c7baf85c950d2b2bfa60231df2d8 | E29: Episode 13: Bring Sie Mit Einem Kuss Zum Schweigen | F29: 13 | G29: 7:15-7:18 | H29: Resolved | I29: formal -> informal - „Wenn Euer Fluch mein Leben fordert, werde ich.“ | J29: AI | K29: Script error | L29: Script error | M29: =IFERROR(IF(VLOOKUP(L29,'Quantification'!$A:$B,2,FALSE)&""="","Unclassified",VLOOKUP(L29,'Quantification'!$A:$B,2,FALSE)),"Unclassified") -> Major | N29: frl-denis.sobol@pocketfm.com | O29: Issues found in raw | P29: =IF(OR(O29="Issues found in master",O29="Final master"),"Master",IF(OR(O29="Ready for Master",O29="Issues found in raw",O29="Raw under QC",O29="Issues resolved in raw"),"Raw","-")) -> Raw | Q29: 46280.616 | R29: 2026-09 (Sept) | S29: =IF(M29="Not an error",0,IF(COUNTIFS($A$2:$A29,$A29,$D$2:$D29,$D29,$M$2:$M29,"<>Not an error")=1,1,0)) -> 0 | T29: =IF(M29<>"Major",0,IF(COUNTIFS($A$2:$A29,$A29,$D$2:$D29,$D29,$M$2:$M29,"Major")=1,1,0)) -> 0 | U29: =IF(M29<>"Minor",0,IF(COUNTIFS($A$2:$A29,$A29,$D$2:$D29,$D29,$M$2:$M29,"Minor")=1,1,0)) -> 0
A30: 341e3264241ee949f8140798461d1a30ee308d63 | B30: A Sacrifice That Lived | C30: Die Opferbraut Des Bestienkönigs | D30: 70b139de96f5c7baf85c950d2b2bfa60231df2d8 | E30: Episode 13: Bring Sie Mit Einem Kuss Zum Schweigen | F30: 13 | G30: 7:30-7:32 | H30: Resolved | I30: formal -> informal - „Wartet, Kian, ich.“ | J30: AI | K30: Script error | L30: Script error | M30: =IFERROR(IF(VLOOKUP(L30,'Quantification'!$A:$B,2,FALSE)&""="","Unclassified",VLOOKUP(L30,'Quantification'!$A:$B,2,FALSE)),"Unclassified") -> Major | N30: frl-denis.sobol@pocketfm.com | O30: Issues found in raw | P30: =IF(OR(O30="Issues found in master",O30="Final master"),"Master",IF(OR(O30="Ready for Master",O30="Issues found in raw",O30="Raw under QC",O30="Issues resolved in raw"),"Raw","-")) -> Raw | Q30: 46280.616 | R30: 2026-09 (Sept) | S30: =IF(M30="Not an error",0,IF(COUNTIFS($A$2:$A30,$A30,$D$2:$D30,$D30,$M$2:$M30,"<>Not an error")=1,1,0)) -> 0 | T30: =IF(M30<>"Major",0,IF(COUNTIFS($A$2:$A30,$A30,$D$2:$D30,$D30,$M$2:$M30,"Major")=1,1,0)) -> 0 | U30: =IF(M30<>"Minor",0,IF(COUNTIFS($A$2:$A30,$A30,$D$2:$D30,$D30,$M$2:$M30,"Minor")=1,1,0)) -> 0
A31: 341e3264241ee949f8140798461d1a30ee308d63 | B31: A Sacrifice That Lived | C31: Die Opferbraut Des Bestienkönigs | D31: 129ec7662bed20adaa4b69eca5980495cc84226b | E31: Episode 14: Du Kannst Deinem Schicksal Nicht Entkommen | F31: 14 | G31: 9:08-9:14 | H31: Resolved | I31: „Einschließlich der Tatsache, dass Ihr nach mir weitere Gemahlinnen haben werdet?“, fragte Liona mit leiser Stimme. -> „Einschließlich der Tatsache, dass du nach mir weitere Gemahlinnen haben wirst?“, fragte Liona mit leiser Stimme. | J31: AI | K31: Script error | L31: Script error | M31: =IFERROR(IF(VLOOKUP(L31,'Quantification'!$A:$B,2,FALSE)&""="","Unclassified",VLOOKUP(L31,'Quantification'!$A:$B,2,FALSE)),"Unclassified") -> Major | N31: frl-denis.sobol@pocketfm.com | O31: Issues found in raw | P31: =IF(OR(O31="Issues found in master",O31="Final master"),"Master",IF(OR(O31="Ready for Master",O31="Issues found in raw",O31="Raw under QC",O31="Issues resolved in raw"),"Raw","-")) -> Raw | Q31: 46280.616 | R31: 2026-09 (Sept) | S31: =IF(M31="Not an error",0,IF(COUNTIFS($A$2:$A31,$A31,$D$2:$D31,$D31,$M$2:$M31,"<>Not an error")=1,1,0)) -> 1 | T31: =IF(M31<>"Major",0,IF(COUNTIFS($A$2:$A31,$A31,$D$2:$D31,$D31,$M$2:$M31,"Major")=1,1,0)) -> 1 | U31: =IF(M31<>"Minor",0,IF(COUNTIFS($A$2:$A31,$A31,$D$2:$D31,$D31,$M$2:$M31,"Minor")=1,1,0)) -> 0
A32: 341e3264241ee949f8140798461d1a30ee308d63 | B32: A Sacrifice That Lived | C32: Die Opferbraut Des Bestienkönigs | D32: 129ec7662bed20adaa4b69eca5980495cc84226b | E32: Episode 14: Du Kannst Deinem Schicksal Nicht Entkommen | F32: 14 | G32: 9:41-9:51 | H32: Resolved | I32: „Ich habe von der Edlen Kira gehört, dass Ihr Frauen aus den Ländern heiraten müsst, die Ihr erobert. Ich bin sicher, sie sind alle schöner als ich. Also ich.“ -> „Ich habe von der Edlen Kira gehört, dass du Frauen aus den Ländern heiraten musst, die du eroberst. Ich bin sicher, sie sind alle schöner als ich. Also ich.“ | J32: AI | K32: Script error | L32: Script error | M32: =IFERROR(IF(VLOOKUP(L32,'Quantification'!$A:$B,2,FALSE)&""="","Unclassified",VLOOKUP(L32,'Quantification'!$A:$B,2,FALSE)),"Unclassified") -> Major | N32: frl-denis.sobol@pocketfm.com | O32: Issues found in raw | P32: =IF(OR(O32="Issues found in master",O32="Final master"),"Master",IF(OR(O32="Ready for Master",O32="Issues found in raw",O32="Raw under QC",O32="Issues resolved in raw"),"Raw","-")) -> Raw | Q32: 46280.616 | R32: 2026-09 (Sept) | S32: =IF(M32="Not an error",0,IF(COUNTIFS($A$2:$A32,$A32,$D$2:$D32,$D32,$M$2:$M32,"<>Not an error")=1,1,0)) -> 0 | T32: =IF(M32<>"Major",0,IF(COUNTIFS($A$2:$A32,$A32,$D$2:$D32,$D32,$M$2:$M32,"Major")=1,1,0)) -> 0 | U32: =IF(M32<>"Minor",0,IF(COUNTIFS($A$2:$A32,$A32,$D$2:$D32,$D32,$M$2:$M32,"Minor")=1,1,0)) -> 0
A33: 341e3264241ee949f8140798461d1a30ee308d63 | B33: A Sacrifice That Lived | C33: Die Opferbraut Des Bestienkönigs | D33: c67838f57aba40d8ab184a0a93a780c8012b0af0 | E33: Episode 22: Das Licht Der Göttin | F33: 22 | G33: 9:53-10:12 | H33: Resolved | I33: die katzenähnlichen Zofen -> die Katzenmenschen-Zofen | J33: AI | K33: Script error | L33: Script error | M33: =IFERROR(IF(VLOOKUP(L33,'Quantification'!$A:$B,2,FALSE)&""="","Unclassified",VLOOKUP(L33,'Quantification'!$A:$B,2,FALSE)),"Unclassified") -> Major | N33: frl-denis.sobol@pocketfm.com | O33: Issues found in raw | P33: =IF(OR(O33="Issues found in master",O33="Final master"),"Master",IF(OR(O33="Ready for Master",O33="Issues found in raw",O33="Raw under QC",O33="Issues resolved in raw"),"Raw","-")) -> Raw | Q33: 46280.616 | R33: 2026-09 (Sept) | S33: =IF(M33="Not an error",0,IF(COUNTIFS($A$2:$A33,$A33,$D$2:$D33,$D33,$M$2:$M33,"<>Not an error")=1,1,0)) -> 1 | T33: =IF(M33<>"Major",0,IF(COUNTIFS($A$2:$A33,$A33,$D$2:$D33,$D33,$M$2:$M33,"Major")=1,1,0)) -> 1 | U33: =IF(M33<>"Minor",0,IF(COUNTIFS($A$2:$A33,$A33,$D$2:$D33,$D33,$M$2:$M33,"Minor")=1,1,0)) -> 0
... A37: 341e3264241ee949f8140798461d1a30ee308d63 | B37: A Sacrifice That Lived | C37: Die Opferbraut Des Bestienkönigs | D37: f58ca7aee71d9f6981fdb10e860239eff0311afc | E37: Episode 29: Haben Wir Uns Schon Einmal Getroffen | F37: 29 | G37: 7:28-11:05 | H37: Resolved | I37: Redano -> Ron (Wäre es nicht...) | J37: VOA | K37: Modulation | L37: Modulation | M37: =IFERROR(IF(VLOOKUP(L37,'Quantification'!$A:$B,2,FALSE)&""="","Unclassified",VLOOKUP(L37,'Quantification'!$A:$B,2,FALSE)),"Unclassified") -> Minor | N37: frl-laura.nissen@pocketfm.com | O37: Issues found in raw | P37: =IF(OR(O37="Issues found in master",O37="Final master"),"Master",IF(OR(O37="Ready for Master",O37="Issues found in raw",O37="Raw under QC",O37="Issues resolved in raw"),"Raw","-")) -> Raw | Q37: 46280.616 | R37: 2026-09 (Sept) | S37: =IF(M37="Not an error",0,IF(COUNTIFS($A$2:$A37,$A37,$D$2:$D37,$D37,$M$2:$M37,"<>Not an error")=1,1,0)) -> 0 | T37: =IF(M37<>"Major",0,IF(COUNTIFS($A$2:$A37,$A37,$D$2:$D37,$D37,$M$2:$M37,"Major")=1,1,0)) -> 0 | U37: =IF(M37<>"Minor",0,IF(COUNTIFS($A$2:$A37,$A37,$D$2:$D37,$D37,$M$2:$M37,"Minor")=1,1,0)) -> 0
A38: 341e3264241ee949f8140798461d1a30ee308d63 | B38: A Sacrifice That Lived | C38: Die Opferbraut Des Bestienkönigs | D38: beca349975cb0e5ae84723f55ebad4e2ee914523 | E38: Episode 32: Was Ist Mit Unseren Jungen | F38: 32 | H38: Resolved | I38: previously Heilachaten was pronounced HeilachÃ ten, in this episode it's pronounced HeilachatÃ¨n (the stress is on a different syllable). I think it's fine, I'm just taking note of it anyway | J38: VOA | K38: Mispronunciation | L38: Mispronunciation | M38: =IFERROR(IF(VLOOKUP(L38,'Quantification'!$A:$B,2,FALSE)&""="","Unclassified",VLOOKUP(L38,'Quantification'!$A:$B,2,FALSE)),"Unclassified") -> Major | N38: frl-denis.sobol@pocketfm.com | O38: Final Master | P38: =IF(OR(O38="Issues found in master",O38="Final master"),"Master",IF(OR(O38="Ready for Master",O38="Issues found in raw",O38="Raw under QC",O38="Issues resolved in raw"),"Raw","-")) -> Master | Q38: 46280.616 | R38: 2026-09 (Sept) | S38: =IF(M38="Not an error",0,IF(COUNTIFS($A$2:$A38,$A38,$D$2:$D38,$D38,$M$2:$M38,"<>Not an error")=1,1,0)) -> 1 | T38: =IF(M38<>"Major",0,IF(COUNTIFS($A$2:$A38,$A38,$D$2:$D38,$D38,$M$2:$M38,"Major")=1,1,0)) -> 1 | U38: =IF(M38<>"Minor",0,IF(COUNTIFS($A$2:$A38,$A38,$D$2:$D38,$D38,$M$2:$M38,"Minor")=1,1,0)) -> 0
A39: 341e3264241ee949f8140798461d1a30ee308d63 | B39: A Sacrifice That Lived | C39: Die Opferbraut Des Bestienkönigs | D39: beca349975cb0e5ae84723f55ebad4e2ee914523 | E39: Episode 32: Was Ist Mit Unseren Jungen | F39: 32 | G39: 00:00-2:25 | H39: Resolved | I39: previously Heilachaten was pronounced HeilachÃ ten, in this episode it's pronounced HeilachatÃ¨n (the stress is on a different syllable). I think it's fine, I'm just taking note of it anyway, line from script "Der Krieg gegen Heilachaten war brutal gewesen, vor allem, weil KÃ¶nig Declan ein grausamer, rÃ¼cksichtsloser Mann war. Er hatte Gift eingesetzt, ihre NahrungsvorrÃ¤te niedergebrannt und sogar wunderschÃ¶ne Frauen ausgeschickt, um seine Soldaten zur Fahnenflucht zu verfÃ¼hren. Das Bestienvolk kannte solche ehrlosen Taktiken nicht. Kians Zorn war so absolut, dass er sich in seine wahre Gestalt verwandelte, einen riesigen schwarzen Wolf. Er vernichtete die feindliche Basis mit einem einzigen Schlag und marschierte zum Palast, um im Austausch fÃ¼r den Frieden die Prinzessin zu fordern.Er hÃ¤tte ganz Heilachaten auslÃ¶schen kÃ¶nnen. Aber Kira hatte ihm von einer â€žgoldenen Prinzessinâ€œ erzÃ¤hlt, die die erste seiner GefÃ¤hrtinnen sein kÃ¶nnte. Er bereute nichts, was er in diesem Krieg getan hatte, und schon gar nicht, Liona als seinen Preis gefordert zu haben.Doch als er sie jetzt ansah und ihren Blick auf sich spÃ¼rte, durchfuhr ihn ein scharfer Stich des SchuldgefÃ¼hls. Er war derjenige, der ihren Vater getÃ¶tet hatte.Kian saÃŸ in der Falle. Sollte er ihr die Wahrheit sagen, dass ihr Vater ein Feigling war, der keinen ehrenhaften Krieg fÃ¼hren konnte? Oder sollte er einfach den Mund halten?Er Ã¼berlegte noch, als Liona sich wieder ihm zuwandte. â€žZahlst du ihnen einen Lohn fÃ¼r ihren Dienst?â€œKian runzelte die Stirn. â€žEinen Lohn?â€œâ€žDu weiÃŸt schonâ€œ, erklÃ¤rte sie. â€žEine Bezahlung fÃ¼r ihre Arbeit.â€œâ€žNeinâ€œ, erwiderte Kian schroff. â€žDas Bestienvolk hat nicht die gleichen seltsamen Begierden wie die Menschen. Wir sind geboren, um zu kÃ¤mpfen und dem StÃ¤rksten zu dienen. Solange sie versorgt sind, dienen sie mit Freude.â€œâ€žAber was ist, wenn sie Kinder haben?â€œ, hakte Liona nach. â€žSicherlich brauchen sie mehr als nur Essen, oder?â€œKians Stirnrunzeln vertiefte sich, er war vÃ¶llig ratlos. â€žDie Kinder des Bestienvolkes brauchen nur Nahrung, um zu wachsen. Sie brauchen nichts anderes.â€œEin Knoten der Angst zog sich in Lionas Magen zusammen, wÃ¤hrend sie versuchte, es ihm zu erklÃ¤ren. Sie wusste, dass ihre Kulturen Welten voneinander trennten; das Bestienvolk wurde zu Kriegern erzogen, schlicht und einfach.Aber Liona wusste auch, dass es mehr als nur rohe Gewalt brauchte, um ein langlebiges KÃ¶nigreich aufzubauen. Die Menschen brauchten Bildung oder zumindest FÃ¤higkeiten, die Ã¼ber das bloÃŸe Austeilen von SchlÃ¤gen hinausgingen.Sie erinnerte sich daran, wie sie die Ritter im Palast von Heilachaten beobachtet hatte." | J39: VOA | K39: Mispronunciation | L39: Mispronunciation | M39: =IFERROR(IF(VLOOKUP(L39,'Quantification'!$A:$B,2,FALSE)&""="","Unclassified",VLOOKUP(L39,'Quantification'!$A:$B,2,FALSE)),"Unclassified") -> Major | N39: frl-laura.nissen@pocketfm.com | O39: Issues found in raw | P39: =IF(OR(O39="Issues found in master",O39="Final master"),"Master",IF(OR(O39="Ready for Master",O39="Issues found in raw",O39="Raw under QC",O39="Issues resolved in raw"),"Raw","-")) -> Raw | Q39: 46280.616 | R39: 2026-09 (Sept) | S39: =IF(M39="Not an error",0,IF(COUNTIFS($A$2:$A39,$A39,$D$2:$D39,$D39,$M$2:$M39,"<>Not an error")=1,1,0)) -> 0 | T39: =IF(M39<>"Major",0,IF(COUNTIFS($A$2:$A39,$A39,$D$2:$D39,$D39,$M$2:$M39,"Major")=1,1,0)) -> 0 | U39: =IF(M39<>"Minor",0,IF(COUNTIFS($A$2:$A39,$A39,$D$2:$D39,$D39,$M$2:$M39,"Minor")=1,1,0)) -> 0
A40: eae3d2a9de33128288e5da99c87128b4548abf58 | B40: Alphas Masked Bride | C40: Die Schattenbraut Des Alphas | D40: 9d2e83be4aa61b9b356222e423c61602d7667640 | E40: EP 3 - Ein Verhängnisvoller Morgen | F40: 3 | G40: 1:47-1:53 | H40: Ignore | I40: Line needs to be rephrased. Instead of ["Sie fragte sich, wie sie an eine Kutsche, einen Vorwand und einen Weg an ihrem Vater vorbeikommen sollte."] it needs to be ["Sie fragte sich, wie sie an eine Kutsche und einen Vorwand kommen und einen Weg finden sollte, an ihrem Vater vorbeizukommen."] - Line of script: " Sie fragte sich, wie sie an eine Kutsche, einen Vorwand und einen Weg an ihrem Vater vorbeikommen sollte. " | J40: VOA | K40: Script Error | L40: Script error | M40: =IFERROR(IF(VLOOKUP(L40,'Quantification'!$A:$B,2,FALSE)&""="","Unclassified",VLOOKUP(L40,'Quantification'!$A:$B,2,FALSE)),"Unclassified") -> Major | N40: frl-kerem.gulsoy@pocketfm.com | O40: Issues found in raw | P40: =IF(OR(O40="Issues found in master",O40="Final master"),"Master",IF(OR(O40="Ready for Master",O40="Issues found in raw",O40="Raw under QC",O40="Issues resolved in raw"),"Raw","-")) -> Raw | Q40: 46289.59 | R40: 2026-09 (Sept) | S40: =IF(M40="Not an error",0,IF(COUNTIFS($A$2:$A40,$A40,$D$2:$D40,$D40,$M$2:$M40,"<>Not an error")=1,1,0)) -> 1 | T40: =IF(M40<>"Major",0,IF(COUNTIFS($A$2:$A40,$A40,$D$2:$D40,$D40,$M$2:$M40,"Major")=1,1,0)) -> 1 | U40: =IF(M40<>"Minor",0,IF(COUNTIFS($A$2:$A40,$A40,$D$2:$D40,$D40,$M$2:$M40,"Minor")=1,1,0)) -> 0
A41: eae3d2a9de33128288e5da99c87128b4548abf58 | B41: Alphas Masked Bride | C41: Die Schattenbraut Des Alphas | D41: 9d2e83be4aa61b9b356222e423c61602d7667640 | E41: EP 3 - Ein Verhängnisvoller Morgen | F41: 3 | G41: 9:45-9:49 | H41: Pending | I41: Mispronunciation of the name ["Vale"] - Line of script: " Du bist die einzige Vale, mit der ich länger als fünf Minuten in einem Raum bleiben kann.“ " | J41: VOA | K41: Mispronunciation | L41: Mispronunciation | M41: =IFERROR(IF(VLOOKUP(L41,'Quantification'!$A:$B,2,FALSE)&""="","Unclassified",VLOOKUP(L41,'Quantification'!$A:$B,2,FALSE)),"Unclassified") -> Major | N41: frl-kerem.gulsoy@pocketfm.com | O41: Issues found in raw | P41: =IF(OR(O41="Issues found in master",O41="Final master"),"Master",IF(OR(O41="Ready for Master",O41="Issues found in raw",O41="Raw under QC",O41="Issues resolved in raw"),"Raw","-")) -> Raw | Q41: 46289.59 | R41: 2026-09 (Sept) | S41: =IF(M41="Not an error",0,IF(COUNTIFS($A$2:$A41,$A41,$D$2:$D41,$D41,$M$2:$M41,"<>Not an error")=1,1,0)) -> 0 | T41: =IF(M41<>"Major",0,IF(COUNTIFS($A$2:$A41,$A41,$D$2:$D41,$D41,$M$2:$M41,"Major")=1,1,0)) -> 0 | U41: =IF(M41<>"Minor",0,IF(COUNTIFS($A$2:$A41,$A41,$D$2:$D41,$D41,$M$2:$M41,"Minor")=1,1,0)) -> 0
A42: eae3d2a9de33128288e5da99c87128b4548abf58 | B42: Alphas Masked Bride | C42: Die Schattenbraut Des Alphas | D42: fc1d8fb97e16137e79230b02f4ac2fe68958629e | E42: EP 4 - Nur Noch Diese Nacht | F42: 4 | G42: 10:25-10:30 | H42: Pending | I42: Mispronunciation of the name ["Tristan"] - Line of script: " Seit der Begegnung mit Alpha Tristan im Garten fühlte sich der Rand des Schleiers gelegentlich anders an. " | J42: VOA | K42: Mispronunciation | L42: Mispronunciation | M42: =IFERROR(IF(VLOOKUP(L42,'Quantification'!$A:$B,2,FALSE)&""="","Unclassified",VLOOKUP(L42,'Quantification'!$A:$B,2,FALSE)),"Unclassified") -> Major | N42: frl-kerem.gulsoy@pocketfm.com | O42: Issues found in raw | P42: =IF(OR(O42="Issues found in master",O42="Final master"),"Master",IF(OR(O42="Ready for Master",O42="Issues found in raw",O42="Raw under QC",O42="Issues resolved in raw"),"Raw","-")) -> Raw | Q42: 46289.59 | R42: 2026-09 (Sept) | S42: =IF(M42="Not an error",0,IF(COUNTIFS($A$2:$A42,$A42,$D$2:$D42,$D42,$M$2:$M42,"<>Not an error")=1,1,0)) -> 1 | T42: =IF(M42<>"Major",0,IF(COUNTIFS($A$2:$A42,$A42,$D$2:$D42,$D42,$M$2:$M42,"Major")=1,1,0)) -> 1 | U42: =IF(M42<>"Minor",0,IF(COUNTIFS($A$2:$A42,$A42,$D$2:$D42,$D42,$M$2:$M42,"Minor")=1,1,0)) -> 0
A43: eae3d2a9de33128288e5da99c87128b4548abf58 | B43: Alphas Masked Bride | C43: Die Schattenbraut Des Alphas | D43: fc1d8fb97e16137e79230b02f4ac2fe68958629e | E43: EP 4 - Nur Noch Diese Nacht | F43: 4 | G43: 10:33-10:36 | H43: Pending | I43: Mispronunciation of the name ["Tristan"] - Line of script: " Fast warm, sobald Ahria an Alpha Tristans ruhige Stimme dachte. " | J43: VOA | K43: Mispronunciation | L43: Mispronunciation | M43: =IFERROR(IF(VLOOKUP(L43,'Quantification'!$A:$B,2,FALSE)&""="","Unclassified",VLOOKUP(L43,'Quantification'!$A:$B,2,FALSE)),"Unclassified") -> Major | N43: frl-kerem.gulsoy@pocketfm.com | O43: Issues found in raw | P43: =IF(OR(O43="Issues found in master",O43="Final master"),"Master",IF(OR(O43="Ready for Master",O43="Issues found in raw",O43="Raw under QC",O43="Issues resolved in raw"),"Raw","-")) -> Raw | Q43: 46289.59 | R43: 2026-09 (Sept) | S43: =IF(M43="Not an error",0,IF(COUNTIFS($A$2:$A43,$A43,$D$2:$D43,$D43,$M$2:$M43,"<>Not an error")=1,1,0)) -> 0 | T43: =IF(M43<>"Major",0,IF(COUNTIFS($A$2:$A43,$A43,$D$2:$D43,$D43,$M$2:$M43,"Major")=1,1,0)) -> 0 | U43: =IF(M43<>"Minor",0,IF(COUNTIFS($A$2:$A43,$A43,$D$2:$D43,$D43,$M$2:$M43,"Minor")=1,1,0)) -> 0
A44: eae3d2a9de33128288e5da99c87128b4548abf58 | B44: Alphas Masked Bride | C44: Die Schattenbraut Des Alphas | D44: fc1d8fb97e16137e79230b02f4ac2fe68958629e | E44: EP 4 - Nur Noch Diese Nacht | F44: 4 | G44: 10:44-10:47 | H44: Pending | I44: Mispronunciation of the name ["Tristan"] - Line of script: " Alpha Tristan war davor nicht zurückgewichen. " | J44: VOA | K44: Mispronunciation | L44: Mispronunciation | M44: =IFERROR(IF(VLOOKUP(L44,'Quantification'!$A:$B,2,FALSE)&""="","Unclassified",VLOOKUP(L44,'Quantification'!$A:$B,2,FALSE)),"Unclassified") -> Major | N44: frl-kerem.gulsoy@pocketfm.com | O44: Issues found in raw | P44: =IF(OR(O44="Issues found in master",O44="Final master"),"Master",IF(OR(O44="Ready for Master",O44="Issues found in raw",O44="Raw under QC",O44="Issues resolved in raw"),"Raw","-")) -> Raw | Q44: 46289.59 | R44: 2026-09 (Sept) | S44: =IF(M44="Not an error",0,IF(COUNTIFS($A$2:$A44,$A44,$D$2:$D44,$D44,$M$2:$M44,"<>Not an error")=1,1,0)) -> 0 | T44: =IF(M44<>"Major",0,IF(COUNTIFS($A$2:$A44,$A44,$D$2:$D44,$D44,$M$2:$M44,"Major")=1,1,0)) -> 0 | U44: =IF(M44<>"Minor",0,IF(COUNTIFS($A$2:$A44,$A44,$D$2:$D44,$D44,$M$2:$M44,"Minor")=1,1,0)) -> 0
A45: eae3d2a9de33128288e5da99c87128b4548abf58 | B45: Alphas Masked Bride | C45: Die Schattenbraut Des Alphas | D45: cf9aa03d182ec94028747692c03ce59a36659dcb | E45: EP 6 - Vor Dem Tor Des Alphas | F45: 6 | G45: 12:14-12:17 | H45: Pending | I45: Mispronunciation of the name ["Alastair"] - Line of script: " „Alastair.“ „Es freut mich, Alastair.“ " | J45: VOA | K45: Mispronunciation | L45: Mispronunciation | M45: =IFERROR(IF(VLOOKUP(L45,'Quantification'!$A:$B,2,FALSE)&""="","Unclassified",VLOOKUP(L45,'Quantification'!$A:$B,2,FALSE)),"Unclassified") -> Major | N45: frl-kerem.gulsoy@pocketfm.com | O45: Issues found in raw | P45: =IF(OR(O45="Issues found in master",O45="Final master"),"Master",IF(OR(O45="Ready for Master",O45="Issues found in raw",O45="Raw under QC",O45="Issues resolved in raw"),"Raw","-")) -> Raw | Q45: 46289.59 | R45: 2026-09 (Sept) | S45: =IF(M45="Not an error",0,IF(COUNTIFS($A$2:$A45,$A45,$D$2:$D45,$D45,$M$2:$M45,"<>Not an error")=1,1,0)) -> 1 | T45: =IF(M45<>"Major",0,IF(COUNTIFS($A$2:$A45,$A45,$D$2:$D45,$D45,$M$2:$M45,"Major")=1,1,0)) -> 1 | U45: =IF(M45<>"Minor",0,IF(COUNTIFS($A$2:$A45,$A45,$D$2:$D45,$D45,$M$2:$M45,"Minor")=1,1,0)) -> 0
A46: eae3d2a9de33128288e5da99c87128b4548abf58 | B46: Alphas Masked Bride | C46: Die Schattenbraut Des Alphas | D46: cf9aa03d182ec94028747692c03ce59a36659dcb | E46: EP 6 - Vor Dem Tor Des Alphas | F46: 6 | G46: 12:36-12:39 | H46: Pending | I46: Mispronunciation of the name ["Alastair"] - Line of script: " Ein kaum sichtbares Lächeln erschien auf Alastairs Gesicht. " | J46: VOA | K46: Mispronunciation | L46: Mispronunciation | M46: =IFERROR(IF(VLOOKUP(L46,'Quantification'!$A:$B,2,FALSE)&""="","Unclassified",VLOOKUP(L46,'Quantification'!$A:$B,2,FALSE)),"Unclassified") -> Major | N46: frl-kerem.gulsoy@pocketfm.com | O46: Issues found in raw | P46: =IF(OR(O46="Issues found in master",O46="Final master"),"Master",IF(OR(O46="Ready for Master",O46="Issues found in raw",O46="Raw under QC",O46="Issues resolved in raw"),"Raw","-")) -> Raw | Q46: 46289.59 | R46: 2026-09 (Sept) | S46: =IF(M46="Not an error",0,IF(COUNTIFS($A$2:$A46,$A46,$D$2:$D46,$D46,$M$2:$M46,"<>Not an error")=1,1,0)) -> 0 | T46: =IF(M46<>"Major",0,IF(COUNTIFS($A$2:$A46,$A46,$D$2:$D46,$D46,$M$2:$M46,"Major")=1,1,0)) -> 0 | U46: =IF(M46<>"Minor",0,IF(COUNTIFS($A$2:$A46,$A46,$D$2:$D46,$D46,$M$2:$M46,"Minor")=1,1,0)) -> 0
A47: eae3d2a9de33128288e5da99c87128b4548abf58 | B47: Alphas Masked Bride | C47: Die Schattenbraut Des Alphas | D47: f492f07d7a738ac2e068e90265a3eccff9df7955 | E47: EP 7 - Die Regeln Der Freiheit | F47: 7 | G47: 8:07-8:12 | H47: Pending | I47: An Addition is needed. Instead of ["noch aus Entscheidungen"] it needs to be ["noch schließt du mich aus Entscheidungen"] - Line of script: " Du sperrst mich weder in ein Zimmer ein, noch aus Entscheidungen aus, die mein Leben betreffen.“ " | J47: VOA | K47: Gramatically incorrect (voa) | L47: Gramatically incorrect (voa) | M47: =IFERROR(IF(VLOOKUP(L47,'Quantification'!$A:$B,2,FALSE)&""="","Unclassified",VLOOKUP(L47,'Quantification'!$A:$B,2,FALSE)),"Unclassified") -> Major | N47: frl-kerem.gulsoy@pocketfm.com | O47: Issues found in raw | P47: =IF(OR(O47="Issues found in master",O47="Final master"),"Master",IF(OR(O47="Ready for Master",O47="Issues found in raw",O47="Raw under QC",O47="Issues resolved in raw"),"Raw","-")) -> Raw | Q47: 46289.59 | R47: 2026-09 (Sept) | S47: =IF(M47="Not an error",0,IF(COUNTIFS($A$2:$A47,$A47,$D$2:$D47,$D47,$M$2:$M47,"<>Not an error")=1,1,0)) -> 1 | T47: =IF(M47<>"Major",0,IF(COUNTIFS($A$2:$A47,$A47,$D$2:$D47,$D47,$M$2:$M47,"Major")=1,1,0)) -> 1 | U47: =IF(M47<>"Minor",0,IF(COUNTIFS($A$2:$A47,$A47,$D$2:$D47,$D47,$M$2:$M47,"Minor")=1,1,0)) -> 0
A48: eae3d2a9de33128288e5da99c87128b4548abf58 | B48: Alphas Masked Bride | C48: Die Schattenbraut Des Alphas | D48: f492f07d7a738ac2e068e90265a3eccff9df7955 | E48: EP 7 - Die Regeln Der Freiheit | F48: 7 | G48: 11:28-11:30 | H48: Pending | I48: Mispronunciation of the name ["Alastair "] - Line of script: " Alastair darf ihn kennen, sonst niemand. " | J48: VOA | K48: Mispronunciation | L48: Mispronunciation | M48: =IFERROR(IF(VLOOKUP(L48,'Quantification'!$A:$B,2,FALSE)&""="","Unclassified",VLOOKUP(L48,'Quantification'!$A:$B,2,FALSE)),"Unclassified") -> Major | N48: frl-kerem.gulsoy@pocketfm.com | O48: Issues found in raw | P48: =IF(OR(O48="Issues found in master",O48="Final master"),"Master",IF(OR(O48="Ready for Master",O48="Issues found in raw",O48="Raw under QC",O48="Issues resolved in raw"),"Raw","-")) -> Raw | Q48: 46289.59 | R48: 2026-09 (Sept) | S48: =IF(M48="Not an error",0,IF(COUNTIFS($A$2:$A48,$A48,$D$2:$D48,$D48,$M$2:$M48,"<>Not an error")=1,1,0)) -> 0 | T48: =IF(M48<>"Major",0,IF(COUNTIFS($A$2:$A48,$A48,$D$2:$D48,$D48,$M$2:$M48,"Major")=1,1,0)) -> 0 | U48: =IF(M48<>"Minor",0,IF(COUNTIFS($A$2:$A48,$A48,$D$2:$D48,$D48,$M$2:$M48,"Minor")=1,1,0)) -> 0
A49: eae3d2a9de33128288e5da99c87128b4548abf58 | B49: Alphas Masked Bride | C49: Die Schattenbraut Des Alphas | D49: 7844d112736d47aa5f31beb942221d1157ac1057 | E49: EP 9 - Der Letzte Tag Im Käfig | F49: 9 | G49: 4:57-5:04 | H49: Resolved | I49: An Addition is needed. Instead of ["Luna würdig wäre"] it needs to be ["Luna nicht würdig wäre"] - Line of script: " Ahria hatte damit gerechnet, dass Alpha Tristan sie auslachte oder ihr erklärte, weshalb eine Frau wie sie einer Luna würdig wäre. | J49: AI | K49: Script error | L49: Script error | M49: =IFERROR(IF(VLOOKUP(L49,'Quantification'!$A:$B,2,FALSE)&""="","Unclassified",VLOOKUP(L49,'Quantification'!$A:$B,2,FALSE)),"Unclassified") -> Major | N49: frl-kerem.gulsoy@pocketfm.com | O49: Issues found in raw | P49: =IF(OR(O49="Issues found in master",O49="Final master"),"Master",IF(OR(O49="Ready for Master",O49="Issues found in raw",O49="Raw under QC",O49="Issues resolved in raw"),"Raw","-")) -> Raw | Q49: 46289.59 | R49: 2026-09 (Sept) | S49: =IF(M49="Not an error",0,IF(COUNTIFS($A$2:$A49,$A49,$D$2:$D49,$D49,$M$2:$M49,"<>Not an error")=1,1,0)) -> 1 | T49: =IF(M49<>"Major",0,IF(COUNTIFS($A$2:$A49,$A49,$D$2:$D49,$D49,$M$2:$M49,"Major")=1,1,0)) -> 1 | U49: =IF(M49<>"Minor",0,IF(COUNTIFS($A$2:$A49,$A49,$D$2:$D49,$D49,$M$2:$M49,"Minor")=1,1,0)) -> 0
A50: eae3d2a9de33128288e5da99c87128b4548abf58 | B50: Alphas Masked Bride | C50: Die Schattenbraut Des Alphas | D50: 7844d112736d47aa5f31beb942221d1157ac1057 | E50: EP 9 - Der Letzte Tag Im Käfig | F50: 9 | G50: 13:13-13:15 | H50: Resolved | I50: An Addition is needed. Instead of ["bleibe in mein"] it needs to be ["bleibe ich in meinem"] - Line of script: " Danach bleibe in mein Zimmer. " | J50: AI | K50: Script error | L50: Script error | M50: =IFERROR(IF(VLOOKUP(L50,'Quantification'!$A:$B,2,FALSE)&""="","Unclassified",VLOOKUP(L50,'Quantification'!$A:$B,2,FALSE)),"Unclassified") -> Major | N50: frl-kerem.gulsoy@pocketfm.com | O50: Issues found in raw | P50: =IF(OR(O50="Issues found in master",O50="Final master"),"Master",IF(OR(O50="Ready for Master",O50="Issues found in raw",O50="Raw under QC",O50="Issues resolved in raw"),"Raw","-")) -> Raw | Q50: 46289.59 | R50: 2026-09 (Sept) | S50: =IF(M50="Not an error",0,IF(COUNTIFS($A$2:$A50,$A50,$D$2:$D50,$D50,$M$2:$M50,"<>Not an error")=1,1,0)) -> 0 | T50: =IF(M50<>"Major",0,IF(COUNTIFS($A$2:$A50,$A50,$D$2:$D50,$D50,$M$2:$M50,"Major")=1,1,0)) -> 0 | U50: =IF(M50<>"Minor",0,IF(COUNTIFS($A$2:$A50,$A50,$D$2:$D50,$D50,$M$2:$M50,"Minor")=1,1,0)) -> 0
... A219: 87dfd458f8a24d7bbd0829af61d48e90284c3786 | B219: Brahmyodha : The Destroyer | ब्रह्मयोद्धा : द डिस्ट्रोयर | C219: Brahma Warrior: Der Zerstörer | D219: b0520589e3c348ea06d8e0801ea8ae83a750cf32 | E219: Episode 4 – Vidyut Und Tejas Treffen Aufeinander | F219: 4 | G219: 9:47-9:55 | H219: Resolved | I219: Super Seven Warriors should be DE, line from script: "Tatsächlich wurde der Shakti-Palast von einem der legendären Sieben geleitet, die man auch Dev-Krieger nannte" | J219: AI | K219: Script error | L219: Script error | M219: =IFERROR(IF(VLOOKUP(L219,'Quantification'!$A:$B,2,FALSE)&""="","Unclassified",VLOOKUP(L219,'Quantification'!$A:$B,2,FALSE)),"Unclassified") -> Major | N219: frl-laura.nissen@pocketfm.com | O219: Issues found in raw | P219: =IF(OR(O219="Issues found in master",O219="Final master"),"Master",IF(OR(O219="Ready for Master",O219="Issues found in raw",O219="Raw under QC",O219="Issues resolved in raw"),"Raw","-")) -> Raw | Q219: 46249.773 | R219: 2026-08 (Aug) | S219: =IF(M219="Not an error",0,IF(COUNTIFS($A$2:$A219,$A219,$D$2:$D219,$D219,$M$2:$M219,"<>Not an error")=1,1,0)) -> 0 | T219: =IF(M219<>"Major",0,IF(COUNTIFS($A$2:$A219,$A219,$D$2:$D219,$D219,$M$2:$M219,"Major")=1,1,0)) -> 0 | U219: =IF(M219<>"Minor",0,IF(COUNTIFS($A$2:$A219,$A219,$D$2:$D219,$D219,$M$2:$M219,"Minor")=1,1,0)) -> 0
A220: 87dfd458f8a24d7bbd0829af61d48e90284c3786 | B220: Brahmyodha : The Destroyer | ब्रह्मयोद्धा : द डिस्ट्रोयर | C220: Brahma Warrior: Der Zerstörer | D220: 3546c45058b84853909dd03e60b29e083b4c8a88 | E220: Episode 5 – Die Göttlichen Zeichen Auf Vidyuts Körper | F220: 5 | G220: 13:17-13:23 | H220: Resolved | I220: Remark: script error Line from script: "Dann werde ich euch zeigen, was ich mit euch beiden – Löwe und Gepard – anstelle." Note: Gepard should be Tiger I think as he is the silver Tiger. | J220: VOA | K220: Script Error | L220: Script error | M220: =IFERROR(IF(VLOOKUP(L220,'Quantification'!$A:$B,2,FALSE)&""="","Unclassified",VLOOKUP(L220,'Quantification'!$A:$B,2,FALSE)),"Unclassified") -> Major | P220: =IF(OR(O220="Issues found in master",O220="Final master"),"Master",IF(OR(O220="Ready for Master",O220="Issues found in raw",O220="Raw under QC",O220="Issues resolved in raw"),"Raw","-")) -> - | Q220: 46249.776 | R220: 2026-08 (Aug) | S220: =IF(M220="Not an error",0,IF(COUNTIFS($A$2:$A220,$A220,$D$2:$D220,$D220,$M$2:$M220,"<>Not an error")=1,1,0)) -> 1 | T220: =IF(M220<>"Major",0,IF(COUNTIFS($A$2:$A220,$A220,$D$2:$D220,$D220,$M$2:$M220,"Major")=1,1,0)) -> 1 | U220: =IF(M220<>"Minor",0,IF(COUNTIFS($A$2:$A220,$A220,$D$2:$D220,$D220,$M$2:$M220,"Minor")=1,1,0)) -> 0
A221: 87dfd458f8a24d7bbd0829af61d48e90284c3786 | B221: Brahmyodha : The Destroyer | ब्रह्मयोद्धा : द डिस्ट्रोयर | C221: Brahma Warrior: Der Zerstörer | D221: 3546c45058b84853909dd03e60b29e083b4c8a88 | E221: Episode 5 – Die Göttlichen Zeichen Auf Vidyuts Körper | F221: 5 | G221: 1:16-1:36 | H221: Resolved | I221: Super Seven Warriors should be DE, line from script: "„Wenn du auf mich hörst“, fuhr Thama fort, „werde ich dich Kampfkünste lehren, durch die du eines Tages zum größten Brahmyodha dieser Erde werden kannst. Nicht einmal die in aller Welt berühmten legendären Sieben werden dir dann gewachsen sein. Die Entscheidung liegt bei dir.“ " | J221: AI | K221: Script error | L221: Script error | M221: =IFERROR(IF(VLOOKUP(L221,'Quantification'!$A:$B,2,FALSE)&""="","Unclassified",VLOOKUP(L221,'Quantification'!$A:$B,2,FALSE)),"Unclassified") -> Major | N221: frl-laura.nissen@pocketfm.com | O221: Issues found in raw | P221: =IF(OR(O221="Issues found in master",O221="Final master"),"Master",IF(OR(O221="Ready for Master",O221="Issues found in raw",O221="Raw under QC",O221="Issues resolved in raw"),"Raw","-")) -> Raw | Q221: 46249.776 | R221: 2026-08 (Aug) | S221: =IF(M221="Not an error",0,IF(COUNTIFS($A$2:$A221,$A221,$D$2:$D221,$D221,$M$2:$M221,"<>Not an error")=1,1,0)) -> 0 | T221: =IF(M221<>"Major",0,IF(COUNTIFS($A$2:$A221,$A221,$D$2:$D221,$D221,$M$2:$M221,"Major")=1,1,0)) -> 0 | U221: =IF(M221<>"Minor",0,IF(COUNTIFS($A$2:$A221,$A221,$D$2:$D221,$D221,$M$2:$M221,"Minor")=1,1,0)) -> 0
A222: 87dfd458f8a24d7bbd0829af61d48e90284c3786 | B222: Brahmyodha : The Destroyer | ब्रह्मयोद्धा : द डिस्ट्रोयर | C222: Brahma Warrior: Der Zerstörer | D222: 4db32aa2a1970840efe87687fc048a8cc544d96f | E222: Episode 6 – Dadis Außergewöhnliches Geschenk | F222: 6 | G222: 5:02-5:04 | H222: Resolved | I222: Remark: script error Line from script: "Ich bin jetzt fünfzehn." Note: He is fourteen (Vierzehn) | J222: VOA | K222: Script Error | L222: Script error | M222: =IFERROR(IF(VLOOKUP(L222,'Quantification'!$A:$B,2,FALSE)&""="","Unclassified",VLOOKUP(L222,'Quantification'!$A:$B,2,FALSE)),"Unclassified") -> Major | N222: frl-carlos.alexander@pocketfm.com | O222: Issues found in raw | P222: =IF(OR(O222="Issues found in master",O222="Final master"),"Master",IF(OR(O222="Ready for Master",O222="Issues found in raw",O222="Raw under QC",O222="Issues resolved in raw"),"Raw","-")) -> Raw | Q222: 46249.776 | R222: 2026-08 (Aug) | S222: =IF(M222="Not an error",0,IF(COUNTIFS($A$2:$A222,$A222,$D$2:$D222,$D222,$M$2:$M222,"<>Not an error")=1,1,0)) -> 1 | T222: =IF(M222<>"Major",0,IF(COUNTIFS($A$2:$A222,$A222,$D$2:$D222,$D222,$M$2:$M222,"Major")=1,1,0)) -> 1 | U222: =IF(M222<>"Minor",0,IF(COUNTIFS($A$2:$A222,$A222,$D$2:$D222,$D222,$M$2:$M222,"Minor")=1,1,0)) -> 0
A223: 87dfd458f8a24d7bbd0829af61d48e90284c3786 | B223: Brahmyodha : The Destroyer | ब्रह्मयोद्धा : द डिस्ट्रोयर | C223: Brahma Warrior: Der Zerstörer | D223: 3c09ff3cf4c4f5d21ca65cd3622289c6874c93bf | E223: Episode 8 – Vidyut, Sei Auf Der Hut | F223: 8 | G223: 6:07-6:11 | H223: Resolved | I223: Remark: Mispronunciation Line from script: "Er zog sich um und machte sich auf den Weg zum Königspalast." Note: first "s" In Königspalast not pronounced. | J223: VOA | K223: Mispronunciation | L223: Mispronunciation | M223: =IFERROR(IF(VLOOKUP(L223,'Quantification'!$A:$B,2,FALSE)&""="","Unclassified",VLOOKUP(L223,'Quantification'!$A:$B,2,FALSE)),"Unclassified") -> Major | N223: frl-carlos.alexander@pocketfm.com | O223: Issues found in raw | P223: =IF(OR(O223="Issues found in master",O223="Final master"),"Master",IF(OR(O223="Ready for Master",O223="Issues found in raw",O223="Raw under QC",O223="Issues resolved in raw"),"Raw","-")) -> Raw | Q223: 46249.774 | R223: 2026-08 (Aug) | S223: =IF(M223="Not an error",0,IF(COUNTIFS($A$2:$A223,$A223,$D$2:$D223,$D223,$M$2:$M223,"<>Not an error")=1,1,0)) -> 1 | T223: =IF(M223<>"Major",0,IF(COUNTIFS($A$2:$A223,$A223,$D$2:$D223,$D223,$M$2:$M223,"Major")=1,1,0)) -> 1 | U223: =IF(M223<>"Minor",0,IF(COUNTIFS($A$2:$A223,$A223,$D$2:$D223,$D223,$M$2:$M223,"Minor")=1,1,0)) -> 0
A224: 87dfd458f8a24d7bbd0829af61d48e90284c3786 | B224: Brahmyodha : The Destroyer | ब्रह्मयोद्धा : द डिस्ट्रोयर | C224: Brahma Warrior: Der Zerstörer | D224: 3c09ff3cf4c4f5d21ca65cd3622289c6874c93bf | E224: Episode 8 – Vidyut, Sei Auf Der Hut | F224: 8 | G224: 9:27-9:33 | H224: Resolved | I224: Remark: Mispronunciation Line from script: "Jeraj und Adheera kochten vor Wut und wollten angreifen." Note: wollten pronounced "wonnten" | J224: VOA | K224: Mispronunciation | L224: Mispronunciation | M224: =IFERROR(IF(VLOOKUP(L224,'Quantification'!$A:$B,2,FALSE)&""="","Unclassified",VLOOKUP(L224,'Quantification'!$A:$B,2,FALSE)),"Unclassified") -> Major | N224: frl-carlos.alexander@pocketfm.com | O224: Issues found in raw | P224: =IF(OR(O224="Issues found in master",O224="Final master"),"Master",IF(OR(O224="Ready for Master",O224="Issues found in raw",O224="Raw under QC",O224="Issues resolved in raw"),"Raw","-")) -> Raw | Q224: 46249.774 | R224: 2026-08 (Aug) | S224: =IF(M224="Not an error",0,IF(COUNTIFS($A$2:$A224,$A224,$D$2:$D224,$D224,$M$2:$M224,"<>Not an error")=1,1,0)) -> 0 | T224: =IF(M224<>"Major",0,IF(COUNTIFS($A$2:$A224,$A224,$D$2:$D224,$D224,$M$2:$M224,"Major")=1,1,0)) -> 0 | U224: =IF(M224<>"Minor",0,IF(COUNTIFS($A$2:$A224,$A224,$D$2:$D224,$D224,$M$2:$M224,"Minor")=1,1,0)) -> 0
A225: 87dfd458f8a24d7bbd0829af61d48e90284c3786 | B225: Brahmyodha : The Destroyer | ब्रह्मयोद्धा : द डिस्ट्रोयर | C225: Brahma Warrior: Der Zerstörer | D225: 3c09ff3cf4c4f5d21ca65cd3622289c6874c93bf | E225: Episode 8 – Vidyut, Sei Auf Der Hut | F225: 8 | G225: 9:36-9:39 | H225: Resolved | I225: Remark: Mispronunciation Line from script: "Jeraj, willst du mein Fest verderben?" Note: "Fest verderben" read as "fessen" | J225: VOA | K225: Mispronunciation | L225: Mispronunciation | M225: =IFERROR(IF(VLOOKUP(L225,'Quantification'!$A:$B,2,FALSE)&""="","Unclassified",VLOOKUP(L225,'Quantification'!$A:$B,2,FALSE)),"Unclassified") -> Major | N225: frl-carlos.alexander@pocketfm.com | O225: Issues found in raw | P225: =IF(OR(O225="Issues found in master",O225="Final master"),"Master",IF(OR(O225="Ready for Master",O225="Issues found in raw",O225="Raw under QC",O225="Issues resolved in raw"),"Raw","-")) -> Raw | Q225: 46249.774 | R225: 2026-08 (Aug) | S225: =IF(M225="Not an error",0,IF(COUNTIFS($A$2:$A225,$A225,$D$2:$D225,$D225,$M$2:$M225,"<>Not an error")=1,1,0)) -> 0 | T225: =IF(M225<>"Major",0,IF(COUNTIFS($A$2:$A225,$A225,$D$2:$D225,$D225,$M$2:$M225,"Major")=1,1,0)) -> 0 | U225: =IF(M225<>"Minor",0,IF(COUNTIFS($A$2:$A225,$A225,$D$2:$D225,$D225,$M$2:$M225,"Minor")=1,1,0)) -> 0
A226: 87dfd458f8a24d7bbd0829af61d48e90284c3786 | B226: Brahmyodha : The Destroyer | ब्रह्मयोद्धा : द डिस्ट्रोयर | C226: Brahma Warrior: Der Zerstörer | D226: 3c09ff3cf4c4f5d21ca65cd3622289c6874c93bf | E226: Episode 8 – Vidyut, Sei Auf Der Hut | F226: 8 | G226: 11:31-11:35 | H226: Resolved | I226: Remark: Mispronunciation Line from script: "Werden Jeraj und Adheera sich an Vidyut rächen?" Note: Jeraj pronounced "dscherai" instead of "yerai" as before | J226: VOA | K226: Mispronunciation | L226: Mispronunciation | M226: =IFERROR(IF(VLOOKUP(L226,'Quantification'!$A:$B,2,FALSE)&""="","Unclassified",VLOOKUP(L226,'Quantification'!$A:$B,2,FALSE)),"Unclassified") -> Major | N226: frl-carlos.alexander@pocketfm.com | O226: Issues found in raw | P226: =IF(OR(O226="Issues found in master",O226="Final master"),"Master",IF(OR(O226="Ready for Master",O226="Issues found in raw",O226="Raw under QC",O226="Issues resolved in raw"),"Raw","-")) -> Raw | Q226: 46249.774 | R226: 2026-08 (Aug) | S226: =IF(M226="Not an error",0,IF(COUNTIFS($A$2:$A226,$A226,$D$2:$D226,$D226,$M$2:$M226,"<>Not an error")=1,1,0)) -> 0 | T226: =IF(M226<>"Major",0,IF(COUNTIFS($A$2:$A226,$A226,$D$2:$D226,$D226,$M$2:$M226,"Major")=1,1,0)) -> 0 | U226: =IF(M226<>"Minor",0,IF(COUNTIFS($A$2:$A226,$A226,$D$2:$D226,$D226,$M$2:$M226,"Minor")=1,1,0)) -> 0
A227: 87dfd458f8a24d7bbd0829af61d48e90284c3786 | B227: Brahmyodha : The Destroyer | ब्रह्मयोद्धा : द डिस्ट्रोयर | C227: Brahma Warrior: Der Zerstörer | D227: 609133b3739c26b50ee599b37a224a6c9d9f60b5 | E227: Episode 9 – Wer Ist Dein Guru? | F227: 9 | G227: 3:22-3:27 | H227: Resolved | I227: Remark: Mispronunciation Line from script: "Mayra und Nayra folgten ihm, um Jeraj und Adheera auszuweichen." Note: Jeraj pronounnced "dscherai" | J227: VOA | K227: Mispronunciation | L227: Mispronunciation | M227: =IFERROR(IF(VLOOKUP(L227,'Quantification'!$A:$B,2,FALSE)&""="","Unclassified",VLOOKUP(L227,'Quantification'!$A:$B,2,FALSE)),"Unclassified") -> Major | N227: frl-carlos.alexander@pocketfm.com | O227: Issues found in raw | P227: =IF(OR(O227="Issues found in master",O227="Final master"),"Master",IF(OR(O227="Ready for Master",O227="Issues found in raw",O227="Raw under QC",O227="Issues resolved in raw"),"Raw","-")) -> Raw | Q227: 46249.774 | R227: 2026-08 (Aug) | S227: =IF(M227="Not an error",0,IF(COUNTIFS($A$2:$A227,$A227,$D$2:$D227,$D227,$M$2:$M227,"<>Not an error")=1,1,0)) -> 1 | T227: =IF(M227<>"Major",0,IF(COUNTIFS($A$2:$A227,$A227,$D$2:$D227,$D227,$M$2:$M227,"Major")=1,1,0)) -> 1 | U227: =IF(M227<>"Minor",0,IF(COUNTIFS($A$2:$A227,$A227,$D$2:$D227,$D227,$M$2:$M227,"Minor")=1,1,0)) -> 0
A228: 87dfd458f8a24d7bbd0829af61d48e90284c3786 | B228: Brahmyodha : The Destroyer | ब्रह्मयोद्धा : द डिस्ट्रोयर | C228: Brahma Warrior: Der Zerstörer | D228: 609133b3739c26b50ee599b37a224a6c9d9f60b5 | E228: Episode 9 – Wer Ist Dein Guru? | F228: 9 | G228: 12:29-12:33 | H228: Resolved | I228: Remark: Mispronunciation Line from script: "Was werden Jeraj, Jora und Adheera nun tun?" Note: Both names pronounced with "dsch" | J228: VOA | K228: Mispronunciation | L228: Mispronunciation | M228: =IFERROR(IF(VLOOKUP(L228,'Quantification'!$A:$B,2,FALSE)&""="","Unclassified",VLOOKUP(L228,'Quantification'!$A:$B,2,FALSE)),"Unclassified") -> Major | N228: frl-carlos.alexander@pocketfm.com | O228: Issues found in raw | P228: =IF(OR(O228="Issues found in master",O228="Final master"),"Master",IF(OR(O228="Ready for Master",O228="Issues found in raw",O228="Raw under QC",O228="Issues resolved in raw"),"Raw","-")) -> Raw | Q228: 46249.774 | R228: 2026-08 (Aug) | S228: =IF(M228="Not an error",0,IF(COUNTIFS($A$2:$A228,$A228,$D$2:$D228,$D228,$M$2:$M228,"<>Not an error")=1,1,0)) -> 0 | T228: =IF(M228<>"Major",0,IF(COUNTIFS($A$2:$A228,$A228,$D$2:$D228,$D228,$M$2:$M228,"Major")=1,1,0)) -> 0 | U228: =IF(M228<>"Minor",0,IF(COUNTIFS($A$2:$A228,$A228,$D$2:$D228,$D228,$M$2:$M228,"Minor")=1,1,0)) -> 0
A229: 87dfd458f8a24d7bbd0829af61d48e90284c3786 | B229: Brahmyodha : The Destroyer | ब्रह्मयोद्धा : द डिस्ट्रोयर | C229: Brahma Warrior: Der Zerstörer | D229: 35b8cdc91bc59c2ab335897943a68502d30d1b4a | E229: Episode 12 – Der Zorn Der Verwundeten Naga-Königin | F229: 12 | G229: 9:13-9:16 | H229: Resolved | I229: Remark: Mispronunciation Line from script: "Sturm kam auf, und die Sonne leuchtete grell." Note: der instead of die read. | J229: VOA | K229: Mispronunciation | L229: Mispronunciation | M229: =IFERROR(IF(VLOOKUP(L229,'Quantification'!$A:$B,2,FALSE)&""="","Unclassified",VLOOKUP(L229,'Quantification'!$A:$B,2,FALSE)),"Unclassified") -> Major | N229: frl-carlos.alexander@pocketfm.com | O229: Issues found in raw | P229: =IF(OR(O229="Issues found in master",O229="Final master"),"Master",IF(OR(O229="Ready for Master",O229="Issues found in raw",O229="Raw under QC",O229="Issues resolved in raw"),"Raw","-")) -> Raw | Q229: 46249.777 | R229: 2026-08 (Aug) | S229: =IF(M229="Not an error",0,IF(COUNTIFS($A$2:$A229,$A229,$D$2:$D229,$D229,$M$2:$M229,"<>Not an error")=1,1,0)) -> 1 | T229: =IF(M229<>"Major",0,IF(COUNTIFS($A$2:$A229,$A229,$D$2:$D229,$D229,$M$2:$M229,"Major")=1,1,0)) -> 1 | U229: =IF(M229<>"Minor",0,IF(COUNTIFS($A$2:$A229,$A229,$D$2:$D229,$D229,$M$2:$M229,"Minor")=1,1,0)) -> 0
A230: 87dfd458f8a24d7bbd0829af61d48e90284c3786 | B230: Brahmyodha : The Destroyer | ब्रह्मयोद्धा : द डिस्ट्रोयर | C230: Brahma Warrior: Der Zerstörer | D230: 61255703722cd16e3de6c0345b9f2e704de26efd | E230: Episode 15 – Vidyuts Erstaunliche Geschwindigkeit | F230: 15 | G230: 7:03-7:10 | H230: Resolved | I230: Remark: mispronunciation Line from script: "Um ihm die Technik vorzuführen, bat Thama den Silver Tiger, ihn mit Windkraft anzugreifen." Note: Tiger should be English in combinaton with silver. | J230: VOA | K230: Mispronunciation | L230: Mispronunciation | M230: =IFERROR(IF(VLOOKUP(L230,'Quantification'!$A:$B,2,FALSE)&""="","Unclassified",VLOOKUP(L230,'Quantification'!$A:$B,2,FALSE)),"Unclassified") -> Major | N230: frl-carlos.alexander@pocketfm.com | O230: Issues found in raw | P230: =IF(OR(O230="Issues found in master",O230="Final master"),"Master",IF(OR(O230="Ready for Master",O230="Issues found in raw",O230="Raw under QC",O230="Issues resolved in raw"),"Raw","-")) -> Raw | Q230: 46249.78 | R230: 2026-08 (Aug) | S230: =IF(M230="Not an error",0,IF(COUNTIFS($A$2:$A230,$A230,$D$2:$D230,$D230,$M$2:$M230,"<>Not an error")=1,1,0)) -> 1 | T230: =IF(M230<>"Major",0,IF(COUNTIFS($A$2:$A230,$A230,$D$2:$D230,$D230,$M$2:$M230,"Major")=1,1,0)) -> 1 | U230: =IF(M230<>"Minor",0,IF(COUNTIFS($A$2:$A230,$A230,$D$2:$D230,$D230,$M$2:$M230,"Minor")=1,1,0)) -> 0
A231: 87dfd458f8a24d7bbd0829af61d48e90284c3786 | B231: Brahmyodha : The Destroyer | ब्रह्मयोद्धा : द डिस्ट्रोयर | C231: Brahma Warrior: Der Zerstörer | D231: 61255703722cd16e3de6c0345b9f2e704de26efd | E231: Episode 15 – Vidyuts Erstaunliche Geschwindigkeit | F231: 15 | G231: 11:34-11:39 | H231: Resolved | I231: Remark: Mispronunciation Line from script: "Der Silver Tiger wird währenddessen deine Bewegungen beobachten.“ Note: TIger should be English in combinaton wih the "silver" | J231: VOA | K231: Mispronunciation | L231: Mispronunciation | M231: =IFERROR(IF(VLOOKUP(L231,'Quantification'!$A:$B,2,FALSE)&""="","Unclassified",VLOOKUP(L231,'Quantification'!$A:$B,2,FALSE)),"Unclassified") -> Major | N231: frl-carlos.alexander@pocketfm.com | O231: Issues found in raw | P231: =IF(OR(O231="Issues found in master",O231="Final master"),"Master",IF(OR(O231="Ready for Master",O231="Issues found in raw",O231="Raw under QC",O231="Issues resolved in raw"),"Raw","-")) -> Raw | Q231: 46249.78 | R231: 2026-08 (Aug) | S231: =IF(M231="Not an error",0,IF(COUNTIFS($A$2:$A231,$A231,$D$2:$D231,$D231,$M$2:$M231,"<>Not an error")=1,1,0)) -> 0 | T231: =IF(M231<>"Major",0,IF(COUNTIFS($A$2:$A231,$A231,$D$2:$D231,$D231,$M$2:$M231,"Major")=1,1,0)) -> 0 | U231: =IF(M231<>"Minor",0,IF(COUNTIFS($A$2:$A231,$A231,$D$2:$D231,$D231,$M$2:$M231,"Minor")=1,1,0)) -> 0
A232: 87dfd458f8a24d7bbd0829af61d48e90284c3786 | B232: Brahmyodha : The Destroyer | ब्रह्मयोद्धा : द डिस्ट्रोयर | C232: Brahma Warrior: Der Zerstörer | D232: 957c4aa63f4bc33cc5839cd6317f69896b78cf1f | E232: Episode 20 – Das Reich Ist in Gefahr | F232: 20 | G232: 5:58-6:00 | H232: Resolved | I232: Remark: script error Line from script: "Elder Dron warnte:" Note: Elder = Ältester | J232: VOA | K232: Script Error | L232: Script error | M232: =IFERROR(IF(VLOOKUP(L232,'Quantification'!$A:$B,2,FALSE)&""="","Unclassified",VLOOKUP(L232,'Quantification'!$A:$B,2,FALSE)),"Unclassified") -> Major | N232: frl-carlos.alexander@pocketfm.com | O232: Issues found in raw | P232: =IF(OR(O232="Issues found in master",O232="Final master"),"Master",IF(OR(O232="Ready for Master",O232="Issues found in raw",O232="Raw under QC",O232="Issues resolved in raw"),"Raw","-")) -> Raw | Q232: 46249.781 | R232: 2026-08 (Aug) | S232: =IF(M232="Not an error",0,IF(COUNTIFS($A$2:$A232,$A232,$D$2:$D232,$D232,$M$2:$M232,"<>Not an error")=1,1,0)) -> 1 | T232: =IF(M232<>"Major",0,IF(COUNTIFS($A$2:$A232,$A232,$D$2:$D232,$D232,$M$2:$M232,"Major")=1,1,0)) -> 1 | U232: =IF(M232<>"Minor",0,IF(COUNTIFS($A$2:$A232,$A232,$D$2:$D232,$D232,$M$2:$M232,"Minor")=1,1,0)) -> 0
... A248: 5928a0f843af5964c0f4a5eb3efd23879b0b93d4 | B248: BRAHMYODHA (Writer Ver.) | C248: Viggo Und Die Macht Der Runen | D248: 3771244779baf78373d673a72d3d90357c8e5e57 | E248: Episode 43 - Die Einstige Königin | F248: 43 | G248: 0:20-0:27 | H248: Pending | I248: Nanna and Solveigh should be mentioned as well, since they are still alive and part of the winning team - line from script: "Sie meldeten die glorreichen Sieger nach oben: Dahg, Illwa, Wiggo, Liv und Prinzessin Sihgrun. " | J248: AI | K248: Script error | L248: Script error | M248: =IFERROR(IF(VLOOKUP(L248,'Quantification'!$A:$B,2,FALSE)&""="","Unclassified",VLOOKUP(L248,'Quantification'!$A:$B,2,FALSE)),"Unclassified") -> Major | N248: frl-yaren.gulsoy@pocketfm.com | O248: Issues found in raw | P248: =IF(OR(O248="Issues found in master",O248="Final master"),"Master",IF(OR(O248="Ready for Master",O248="Issues found in raw",O248="Raw under QC",O248="Issues resolved in raw"),"Raw","-")) -> Raw | Q248: 46290.562 | R248: 2026-09 (Sept) | S248: =IF(M248="Not an error",0,IF(COUNTIFS($A$2:$A248,$A248,$D$2:$D248,$D248,$M$2:$M248,"<>Not an error")=1,1,0)) -> 1 | T248: =IF(M248<>"Major",0,IF(COUNTIFS($A$2:$A248,$A248,$D$2:$D248,$D248,$M$2:$M248,"Major")=1,1,0)) -> 1 | U248: =IF(M248<>"Minor",0,IF(COUNTIFS($A$2:$A248,$A248,$D$2:$D248,$D248,$M$2:$M248,"Minor")=1,1,0)) -> 0
A249: 5928a0f843af5964c0f4a5eb3efd23879b0b93d4 | B249: BRAHMYODHA (Writer Ver.) | C249: Viggo Und Die Macht Der Runen | D249: 78202329a06ff90a680828bd89895ab26aa196bb | E249: Episode 46 - Hinter Verschlossenen Türen | F249: 46 | G249: 5:03-5:10 | H249: Pending | I249: It should be more than that: Wiggo, Illwa, Dahg, Liv, Sighrun, Nanna and Solveig (those two are often left out for no reason) - line from script: "„Du weißt doch, dass nach dieser Königsprobe die fünf Sieger, es sind weniger als in jedem anderen Jahr, auf die weitere Reise gehen." | J249: AI | K249: Script error | L249: Script error | M249: =IFERROR(IF(VLOOKUP(L249,'Quantification'!$A:$B,2,FALSE)&""="","Unclassified",VLOOKUP(L249,'Quantification'!$A:$B,2,FALSE)),"Unclassified") -> Major | P249: =IF(OR(O249="Issues found in master",O249="Final master"),"Master",IF(OR(O249="Ready for Master",O249="Issues found in raw",O249="Raw under QC",O249="Issues resolved in raw"),"Raw","-")) -> - | Q249: 46290.562 | R249: 2026-09 (Sept) | S249: =IF(M249="Not an error",0,IF(COUNTIFS($A$2:$A249,$A249,$D$2:$D249,$D249,$M$2:$M249,"<>Not an error")=1,1,0)) -> 1 | T249: =IF(M249<>"Major",0,IF(COUNTIFS($A$2:$A249,$A249,$D$2:$D249,$D249,$M$2:$M249,"Major")=1,1,0)) -> 1 | U249: =IF(M249<>"Minor",0,IF(COUNTIFS($A$2:$A249,$A249,$D$2:$D249,$D249,$M$2:$M249,"Minor")=1,1,0)) -> 0
A250: 5928a0f843af5964c0f4a5eb3efd23879b0b93d4 | B250: BRAHMYODHA (Writer Ver.) | C250: Viggo Und Die Macht Der Runen | D250: e0976539643491e9fb6bef99d3cbb0bbbf6de100 | E250: Episode 48 - Folge Dem Blauen Licht | F250: 48 | G250: 3:30-3:34 | H250: Pending | I250: the same plot hole as before. It should be seven winners (Viggo, Illwa, Dahg, Liv, Sihgrun, Nanna, Solveig) - line from script: "Soweit ich spüre, sind in diesem Jahr nur fünf gekommen." | J250: AI | K250: Script error | L250: Script error | M250: =IFERROR(IF(VLOOKUP(L250,'Quantification'!$A:$B,2,FALSE)&""="","Unclassified",VLOOKUP(L250,'Quantification'!$A:$B,2,FALSE)),"Unclassified") -> Major | N250: frl-yaren.gulsoy@pocketfm.com | O250: Issues found in raw | P250: =IF(OR(O250="Issues found in master",O250="Final master"),"Master",IF(OR(O250="Ready for Master",O250="Issues found in raw",O250="Raw under QC",O250="Issues resolved in raw"),"Raw","-")) -> Raw | Q250: 46290.562 | R250: 2026-09 (Sept) | S250: =IF(M250="Not an error",0,IF(COUNTIFS($A$2:$A250,$A250,$D$2:$D250,$D250,$M$2:$M250,"<>Not an error")=1,1,0)) -> 1 | T250: =IF(M250<>"Major",0,IF(COUNTIFS($A$2:$A250,$A250,$D$2:$D250,$D250,$M$2:$M250,"Major")=1,1,0)) -> 1 | U250: =IF(M250<>"Minor",0,IF(COUNTIFS($A$2:$A250,$A250,$D$2:$D250,$D250,$M$2:$M250,"Minor")=1,1,0)) -> 0
A251: 5928a0f843af5964c0f4a5eb3efd23879b0b93d4 | B251: BRAHMYODHA (Writer Ver.) | C251: Viggo Und Die Macht Der Runen | D251: e0976539643491e9fb6bef99d3cbb0bbbf6de100 | E251: Episode 48 - Folge Dem Blauen Licht | F251: 48 | G251: 4:27-4:30 | H251: Pending | I251: The same plot hole as before. It should be seven winners (Viggo, Illwa, Dahg, Liv, Sihgrun, Nanna, Solveig) - line from script: "Statt zehn Kriegern standen nur noch fünf im letzten Teil." | J251: AI | K251: Script error | L251: Script error | M251: =IFERROR(IF(VLOOKUP(L251,'Quantification'!$A:$B,2,FALSE)&""="","Unclassified",VLOOKUP(L251,'Quantification'!$A:$B,2,FALSE)),"Unclassified") -> Major | N251: frl-yaren.gulsoy@pocketfm.com | O251: Issues found in raw | P251: =IF(OR(O251="Issues found in master",O251="Final master"),"Master",IF(OR(O251="Ready for Master",O251="Issues found in raw",O251="Raw under QC",O251="Issues resolved in raw"),"Raw","-")) -> Raw | Q251: 46290.562 | R251: 2026-09 (Sept) | S251: =IF(M251="Not an error",0,IF(COUNTIFS($A$2:$A251,$A251,$D$2:$D251,$D251,$M$2:$M251,"<>Not an error")=1,1,0)) -> 0 | T251: =IF(M251<>"Major",0,IF(COUNTIFS($A$2:$A251,$A251,$D$2:$D251,$D251,$M$2:$M251,"Major")=1,1,0)) -> 0 | U251: =IF(M251<>"Minor",0,IF(COUNTIFS($A$2:$A251,$A251,$D$2:$D251,$D251,$M$2:$M251,"Minor")=1,1,0)) -> 0
A252: 5928a0f843af5964c0f4a5eb3efd23879b0b93d4 | B252: BRAHMYODHA (Writer Ver.) | C252: Viggo Und Die Macht Der Runen | D252: eac2b47f04f0b1794037de1e944f01b30bd9ba1f | E252: Episode 50 - Halb Schlange, Halb Mensch | F252: 50 | G252: 1:43-1:52 | H252: Pending | I252: Grammar. The sentence doesn't make sense - line from script: "Als während des Kampfes mit Eirik ein heftiger Stoß durch den Ring gefahren war, um Wiggo zu schützen, doch da war Eirik bereits geflohen. " | J252: AI | K252: Script error | L252: Script error | M252: =IFERROR(IF(VLOOKUP(L252,'Quantification'!$A:$B,2,FALSE)&""="","Unclassified",VLOOKUP(L252,'Quantification'!$A:$B,2,FALSE)),"Unclassified") -> Major | N252: frl-yaren.gulsoy@pocketfm.com | O252: Issues found in raw | P252: =IF(OR(O252="Issues found in master",O252="Final master"),"Master",IF(OR(O252="Ready for Master",O252="Issues found in raw",O252="Raw under QC",O252="Issues resolved in raw"),"Raw","-")) -> Raw | Q252: 46290.563 | R252: 2026-09 (Sept) | S252: =IF(M252="Not an error",0,IF(COUNTIFS($A$2:$A252,$A252,$D$2:$D252,$D252,$M$2:$M252,"<>Not an error")=1,1,0)) -> 1 | T252: =IF(M252<>"Major",0,IF(COUNTIFS($A$2:$A252,$A252,$D$2:$D252,$D252,$M$2:$M252,"Major")=1,1,0)) -> 1 | U252: =IF(M252<>"Minor",0,IF(COUNTIFS($A$2:$A252,$A252,$D$2:$D252,$D252,$M$2:$M252,"Minor")=1,1,0)) -> 0
A253: 4baec2ac0f23302985d2ad577e111504bd88c99c | B253: Bride of a dragon | C253: Die Braut Des Drachenkönigs | D253: 77a2d357aca4db184c28e2072e3ab7ed5e54da32 | E253: Episode 1: Der Drachenkönig | F253: 1 | G253: 8:38-8:39 | H253: Ignore | I253: it would sound better to say "auf mich zukommen" - line from script: "Auf mich zu." | J253: AI | K253: Script error | L253: Script error | M253: =IFERROR(IF(VLOOKUP(L253,'Quantification'!$A:$B,2,FALSE)&""="","Unclassified",VLOOKUP(L253,'Quantification'!$A:$B,2,FALSE)),"Unclassified") -> Major | N253: frl-esma.gulsoy@pocketfm.com | O253: Raw under QC | P253: =IF(OR(O253="Issues found in master",O253="Final master"),"Master",IF(OR(O253="Ready for Master",O253="Issues found in raw",O253="Raw under QC",O253="Issues resolved in raw"),"Raw","-")) -> Raw | Q253: 46286.307 | R253: 2026-09 (Sept) | S253: =IF(M253="Not an error",0,IF(COUNTIFS($A$2:$A253,$A253,$D$2:$D253,$D253,$M$2:$M253,"<>Not an error")=1,1,0)) -> 1 | T253: =IF(M253<>"Major",0,IF(COUNTIFS($A$2:$A253,$A253,$D$2:$D253,$D253,$M$2:$M253,"Major")=1,1,0)) -> 1 | U253: =IF(M253<>"Minor",0,IF(COUNTIFS($A$2:$A253,$A253,$D$2:$D253,$D253,$M$2:$M253,"Minor")=1,1,0)) -> 0
A254: 4baec2ac0f23302985d2ad577e111504bd88c99c | B254: Bride of a dragon | C254: Die Braut Des Drachenkönigs | D254: 77a2d357aca4db184c28e2072e3ab7ed5e54da32 | E254: Episode 1: Der Drachenkönig | F254: 1 | G254: 9:42-9:45 | H254: Ignore | I254: The name of the King of Dragon should be introduced beforehand. "Damons Stirnrunzeln vertiefte sich, als er zu Gareth zurückblickte." It could be introduced in line 7:50 " Ich hatte den Drachenkönig Damon noch nie zuvor gesehen." for example. | J254: AI | K254: Script error | L254: Script error | M254: =IFERROR(IF(VLOOKUP(L254,'Quantification'!$A:$B,2,FALSE)&""="","Unclassified",VLOOKUP(L254,'Quantification'!$A:$B,2,FALSE)),"Unclassified") -> Major | N254: frl-esma.gulsoy@pocketfm.com | O254: Issues found in raw | P254: =IF(OR(O254="Issues found in master",O254="Final master"),"Master",IF(OR(O254="Ready for Master",O254="Issues found in raw",O254="Raw under QC",O254="Issues resolved in raw"),"Raw","-")) -> Raw | Q254: 46286.307 | R254: 2026-09 (Sept) | S254: =IF(M254="Not an error",0,IF(COUNTIFS($A$2:$A254,$A254,$D$2:$D254,$D254,$M$2:$M254,"<>Not an error")=1,1,0)) -> 0 | T254: =IF(M254<>"Major",0,IF(COUNTIFS($A$2:$A254,$A254,$D$2:$D254,$D254,$M$2:$M254,"Major")=1,1,0)) -> 0 | U254: =IF(M254<>"Minor",0,IF(COUNTIFS($A$2:$A254,$A254,$D$2:$D254,$D254,$M$2:$M254,"Minor")=1,1,0)) -> 0
A255: 4baec2ac0f23302985d2ad577e111504bd88c99c | B255: Bride of a dragon | C255: Die Braut Des Drachenkönigs | D255: 3b575c6c396ce4e062eb1d58810a9f1b5b001195 | E255: Episode 3: Die Feuerprobe | F255: 3 | G255: 1:47-1:49 | H255: Resolved | I255: Mispronunciation of the word (ihnen) - Line of script: "Die Augen von ihnen allen." | J255: VOA | K255: Mispronunciation | L255: Mispronunciation | M255: =IFERROR(IF(VLOOKUP(L255,'Quantification'!$A:$B,2,FALSE)&""="","Unclassified",VLOOKUP(L255,'Quantification'!$A:$B,2,FALSE)),"Unclassified") -> Major | N255: frl-esma.gulsoy@pocketfm.com | O255: Issues found in raw | P255: =IF(OR(O255="Issues found in master",O255="Final master"),"Master",IF(OR(O255="Ready for Master",O255="Issues found in raw",O255="Raw under QC",O255="Issues resolved in raw"),"Raw","-")) -> Raw | Q255: 46286.324 | R255: 2026-09 (Sept) | S255: =IF(M255="Not an error",0,IF(COUNTIFS($A$2:$A255,$A255,$D$2:$D255,$D255,$M$2:$M255,"<>Not an error")=1,1,0)) -> 1 | T255: =IF(M255<>"Major",0,IF(COUNTIFS($A$2:$A255,$A255,$D$2:$D255,$D255,$M$2:$M255,"Major")=1,1,0)) -> 1 | U255: =IF(M255<>"Minor",0,IF(COUNTIFS($A$2:$A255,$A255,$D$2:$D255,$D255,$M$2:$M255,"Minor")=1,1,0)) -> 0
A256: 4baec2ac0f23302985d2ad577e111504bd88c99c | B256: Bride of a dragon | C256: Die Braut Des Drachenkönigs | D256: 3b575c6c396ce4e062eb1d58810a9f1b5b001195 | E256: Episode 3: Die Feuerprobe | F256: 3 | G256: 1:50-1:54 | H256: Resolved | I256: Mispronunciation of the word (ihnen) - Line of script: "Wartend, was aus der gefallenen Prinzessin werden würde, die vor ihnen kniete." | J256: VOA | K256: Modulation | L256: Modulation | M256: =IFERROR(IF(VLOOKUP(L256,'Quantification'!$A:$B,2,FALSE)&""="","Unclassified",VLOOKUP(L256,'Quantification'!$A:$B,2,FALSE)),"Unclassified") -> Minor | N256: frl-esma.gulsoy@pocketfm.com | O256: Issues found in raw | P256: =IF(OR(O256="Issues found in master",O256="Final master"),"Master",IF(OR(O256="Ready for Master",O256="Issues found in raw",O256="Raw under QC",O256="Issues resolved in raw"),"Raw","-")) -> Raw | Q256: 46286.324 | R256: 2026-09 (Sept) | S256: =IF(M256="Not an error",0,IF(COUNTIFS($A$2:$A256,$A256,$D$2:$D256,$D256,$M$2:$M256,"<>Not an error")=1,1,0)) -> 0 | T256: =IF(M256<>"Major",0,IF(COUNTIFS($A$2:$A256,$A256,$D$2:$D256,$D256,$M$2:$M256,"Major")=1,1,0)) -> 0 | U256: =IF(M256<>"Minor",0,IF(COUNTIFS($A$2:$A256,$A256,$D$2:$D256,$D256,$M$2:$M256,"Minor")=1,1,0)) -> 1
A257: 4baec2ac0f23302985d2ad577e111504bd88c99c | B257: Bride of a dragon | C257: Die Braut Des Drachenkönigs | D257: 3b575c6c396ce4e062eb1d58810a9f1b5b001195 | E257: Episode 3: Die Feuerprobe | F257: 3 | G257: 1:06-1:07 | H257: Resolved | I257: Mispronunciation of the name "Selene". The name should be pronounced in English (like "Celine"). - Line of script: "Genug, Selene." | J257: VOA | K257: Mispronunciation | L257: Mispronunciation | M257: =IFERROR(IF(VLOOKUP(L257,'Quantification'!$A:$B,2,FALSE)&""="","Unclassified",VLOOKUP(L257,'Quantification'!$A:$B,2,FALSE)),"Unclassified") -> Major | N257: frl-esma.gulsoy@pocketfm.com | O257: Issues found in raw | P257: =IF(OR(O257="Issues found in master",O257="Final master"),"Master",IF(OR(O257="Ready for Master",O257="Issues found in raw",O257="Raw under QC",O257="Issues resolved in raw"),"Raw","-")) -> Raw | Q257: 46286.324 | R257: 2026-09 (Sept) | S257: =IF(M257="Not an error",0,IF(COUNTIFS($A$2:$A257,$A257,$D$2:$D257,$D257,$M$2:$M257,"<>Not an error")=1,1,0)) -> 0 | T257: =IF(M257<>"Major",0,IF(COUNTIFS($A$2:$A257,$A257,$D$2:$D257,$D257,$M$2:$M257,"Major")=1,1,0)) -> 0 | U257: =IF(M257<>"Minor",0,IF(COUNTIFS($A$2:$A257,$A257,$D$2:$D257,$D257,$M$2:$M257,"Minor")=1,1,0)) -> 0
A258: 4baec2ac0f23302985d2ad577e111504bd88c99c | B258: Bride of a dragon | C258: Die Braut Des Drachenkönigs | D258: 3b575c6c396ce4e062eb1d58810a9f1b5b001195 | E258: Episode 3: Die Feuerprobe | F258: 3 | G258: 1:12-1:14 | H258: Resolved | I258: Mispronunciation of the name "Selene". The name should be pronounced in English (like "Celine"). - Line of script: "Selene erstarrte mitten in der Bewegung." | J258: VOA | K258: Mispronunciation | L258: Mispronunciation | M258: =IFERROR(IF(VLOOKUP(L258,'Quantification'!$A:$B,2,FALSE)&""="","Unclassified",VLOOKUP(L258,'Quantification'!$A:$B,2,FALSE)),"Unclassified") -> Major | N258: frl-esma.gulsoy@pocketfm.com | O258: Issues found in raw | P258: =IF(OR(O258="Issues found in master",O258="Final master"),"Master",IF(OR(O258="Ready for Master",O258="Issues found in raw",O258="Raw under QC",O258="Issues resolved in raw"),"Raw","-")) -> Raw | Q258: 46286.324 | R258: 2026-09 (Sept) | S258: =IF(M258="Not an error",0,IF(COUNTIFS($A$2:$A258,$A258,$D$2:$D258,$D258,$M$2:$M258,"<>Not an error")=1,1,0)) -> 0 | T258: =IF(M258<>"Major",0,IF(COUNTIFS($A$2:$A258,$A258,$D$2:$D258,$D258,$M$2:$M258,"Major")=1,1,0)) -> 0 | U258: =IF(M258<>"Minor",0,IF(COUNTIFS($A$2:$A258,$A258,$D$2:$D258,$D258,$M$2:$M258,"Minor")=1,1,0)) -> 0
A259: 4baec2ac0f23302985d2ad577e111504bd88c99c | B259: Bride of a dragon | C259: Die Braut Des Drachenkönigs | D259: 3b575c6c396ce4e062eb1d58810a9f1b5b001195 | E259: Episode 3: Die Feuerprobe | F259: 3 | G259: 3:13-3:15 | H259: Resolved | I259: Mispronunciation of the name "Selene". The name should be pronounced in English (like "Celine"). - Line of script: "Ich beobachtete, wie sich Selenes Gesicht veränderte." | J259: VOA | K259: Mispronunciation | L259: Mispronunciation | M259: =IFERROR(IF(VLOOKUP(L259,'Quantification'!$A:$B,2,FALSE)&""="","Unclassified",VLOOKUP(L259,'Quantification'!$A:$B,2,FALSE)),"Unclassified") -> Major | N259: frl-esma.gulsoy@pocketfm.com | O259: Issues found in raw | P259: =IF(OR(O259="Issues found in master",O259="Final master"),"Master",IF(OR(O259="Ready for Master",O259="Issues found in raw",O259="Raw under QC",O259="Issues resolved in raw"),"Raw","-")) -> Raw | Q259: 46286.324 | R259: 2026-09 (Sept) | S259: =IF(M259="Not an error",0,IF(COUNTIFS($A$2:$A259,$A259,$D$2:$D259,$D259,$M$2:$M259,"<>Not an error")=1,1,0)) -> 0 | T259: =IF(M259<>"Major",0,IF(COUNTIFS($A$2:$A259,$A259,$D$2:$D259,$D259,$M$2:$M259,"Major")=1,1,0)) -> 0 | U259: =IF(M259<>"Minor",0,IF(COUNTIFS($A$2:$A259,$A259,$D$2:$D259,$D259,$M$2:$M259,"Minor")=1,1,0)) -> 0
A260: 4baec2ac0f23302985d2ad577e111504bd88c99c | B260: Bride of a dragon | C260: Die Braut Des Drachenkönigs | D260: 3b575c6c396ce4e062eb1d58810a9f1b5b001195 | E260: Episode 3: Die Feuerprobe | F260: 3 | G260: 6:25-6:29 | H260: Resolved | I260: Mispronunciation of the name "Selene". The name should be pronounced in English (like "Celine"). - Line of script: "Und du hast bereits Selene, um all deine Bedürfnisse zu befriedigen." | J260: VOA | K260: Mispronunciation | L260: Mispronunciation | M260: =IFERROR(IF(VLOOKUP(L260,'Quantification'!$A:$B,2,FALSE)&""="","Unclassified",VLOOKUP(L260,'Quantification'!$A:$B,2,FALSE)),"Unclassified") -> Major | N260: frl-esma.gulsoy@pocketfm.com | O260: Issues found in raw | P260: =IF(OR(O260="Issues found in master",O260="Final master"),"Master",IF(OR(O260="Ready for Master",O260="Issues found in raw",O260="Raw under QC",O260="Issues resolved in raw"),"Raw","-")) -> Raw | Q260: 46286.324 | R260: 2026-09 (Sept) | S260: =IF(M260="Not an error",0,IF(COUNTIFS($A$2:$A260,$A260,$D$2:$D260,$D260,$M$2:$M260,"<>Not an error")=1,1,0)) -> 0 | T260: =IF(M260<>"Major",0,IF(COUNTIFS($A$2:$A260,$A260,$D$2:$D260,$D260,$M$2:$M260,"Major")=1,1,0)) -> 0 | U260: =IF(M260<>"Minor",0,IF(COUNTIFS($A$2:$A260,$A260,$D$2:$D260,$D260,$M$2:$M260,"Minor")=1,1,0)) -> 0
A261: 4baec2ac0f23302985d2ad577e111504bd88c99c | B261: Bride of a dragon | C261: Die Braut Des Drachenkönigs | D261: 3b575c6c396ce4e062eb1d58810a9f1b5b001195 | E261: Episode 3: Die Feuerprobe | F261: 3 | G261: 6:34-6:38 | H261: Resolved | I261: Mispronunciation of the name "Selene". The name should be pronounced in English (like "Celine"). - Line of script: "Sie hat nicht einmal das Zeug zur Königin“, zischte Selene von ihrem Platz, ihre Stimme triefte vor Verachtung. | J261: VOA | K261: Mispronunciation | L261: Mispronunciation | M261: =IFERROR(IF(VLOOKUP(L261,'Quantification'!$A:$B,2,FALSE)&""="","Unclassified",VLOOKUP(L261,'Quantification'!$A:$B,2,FALSE)),"Unclassified") -> Major | N261: frl-esma.gulsoy@pocketfm.com | O261: Issues found in raw | P261: =IF(OR(O261="Issues found in master",O261="Final master"),"Master",IF(OR(O261="Ready for Master",O261="Issues found in raw",O261="Raw under QC",O261="Issues resolved in raw"),"Raw","-")) -> Raw | Q261: 46286.324 | R261: 2026-09 (Sept) | S261: =IF(M261="Not an error",0,IF(COUNTIFS($A$2:$A261,$A261,$D$2:$D261,$D261,$M$2:$M261,"<>Not an error")=1,1,0)) -> 0 | T261: =IF(M261<>"Major",0,IF(COUNTIFS($A$2:$A261,$A261,$D$2:$D261,$D261,$M$2:$M261,"Major")=1,1,0)) -> 0 | U261: =IF(M261<>"Minor",0,IF(COUNTIFS($A$2:$A261,$A261,$D$2:$D261,$D261,$M$2:$M261,"Minor")=1,1,0)) -> 0
... A721: efa111b397877a29364b57266d879e11bff528fd | B721: Hacking the Mafia's Heart | C721: Mafiaherz Gehackt | D721: 05d488ebe31b74b9e67e941f888fa2d00abccd6b | E721: Episode 8: Ihre Erste Nacht | F721: 8 | G721: 7:10-7:16 | H721: Resolved | I721: VA says liyama - "Liyana schlug langsam die Augen auf, während das sanfte Morgenlicht durch die schweren Vorhänge sickerte." | J721: VOA | K721: Mispronunciation | L721: Mispronunciation | M721: =IFERROR(IF(VLOOKUP(L721,'Quantification'!$A:$B,2,FALSE)&""="","Unclassified",VLOOKUP(L721,'Quantification'!$A:$B,2,FALSE)),"Unclassified") -> Major | N721: frl-denis.sobol@pocketfm.com | O721: Issues found in raw | P721: =IF(OR(O721="Issues found in master",O721="Final master"),"Master",IF(OR(O721="Ready for Master",O721="Issues found in raw",O721="Raw under QC",O721="Issues resolved in raw"),"Raw","-")) -> Raw | Q721: 46288.54 | R721: 2026-09 (Sept) | S721: =IF(M721="Not an error",0,IF(COUNTIFS($A$2:$A721,$A721,$D$2:$D721,$D721,$M$2:$M721,"<>Not an error")=1,1,0)) -> 1 | T721: =IF(M721<>"Major",0,IF(COUNTIFS($A$2:$A721,$A721,$D$2:$D721,$D721,$M$2:$M721,"Major")=1,1,0)) -> 1 | U721: =IF(M721<>"Minor",0,IF(COUNTIFS($A$2:$A721,$A721,$D$2:$D721,$D721,$M$2:$M721,"Minor")=1,1,0)) -> 0
A722: efa111b397877a29364b57266d879e11bff528fd | B722: Hacking the Mafia's Heart | C722: Mafiaherz Gehackt | D722: 534277e3f5092108414abe5176ce2bb08ac3b092 | E722: Episode 14: Wütende Lippenstift-Dame | F722: 14 | H722: Ignore | I722: episode title has to be "Wütende Lippenstift Dame" instead | J722: AI | K722: Script error | L722: Script error | M722: =IFERROR(IF(VLOOKUP(L722,'Quantification'!$A:$B,2,FALSE)&""="","Unclassified",VLOOKUP(L722,'Quantification'!$A:$B,2,FALSE)),"Unclassified") -> Major | N722: frl-denis.sobol@pocketfm.com | O722: Issues found in raw | P722: =IF(OR(O722="Issues found in master",O722="Final master"),"Master",IF(OR(O722="Ready for Master",O722="Issues found in raw",O722="Raw under QC",O722="Issues resolved in raw"),"Raw","-")) -> Raw | Q722: 46287.656 | R722: 2026-09 (Sept) | S722: =IF(M722="Not an error",0,IF(COUNTIFS($A$2:$A722,$A722,$D$2:$D722,$D722,$M$2:$M722,"<>Not an error")=1,1,0)) -> 1 | T722: =IF(M722<>"Major",0,IF(COUNTIFS($A$2:$A722,$A722,$D$2:$D722,$D722,$M$2:$M722,"Major")=1,1,0)) -> 1 | U722: =IF(M722<>"Minor",0,IF(COUNTIFS($A$2:$A722,$A722,$D$2:$D722,$D722,$M$2:$M722,"Minor")=1,1,0)) -> 0
A723: efa111b397877a29364b57266d879e11bff528fd | B723: Hacking the Mafia's Heart | C723: Mafiaherz Gehackt | D723: 87e8ce7967caa37f4822f5172f895709a9d37c2f | E723: Episode 15: Zehn Schritte Voraus | F723: 15 | G723: 1:34-1:41 | H723: Resolved | I723: V i p-raum -> Vip-Raum (more natural in german) - Sie räkelte sich in einem privaten V i P-Raum, der nur aus teuren Möbeln und gedämpftem, goldenem Licht zu bestehen schien. | J723: AI | K723: Script error | L723: Script error | M723: =IFERROR(IF(VLOOKUP(L723,'Quantification'!$A:$B,2,FALSE)&""="","Unclassified",VLOOKUP(L723,'Quantification'!$A:$B,2,FALSE)),"Unclassified") -> Major | N723: frl-denis.sobol@pocketfm.com | O723: Issues found in raw | P723: =IF(OR(O723="Issues found in master",O723="Final master"),"Master",IF(OR(O723="Ready for Master",O723="Issues found in raw",O723="Raw under QC",O723="Issues resolved in raw"),"Raw","-")) -> Raw | Q723: 46290.167 | R723: 2026-09 (Sept) | S723: =IF(M723="Not an error",0,IF(COUNTIFS($A$2:$A723,$A723,$D$2:$D723,$D723,$M$2:$M723,"<>Not an error")=1,1,0)) -> 1 | T723: =IF(M723<>"Major",0,IF(COUNTIFS($A$2:$A723,$A723,$D$2:$D723,$D723,$M$2:$M723,"Major")=1,1,0)) -> 1 | U723: =IF(M723<>"Minor",0,IF(COUNTIFS($A$2:$A723,$A723,$D$2:$D723,$D723,$M$2:$M723,"Minor")=1,1,0)) -> 0
A724: efa111b397877a29364b57266d879e11bff528fd | B724: Hacking the Mafia's Heart | C724: Mafiaherz Gehackt | D724: b4a5cbcbdb62e47a7c82eb383b6f9d2ebb6ff88c | E724: Episode 18: Lorenzos Schutz | F724: 18 | G724: 5:53-5:58 | H724: Resolved | I724: VA says Liyama - "Liyana, die von der unterschwelligen Spannung nichts mitbekam, nickte währenddessen bereits ein." | J724: VOA | K724: Mispronunciation | L724: Mispronunciation | M724: =IFERROR(IF(VLOOKUP(L724,'Quantification'!$A:$B,2,FALSE)&""="","Unclassified",VLOOKUP(L724,'Quantification'!$A:$B,2,FALSE)),"Unclassified") -> Major | N724: frl-denis.sobol@pocketfm.com | O724: Issues found in raw | P724: =IF(OR(O724="Issues found in master",O724="Final master"),"Master",IF(OR(O724="Ready for Master",O724="Issues found in raw",O724="Raw under QC",O724="Issues resolved in raw"),"Raw","-")) -> Raw | Q724: 46290.167 | R724: 2026-09 (Sept) | S724: =IF(M724="Not an error",0,IF(COUNTIFS($A$2:$A724,$A724,$D$2:$D724,$D724,$M$2:$M724,"<>Not an error")=1,1,0)) -> 1 | T724: =IF(M724<>"Major",0,IF(COUNTIFS($A$2:$A724,$A724,$D$2:$D724,$D724,$M$2:$M724,"Major")=1,1,0)) -> 1 | U724: =IF(M724<>"Minor",0,IF(COUNTIFS($A$2:$A724,$A724,$D$2:$D724,$D724,$M$2:$M724,"Minor")=1,1,0)) -> 0
A725: efa111b397877a29364b57266d879e11bff528fd | B725: Hacking the Mafia's Heart | C725: Mafiaherz Gehackt | D725: 7a2136f3f45a746cfa2c912db072446ca8421e63 | E725: Episode 22: Hacking-Herausforderung | F725: 22 | G725: 0:00-0:22 | H725: Resolved | I725: the doctor that examined her in episode 20 was explicitly male, unless in the meantime she was examined by another doctor that is female, but there's no mention of that; possibly a mistake but it's unclear - „Wie geht es ihr?“, fragte Lorenzo erneut, seine Stimme leiser und angespannter. Die Hausangestellte, die in der Nähe gewartet hatte, antwortete rasch. „Es geht ihr wieder gut, Herr. Die Ärztin meinte, es war nur leichtes Fieber, ausgelöst durch Überarbeitung und Stress. Ihre Temperatur ist wieder normal, aber sie ist noch sehr schwach. Sie sagte, sie brauche viel Ruhe.“ | J725: AI | K725: Script error | L725: Script error | M725: =IFERROR(IF(VLOOKUP(L725,'Quantification'!$A:$B,2,FALSE)&""="","Unclassified",VLOOKUP(L725,'Quantification'!$A:$B,2,FALSE)),"Unclassified") -> Major | N725: frl-denis.sobol@pocketfm.com | O725: Issues found in raw | P725: =IF(OR(O725="Issues found in master",O725="Final master"),"Master",IF(OR(O725="Ready for Master",O725="Issues found in raw",O725="Raw under QC",O725="Issues resolved in raw"),"Raw","-")) -> Raw | Q725: 46290.167 | R725: 2026-09 (Sept) | S725: =IF(M725="Not an error",0,IF(COUNTIFS($A$2:$A725,$A725,$D$2:$D725,$D725,$M$2:$M725,"<>Not an error")=1,1,0)) -> 1 | T725: =IF(M725<>"Major",0,IF(COUNTIFS($A$2:$A725,$A725,$D$2:$D725,$D725,$M$2:$M725,"Major")=1,1,0)) -> 1 | U725: =IF(M725<>"Minor",0,IF(COUNTIFS($A$2:$A725,$A725,$D$2:$D725,$D725,$M$2:$M725,"Minor")=1,1,0)) -> 0
A726: efa111b397877a29364b57266d879e11bff528fd | B726: Hacking the Mafia's Heart | C726: Mafiaherz Gehackt | D726: 7a2136f3f45a746cfa2c912db072446ca8421e63 | E726: Episode 22: Hacking-Herausforderung | F726: 22 | G726: 7:13-7:19 | H726: Resolved | I726: VA says liyama - "Liyana blinzelte auf den Bildschirm, für einen Moment überfordert, bevor sich ein Lächeln auf ihre Lippen stahl." | J726: VOA | K726: Mispronunciation | L726: Mispronunciation | M726: =IFERROR(IF(VLOOKUP(L726,'Quantification'!$A:$B,2,FALSE)&""="","Unclassified",VLOOKUP(L726,'Quantification'!$A:$B,2,FALSE)),"Unclassified") -> Major | N726: frl-denis.sobol@pocketfm.com | O726: Issues found in raw | P726: =IF(OR(O726="Issues found in master",O726="Final master"),"Master",IF(OR(O726="Ready for Master",O726="Issues found in raw",O726="Raw under QC",O726="Issues resolved in raw"),"Raw","-")) -> Raw | Q726: 46290.167 | R726: 2026-09 (Sept) | S726: =IF(M726="Not an error",0,IF(COUNTIFS($A$2:$A726,$A726,$D$2:$D726,$D726,$M$2:$M726,"<>Not an error")=1,1,0)) -> 0 | T726: =IF(M726<>"Major",0,IF(COUNTIFS($A$2:$A726,$A726,$D$2:$D726,$D726,$M$2:$M726,"Major")=1,1,0)) -> 0 | U726: =IF(M726<>"Minor",0,IF(COUNTIFS($A$2:$A726,$A726,$D$2:$D726,$D726,$M$2:$M726,"Minor")=1,1,0)) -> 0
A727: efa111b397877a29364b57266d879e11bff528fd | B727: Hacking the Mafia's Heart | C727: Mafiaherz Gehackt | D727: 7a2136f3f45a746cfa2c912db072446ca8421e63 | E727: Episode 22: Hacking-Herausforderung | F727: 22 | G727: 8:16-8:21 | H727: Resolved | I727: the term VPN doesn't make sense here, it's not a physical object. they might have meant that they would bring a device like a travel router that connects to a VPN, even then a tech savvy person would never put it like that - „Ich bringe Snacks und ein V P N mit. Wir müssen nicht mal über Hacking reden. Einfach nur chillen.“ -> „Ich bringe Snacks und ein Travel-Router mit. Wir müssen nicht mal über Hacking reden. Einfach nur chillen.“ / „Ich bringe Snacks mit. Wir müssen nicht mal über Hacking reden. Einfach nur chillen.“ | J727: AI | K727: Script error | L727: Script error | M727: =IFERROR(IF(VLOOKUP(L727,'Quantification'!$A:$B,2,FALSE)&""="","Unclassified",VLOOKUP(L727,'Quantification'!$A:$B,2,FALSE)),"Unclassified") -> Major | N727: frl-denis.sobol@pocketfm.com | O727: Issues found in raw | P727: =IF(OR(O727="Issues found in master",O727="Final master"),"Master",IF(OR(O727="Ready for Master",O727="Issues found in raw",O727="Raw under QC",O727="Issues resolved in raw"),"Raw","-")) -> Raw | Q727: 46290.167 | R727: 2026-09 (Sept) | S727: =IF(M727="Not an error",0,IF(COUNTIFS($A$2:$A727,$A727,$D$2:$D727,$D727,$M$2:$M727,"<>Not an error")=1,1,0)) -> 0 | T727: =IF(M727<>"Major",0,IF(COUNTIFS($A$2:$A727,$A727,$D$2:$D727,$D727,$M$2:$M727,"Major")=1,1,0)) -> 0 | U727: =IF(M727<>"Minor",0,IF(COUNTIFS($A$2:$A727,$A727,$D$2:$D727,$D727,$M$2:$M727,"Minor")=1,1,0)) -> 0
A728: efa111b397877a29364b57266d879e11bff528fd | B728: Hacking the Mafia's Heart | C728: Mafiaherz Gehackt | D728: 41278ca75d8226ce95f0c717593e2be76ff2b004 | E728: Episode 23: Neuanfänge | F728: 23 | G728: 5:10-5:13 | H728: Resolved | I728: VA says Abendessen-essen - „Das Abendessen ist fast fertig. Komm, gehen wir nach unten.“ | J728: VOA | K728: Mispronunciation | L728: Mispronunciation | M728: =IFERROR(IF(VLOOKUP(L728,'Quantification'!$A:$B,2,FALSE)&""="","Unclassified",VLOOKUP(L728,'Quantification'!$A:$B,2,FALSE)),"Unclassified") -> Major | N728: frl-denis.sobol@pocketfm.com | O728: Issues found in raw | P728: =IF(OR(O728="Issues found in master",O728="Final master"),"Master",IF(OR(O728="Ready for Master",O728="Issues found in raw",O728="Raw under QC",O728="Issues resolved in raw"),"Raw","-")) -> Raw | Q728: 46290.167 | R728: 2026-09 (Sept) | S728: =IF(M728="Not an error",0,IF(COUNTIFS($A$2:$A728,$A728,$D$2:$D728,$D728,$M$2:$M728,"<>Not an error")=1,1,0)) -> 1 | T728: =IF(M728<>"Major",0,IF(COUNTIFS($A$2:$A728,$A728,$D$2:$D728,$D728,$M$2:$M728,"Major")=1,1,0)) -> 1 | U728: =IF(M728<>"Minor",0,IF(COUNTIFS($A$2:$A728,$A728,$D$2:$D728,$D728,$M$2:$M728,"Minor")=1,1,0)) -> 0
A729: efa111b397877a29364b57266d879e11bff528fd | B729: Hacking the Mafia's Heart | C729: Mafiaherz Gehackt | D729: 41278ca75d8226ce95f0c717593e2be76ff2b004 | E729: Episode 23: Neuanfänge | F729: 23 | G729: 9:42-9:49 | H729: Resolved | I729: VA says Liyama - „Mir ist ein bisschen langweilig“, gab Liyana mit leiser Stimme zu. „Und ich dachte, vielleicht könnte ich etwas Neues lernen?“ | J729: VOA | K729: Mispronunciation | L729: Mispronunciation | M729: =IFERROR(IF(VLOOKUP(L729,'Quantification'!$A:$B,2,FALSE)&""="","Unclassified",VLOOKUP(L729,'Quantification'!$A:$B,2,FALSE)),"Unclassified") -> Major | N729: frl-denis.sobol@pocketfm.com | O729: Issues found in raw | P729: =IF(OR(O729="Issues found in master",O729="Final master"),"Master",IF(OR(O729="Ready for Master",O729="Issues found in raw",O729="Raw under QC",O729="Issues resolved in raw"),"Raw","-")) -> Raw | Q729: 46290.167 | R729: 2026-09 (Sept) | S729: =IF(M729="Not an error",0,IF(COUNTIFS($A$2:$A729,$A729,$D$2:$D729,$D729,$M$2:$M729,"<>Not an error")=1,1,0)) -> 0 | T729: =IF(M729<>"Major",0,IF(COUNTIFS($A$2:$A729,$A729,$D$2:$D729,$D729,$M$2:$M729,"Major")=1,1,0)) -> 0 | U729: =IF(M729<>"Minor",0,IF(COUNTIFS($A$2:$A729,$A729,$D$2:$D729,$D729,$M$2:$M729,"Minor")=1,1,0)) -> 0
A730: efa111b397877a29364b57266d879e11bff528fd | B730: Hacking the Mafia's Heart | C730: Mafiaherz Gehackt | D730: 4d59b1ebe2027ab6c9c7f91c8fb4a03ba92439d1 | E730: Episode 24: Geheimes Programmierleben | F730: 24 | G730: 7:25-7:29 | H730: Resolved | I730: VA says liyama - Liyana kicherte, aber ihr Gesicht hellte sich nicht ganz auf. | J730: VOA | K730: Mispronunciation | L730: Mispronunciation | M730: =IFERROR(IF(VLOOKUP(L730,'Quantification'!$A:$B,2,FALSE)&""="","Unclassified",VLOOKUP(L730,'Quantification'!$A:$B,2,FALSE)),"Unclassified") -> Major | N730: frl-denis.sobol@pocketfm.com | O730: Issues found in raw | P730: =IF(OR(O730="Issues found in master",O730="Final master"),"Master",IF(OR(O730="Ready for Master",O730="Issues found in raw",O730="Raw under QC",O730="Issues resolved in raw"),"Raw","-")) -> Raw | Q730: 46290.168 | R730: 2026-09 (Sept) | S730: =IF(M730="Not an error",0,IF(COUNTIFS($A$2:$A730,$A730,$D$2:$D730,$D730,$M$2:$M730,"<>Not an error")=1,1,0)) -> 1 | T730: =IF(M730<>"Major",0,IF(COUNTIFS($A$2:$A730,$A730,$D$2:$D730,$D730,$M$2:$M730,"Major")=1,1,0)) -> 1 | U730: =IF(M730<>"Minor",0,IF(COUNTIFS($A$2:$A730,$A730,$D$2:$D730,$D730,$M$2:$M730,"Minor")=1,1,0)) -> 0
A731: efa111b397877a29364b57266d879e11bff528fd | B731: Hacking the Mafia's Heart | C731: Mafiaherz Gehackt | D731: 4d59b1ebe2027ab6c9c7f91c8fb4a03ba92439d1 | E731: Episode 24: Geheimes Programmierleben | F731: 24 | G731: 8:05-8:10 | H731: Resolved | I731: Plüscherdbeerhasen -> Plüsch-Erdbeerhasen - „Erdbeerchen, Mondchen“, flüsterte sie und griff nach ihrem Plüscherdbeerhasen und dem Einhorn. | J731: AI | K731: Script error | L731: Script error | M731: =IFERROR(IF(VLOOKUP(L731,'Quantification'!$A:$B,2,FALSE)&""="","Unclassified",VLOOKUP(L731,'Quantification'!$A:$B,2,FALSE)),"Unclassified") -> Major | N731: frl-denis.sobol@pocketfm.com | O731: Issues found in raw | P731: =IF(OR(O731="Issues found in master",O731="Final master"),"Master",IF(OR(O731="Ready for Master",O731="Issues found in raw",O731="Raw under QC",O731="Issues resolved in raw"),"Raw","-")) -> Raw | Q731: 46290.168 | R731: 2026-09 (Sept) | S731: =IF(M731="Not an error",0,IF(COUNTIFS($A$2:$A731,$A731,$D$2:$D731,$D731,$M$2:$M731,"<>Not an error")=1,1,0)) -> 0 | T731: =IF(M731<>"Major",0,IF(COUNTIFS($A$2:$A731,$A731,$D$2:$D731,$D731,$M$2:$M731,"Major")=1,1,0)) -> 0 | U731: =IF(M731<>"Minor",0,IF(COUNTIFS($A$2:$A731,$A731,$D$2:$D731,$D731,$M$2:$M731,"Minor")=1,1,0)) -> 0
A732: efa111b397877a29364b57266d879e11bff528fd | B732: Hacking the Mafia's Heart | C732: Mafiaherz Gehackt | D732: 2a6918af85638e30a3d42478d781d18c3559bd7e | E732: Episode 26: Unerwarteter Morgen | F732: 26 | G732: 0:00-0:08 | H732: Resolved | I732: VA mispronounces Kopf - "Er legte den Kopf in den Nacken, trank das halbe Bier in einem Zug leer und stieß langsam den Atem aus. Sein Kiefer war angespannt." | J732: VOA | K732: Mispronunciation | L732: Mispronunciation | M732: =IFERROR(IF(VLOOKUP(L732,'Quantification'!$A:$B,2,FALSE)&""="","Unclassified",VLOOKUP(L732,'Quantification'!$A:$B,2,FALSE)),"Unclassified") -> Major | N732: frl-denis.sobol@pocketfm.com | O732: Issues found in raw | P732: =IF(OR(O732="Issues found in master",O732="Final master"),"Master",IF(OR(O732="Ready for Master",O732="Issues found in raw",O732="Raw under QC",O732="Issues resolved in raw"),"Raw","-")) -> Raw | Q732: 46290.498 | R732: 2026-09 (Sept) | S732: =IF(M732="Not an error",0,IF(COUNTIFS($A$2:$A732,$A732,$D$2:$D732,$D732,$M$2:$M732,"<>Not an error")=1,1,0)) -> 1 | T732: =IF(M732<>"Major",0,IF(COUNTIFS($A$2:$A732,$A732,$D$2:$D732,$D732,$M$2:$M732,"Major")=1,1,0)) -> 1 | U732: =IF(M732<>"Minor",0,IF(COUNTIFS($A$2:$A732,$A732,$D$2:$D732,$D732,$M$2:$M732,"Minor")=1,1,0)) -> 0
A733: efa111b397877a29364b57266d879e11bff528fd | B733: Hacking the Mafia's Heart | C733: Mafiaherz Gehackt | D733: c1e9c959eb1eb78721031e128fd32e7e144a685e | E733: Episode 28: Garten Begegnung | F733: 28 | G733: 9:48-9:56 | H733: Resolved | I733: VA says liyama - "Liyana wanderte tiefer in den stillen Garten hinein, ihre Absätze klickten leise auf dem Steinweg, während sie sich fröstelnd die Arme rieb." | J733: VOA | K733: Mispronunciation | L733: Mispronunciation | M733: =IFERROR(IF(VLOOKUP(L733,'Quantification'!$A:$B,2,FALSE)&""="","Unclassified",VLOOKUP(L733,'Quantification'!$A:$B,2,FALSE)),"Unclassified") -> Major | N733: frl-denis.sobol@pocketfm.com | O733: Issues found in raw | P733: =IF(OR(O733="Issues found in master",O733="Final master"),"Master",IF(OR(O733="Ready for Master",O733="Issues found in raw",O733="Raw under QC",O733="Issues resolved in raw"),"Raw","-")) -> Raw | Q733: 46290.497 | R733: 2026-09 (Sept) | S733: =IF(M733="Not an error",0,IF(COUNTIFS($A$2:$A733,$A733,$D$2:$D733,$D733,$M$2:$M733,"<>Not an error")=1,1,0)) -> 1 | T733: =IF(M733<>"Major",0,IF(COUNTIFS($A$2:$A733,$A733,$D$2:$D733,$D733,$M$2:$M733,"Major")=1,1,0)) -> 1 | U733: =IF(M733<>"Minor",0,IF(COUNTIFS($A$2:$A733,$A733,$D$2:$D733,$D733,$M$2:$M733,"Minor")=1,1,0)) -> 0
A734: efa111b397877a29364b57266d879e11bff528fd | B734: Hacking the Mafia's Heart | C734: Mafiaherz Gehackt | D734: f73ac87f5e1e497bf230450b1be080f36c0c7a43 | E734: Episode 31: Besuch Im Spezialeffekte-Studio | F734: 31 | G734: 11:03-11:08 | H734: Resolved | I734: VA mispronounces Geräuschemacher - „Geräuschemacher und Synchronregisseure arbeiten hier zusammen, um unsere Welten zum Leben zu erwecken.“ | J734: VOA | K734: Mispronunciation | L734: Mispronunciation | M734: =IFERROR(IF(VLOOKUP(L734,'Quantification'!$A:$B,2,FALSE)&""="","Unclassified",VLOOKUP(L734,'Quantification'!$A:$B,2,FALSE)),"Unclassified") -> Major | N734: frl-denis.sobol@pocketfm.com | O734: Issues found in raw | P734: =IF(OR(O734="Issues found in master",O734="Final master"),"Master",IF(OR(O734="Ready for Master",O734="Issues found in raw",O734="Raw under QC",O734="Issues resolved in raw"),"Raw","-")) -> Raw | Q734: 46290.497 | R734: 2026-09 (Sept) | S734: =IF(M734="Not an error",0,IF(COUNTIFS($A$2:$A734,$A734,$D$2:$D734,$D734,$M$2:$M734,"<>Not an error")=1,1,0)) -> 1 | T734: =IF(M734<>"Major",0,IF(COUNTIFS($A$2:$A734,$A734,$D$2:$D734,$D734,$M$2:$M734,"Major")=1,1,0)) -> 1 | U734: =IF(M734<>"Minor",0,IF(COUNTIFS($A$2:$A734,$A734,$D$2:$D734,$D734,$M$2:$M734,"Minor")=1,1,0)) -> 0
... A1057: 9540fa0b0f0a4e67296efcd05e977d34ff2d48cc | B1057: Mad Vampire Lord's Bride | C1057: Die Braut Des Wahnsinnigen Vampirfürsten | D1057: ec852baef0c5063293f13e2b93c786387b533f74 | E1057: Episode 28: Die Mahlzeit Entreißen | F1057: 28 | G1057: 7:45-7:50 | H1057: Resolved | I1057: Remarks: change in accent Line from Script: " Das Blut tropfte in Cordelias Mahlzeit, als wollte es dem Essen ein Blutaroma hinzufügen. " Notes: "Cordelia" DE-->EN | J1057: VOA | K1057: Mispronunciation | L1057: Mispronunciation | M1057: =IFERROR(IF(VLOOKUP(L1057,'Quantification'!$A:$B,2,FALSE)&""="","Unclassified",VLOOKUP(L1057,'Quantification'!$A:$B,2,FALSE)),"Unclassified") -> Major | N1057: frl-florinda.frisardi@pocketfm.com | O1057: Issues found in raw | P1057: =IF(OR(O1057="Issues found in master",O1057="Final master"),"Master",IF(OR(O1057="Ready for Master",O1057="Issues found in raw",O1057="Raw under QC",O1057="Issues resolved in raw"),"Raw","-")) -> Raw | Q1057: 46265.249 | R1057: 2026-08 (Aug) | S1057: =IF(M1057="Not an error",0,IF(COUNTIFS($A$2:$A1057,$A1057,$D$2:$D1057,$D1057,$M$2:$M1057,"<>Not an error")=1,1,0)) -> 0 | T1057: =IF(M1057<>"Major",0,IF(COUNTIFS($A$2:$A1057,$A1057,$D$2:$D1057,$D1057,$M$2:$M1057,"Major")=1,1,0)) -> 0 | U1057: =IF(M1057<>"Minor",0,IF(COUNTIFS($A$2:$A1057,$A1057,$D$2:$D1057,$D1057,$M$2:$M1057,"Minor")=1,1,0)) -> 0
A1058: 9540fa0b0f0a4e67296efcd05e977d34ff2d48cc | B1058: Mad Vampire Lord's Bride | C1058: Die Braut Des Wahnsinnigen Vampirfürsten | D1058: 6f404de16ec92be24f8f4d4e7fd67c5a1fea1f3d | E1058: Episode 39: Die Neugier Des Wolfes ( Re Generated and Replaced) | F1058: 39 | H1058: Resolved | I1058: Remark: script error Line from script: "Sie würde nicht einmal lange genug leben, um Nachtbach an Argonien zu verraten oder zu Jamie zurückzukehren und ihm seinen Ring zurückzugeben." Note: Argonien = Aragon; Nachtbach = Nightbrook | J1058: VOA | K1058: Script Error | L1058: Script error | M1058: =IFERROR(IF(VLOOKUP(L1058,'Quantification'!$A:$B,2,FALSE)&""="","Unclassified",VLOOKUP(L1058,'Quantification'!$A:$B,2,FALSE)),"Unclassified") -> Major | N1058: frl-carlos.alexander@pocketfm.com | O1058: Issues found in raw | P1058: =IF(OR(O1058="Issues found in master",O1058="Final master"),"Master",IF(OR(O1058="Ready for Master",O1058="Issues found in raw",O1058="Raw under QC",O1058="Issues resolved in raw"),"Raw","-")) -> Raw | Q1058: 46248.508 | R1058: 2026-08 (Aug) | S1058: =IF(M1058="Not an error",0,IF(COUNTIFS($A$2:$A1058,$A1058,$D$2:$D1058,$D1058,$M$2:$M1058,"<>Not an error")=1,1,0)) -> 1 | T1058: =IF(M1058<>"Major",0,IF(COUNTIFS($A$2:$A1058,$A1058,$D$2:$D1058,$D1058,$M$2:$M1058,"Major")=1,1,0)) -> 1 | U1058: =IF(M1058<>"Minor",0,IF(COUNTIFS($A$2:$A1058,$A1058,$D$2:$D1058,$D1058,$M$2:$M1058,"Minor")=1,1,0)) -> 0
A1059: 9540fa0b0f0a4e67296efcd05e977d34ff2d48cc | B1059: Mad Vampire Lord's Bride | C1059: Die Braut Des Wahnsinnigen Vampirfürsten | D1059: ca54bc0189bfb58fa3318518dd116a5533d02b30 | E1059: Episode 39: Die Neugier Des Wolfes | F1059: 39 | G1059: 3:17-3:21 | H1059: Resolved | I1059: Remarks: change in accent Line from Script: "Cordelia runzelte bei diesen Worten die Stirn und schürzte die Lippen. " Notes: "Cordelia" DE-->EN | J1059: VOA | K1059: Mispronunciation | L1059: Mispronunciation | M1059: =IFERROR(IF(VLOOKUP(L1059,'Quantification'!$A:$B,2,FALSE)&""="","Unclassified",VLOOKUP(L1059,'Quantification'!$A:$B,2,FALSE)),"Unclassified") -> Major | N1059: frl-florinda.frisardi@pocketfm.com | O1059: Issues found in raw | P1059: =IF(OR(O1059="Issues found in master",O1059="Final master"),"Master",IF(OR(O1059="Ready for Master",O1059="Issues found in raw",O1059="Raw under QC",O1059="Issues resolved in raw"),"Raw","-")) -> Raw | Q1059: 46280.214 | R1059: 2026-09 (Sept) | S1059: =IF(M1059="Not an error",0,IF(COUNTIFS($A$2:$A1059,$A1059,$D$2:$D1059,$D1059,$M$2:$M1059,"<>Not an error")=1,1,0)) -> 1 | T1059: =IF(M1059<>"Major",0,IF(COUNTIFS($A$2:$A1059,$A1059,$D$2:$D1059,$D1059,$M$2:$M1059,"Major")=1,1,0)) -> 1 | U1059: =IF(M1059<>"Minor",0,IF(COUNTIFS($A$2:$A1059,$A1059,$D$2:$D1059,$D1059,$M$2:$M1059,"Minor")=1,1,0)) -> 0
A1060: 9540fa0b0f0a4e67296efcd05e977d34ff2d48cc | B1060: Mad Vampire Lord's Bride | C1060: Die Braut Des Wahnsinnigen Vampirfürsten | D1060: ca54bc0189bfb58fa3318518dd116a5533d02b30 | E1060: Episode 39: Die Neugier Des Wolfes | F1060: 39 | G1060: 3:32-3:38 | H1060: Resolved | I1060: Remarks: change in accent Line from Script: "Und was war mit der linken Augenbraue des Menschen passiert?, fragte sich Cordelia, die neben Rohan stand. " Notes: "Cordelia" DE-->EN | J1060: VOA | K1060: Mispronunciation | L1060: Mispronunciation | M1060: =IFERROR(IF(VLOOKUP(L1060,'Quantification'!$A:$B,2,FALSE)&""="","Unclassified",VLOOKUP(L1060,'Quantification'!$A:$B,2,FALSE)),"Unclassified") -> Major | N1060: frl-florinda.frisardi@pocketfm.com | O1060: Issues found in raw | P1060: =IF(OR(O1060="Issues found in master",O1060="Final master"),"Master",IF(OR(O1060="Ready for Master",O1060="Issues found in raw",O1060="Raw under QC",O1060="Issues resolved in raw"),"Raw","-")) -> Raw | Q1060: 46280.214 | R1060: 2026-09 (Sept) | S1060: =IF(M1060="Not an error",0,IF(COUNTIFS($A$2:$A1060,$A1060,$D$2:$D1060,$D1060,$M$2:$M1060,"<>Not an error")=1,1,0)) -> 0 | T1060: =IF(M1060<>"Major",0,IF(COUNTIFS($A$2:$A1060,$A1060,$D$2:$D1060,$D1060,$M$2:$M1060,"Major")=1,1,0)) -> 0 | U1060: =IF(M1060<>"Minor",0,IF(COUNTIFS($A$2:$A1060,$A1060,$D$2:$D1060,$D1060,$M$2:$M1060,"Minor")=1,1,0)) -> 0
A1061: 9540fa0b0f0a4e67296efcd05e977d34ff2d48cc | B1061: Mad Vampire Lord's Bride | C1061: Die Braut Des Wahnsinnigen Vampirfürsten | D1061: ca54bc0189bfb58fa3318518dd116a5533d02b30 | E1061: Episode 39: Die Neugier Des Wolfes | F1061: 39 | G1061: 3:51-3:54 | H1061: Resolved | I1061: Remarks: change in accent Line from Script: "Cordelia runzelte die Stirn, als sie auf die Narbe starrte." Notes: "Cordelia" DE-->EN | J1061: VOA | K1061: Mispronunciation | L1061: Mispronunciation | M1061: =IFERROR(IF(VLOOKUP(L1061,'Quantification'!$A:$B,2,FALSE)&""="","Unclassified",VLOOKUP(L1061,'Quantification'!$A:$B,2,FALSE)),"Unclassified") -> Major | N1061: frl-florinda.frisardi@pocketfm.com | O1061: Issues found in raw | P1061: =IF(OR(O1061="Issues found in master",O1061="Final master"),"Master",IF(OR(O1061="Ready for Master",O1061="Issues found in raw",O1061="Raw under QC",O1061="Issues resolved in raw"),"Raw","-")) -> Raw | Q1061: 46280.214 | R1061: 2026-09 (Sept) | S1061: =IF(M1061="Not an error",0,IF(COUNTIFS($A$2:$A1061,$A1061,$D$2:$D1061,$D1061,$M$2:$M1061,"<>Not an error")=1,1,0)) -> 0 | T1061: =IF(M1061<>"Major",0,IF(COUNTIFS($A$2:$A1061,$A1061,$D$2:$D1061,$D1061,$M$2:$M1061,"Major")=1,1,0)) -> 0 | U1061: =IF(M1061<>"Minor",0,IF(COUNTIFS($A$2:$A1061,$A1061,$D$2:$D1061,$D1061,$M$2:$M1061,"Minor")=1,1,0)) -> 0
A1062: 9540fa0b0f0a4e67296efcd05e977d34ff2d48cc | B1062: Mad Vampire Lord's Bride | C1062: Die Braut Des Wahnsinnigen Vampirfürsten | D1062: ca54bc0189bfb58fa3318518dd116a5533d02b30 | E1062: Episode 39: Die Neugier Des Wolfes | F1062: 39 | G1062: 6:19-6:36 | H1062: Resolved | I1062: Remarks: change in accent Line from Script: "Cordelia hatte vergessen, dass er sie besser kannte als jeder andere, als sie diesen Plan schmiedete. Cordelia, die darauf wartete, dass er den Menschen tötete, keuchte und fuhr vor. „Was? Ich habe sie nicht zerbrochen! Sieh dir ihre Hände an, sie sind voller Schlamm, und.“ Notes: "Cordelia" DE-->EN | J1062: VOA | K1062: Mispronunciation | L1062: Mispronunciation | M1062: =IFERROR(IF(VLOOKUP(L1062,'Quantification'!$A:$B,2,FALSE)&""="","Unclassified",VLOOKUP(L1062,'Quantification'!$A:$B,2,FALSE)),"Unclassified") -> Major | N1062: frl-florinda.frisardi@pocketfm.com | O1062: Issues found in raw | P1062: =IF(OR(O1062="Issues found in master",O1062="Final master"),"Master",IF(OR(O1062="Ready for Master",O1062="Issues found in raw",O1062="Raw under QC",O1062="Issues resolved in raw"),"Raw","-")) -> Raw | Q1062: 46280.214 | R1062: 2026-09 (Sept) | S1062: =IF(M1062="Not an error",0,IF(COUNTIFS($A$2:$A1062,$A1062,$D$2:$D1062,$D1062,$M$2:$M1062,"<>Not an error")=1,1,0)) -> 0 | T1062: =IF(M1062<>"Major",0,IF(COUNTIFS($A$2:$A1062,$A1062,$D$2:$D1062,$D1062,$M$2:$M1062,"Major")=1,1,0)) -> 0 | U1062: =IF(M1062<>"Minor",0,IF(COUNTIFS($A$2:$A1062,$A1062,$D$2:$D1062,$D1062,$M$2:$M1062,"Minor")=1,1,0)) -> 0
A1063: 9540fa0b0f0a4e67296efcd05e977d34ff2d48cc | B1063: Mad Vampire Lord's Bride | C1063: Die Braut Des Wahnsinnigen Vampirfürsten | D1063: ca54bc0189bfb58fa3318518dd116a5533d02b30 | E1063: Episode 39: Die Neugier Des Wolfes | F1063: 39 | G1063: 9:24-9:30 | H1063: Resolved | I1063: Remarks: change in accent Line from Script: "Obwohl sie wütend auf Cordelia sein mochte, konnte sie nicht leugnen, dass sie die Pflanze zerbrochen hatte." Notes: "Cordelia" DE-->EN | J1063: VOA | K1063: Mispronunciation | L1063: Mispronunciation | M1063: =IFERROR(IF(VLOOKUP(L1063,'Quantification'!$A:$B,2,FALSE)&""="","Unclassified",VLOOKUP(L1063,'Quantification'!$A:$B,2,FALSE)),"Unclassified") -> Major | N1063: frl-florinda.frisardi@pocketfm.com | O1063: Issues found in raw | P1063: =IF(OR(O1063="Issues found in master",O1063="Final master"),"Master",IF(OR(O1063="Ready for Master",O1063="Issues found in raw",O1063="Raw under QC",O1063="Issues resolved in raw"),"Raw","-")) -> Raw | Q1063: 46280.214 | R1063: 2026-09 (Sept) | S1063: =IF(M1063="Not an error",0,IF(COUNTIFS($A$2:$A1063,$A1063,$D$2:$D1063,$D1063,$M$2:$M1063,"<>Not an error")=1,1,0)) -> 0 | T1063: =IF(M1063<>"Major",0,IF(COUNTIFS($A$2:$A1063,$A1063,$D$2:$D1063,$D1063,$M$2:$M1063,"Major")=1,1,0)) -> 0 | U1063: =IF(M1063<>"Minor",0,IF(COUNTIFS($A$2:$A1063,$A1063,$D$2:$D1063,$D1063,$M$2:$M1063,"Minor")=1,1,0)) -> 0
A1064: 9540fa0b0f0a4e67296efcd05e977d34ff2d48cc | B1064: Mad Vampire Lord's Bride | C1064: Die Braut Des Wahnsinnigen Vampirfürsten | D1064: ea6090d12b92ff2a45e53cb7a53958b7ea8fe1d2 | E1064: Episode 409: Gerechtigkeit Neugeschrieben | F1064: 409 | G1064: 0:27-0:43 | H1064: Resolved | I1064: Remark: Mispronunciation Line from script: "Er hatte gehofft, eine große Distanz zwischen ihnen zu schaffen und sein Leben wieder in geordnete Bahnen zu lenken, ohne nachts wach zu liegen und darüber nachzudenken, wie ihre Augen funkelten, wenn sie lachte, oder wie gut es sich angefühlt hatte, sie in Aragon eng an sich zu halten und zur Musik zu wiegen." Note: Aragon English | J1064: VOA | K1064: Mispronunciation | L1064: Mispronunciation | M1064: =IFERROR(IF(VLOOKUP(L1064,'Quantification'!$A:$B,2,FALSE)&""="","Unclassified",VLOOKUP(L1064,'Quantification'!$A:$B,2,FALSE)),"Unclassified") -> Major | N1064: frl-carlos.alexander@pocketfm.com | O1064: Issues found in raw | P1064: =IF(OR(O1064="Issues found in master",O1064="Final master"),"Master",IF(OR(O1064="Ready for Master",O1064="Issues found in raw",O1064="Raw under QC",O1064="Issues resolved in raw"),"Raw","-")) -> Raw | Q1064: 46248.151 | R1064: 2026-08 (Aug) | S1064: =IF(M1064="Not an error",0,IF(COUNTIFS($A$2:$A1064,$A1064,$D$2:$D1064,$D1064,$M$2:$M1064,"<>Not an error")=1,1,0)) -> 1 | T1064: =IF(M1064<>"Major",0,IF(COUNTIFS($A$2:$A1064,$A1064,$D$2:$D1064,$D1064,$M$2:$M1064,"Major")=1,1,0)) -> 1 | U1064: =IF(M1064<>"Minor",0,IF(COUNTIFS($A$2:$A1064,$A1064,$D$2:$D1064,$D1064,$M$2:$M1064,"Minor")=1,1,0)) -> 0
A1065: 9540fa0b0f0a4e67296efcd05e977d34ff2d48cc | B1065: Mad Vampire Lord's Bride | C1065: Die Braut Des Wahnsinnigen Vampirfürsten | D1065: ea6090d12b92ff2a45e53cb7a53958b7ea8fe1d2 | E1065: Episode 409: Gerechtigkeit Neugeschrieben | F1065: 409 | G1065: 3:09-3:15 | H1065: Resolved | I1065: Remark: Mispronunciation Line from script: "Sie hatte schon vor langer Zeit bemerkt, dass alles, was sie in Aragon für ihn ausgesucht hatte, in einem anderen Zimmer untergebracht worden war." Note: Aragon English | J1065: VOA | K1065: Mispronunciation | L1065: Mispronunciation | M1065: =IFERROR(IF(VLOOKUP(L1065,'Quantification'!$A:$B,2,FALSE)&""="","Unclassified",VLOOKUP(L1065,'Quantification'!$A:$B,2,FALSE)),"Unclassified") -> Major | N1065: frl-carlos.alexander@pocketfm.com | O1065: Issues found in raw | P1065: =IF(OR(O1065="Issues found in master",O1065="Final master"),"Master",IF(OR(O1065="Ready for Master",O1065="Issues found in raw",O1065="Raw under QC",O1065="Issues resolved in raw"),"Raw","-")) -> Raw | Q1065: 46248.151 | R1065: 2026-08 (Aug) | S1065: =IF(M1065="Not an error",0,IF(COUNTIFS($A$2:$A1065,$A1065,$D$2:$D1065,$D1065,$M$2:$M1065,"<>Not an error")=1,1,0)) -> 0 | T1065: =IF(M1065<>"Major",0,IF(COUNTIFS($A$2:$A1065,$A1065,$D$2:$D1065,$D1065,$M$2:$M1065,"Major")=1,1,0)) -> 0 | U1065: =IF(M1065<>"Minor",0,IF(COUNTIFS($A$2:$A1065,$A1065,$D$2:$D1065,$D1065,$M$2:$M1065,"Minor")=1,1,0)) -> 0
A1066: 9540fa0b0f0a4e67296efcd05e977d34ff2d48cc | B1066: Mad Vampire Lord's Bride | C1066: Die Braut Des Wahnsinnigen Vampirfürsten | D1066: 0b559c3df2b36008e6c3f819a543f762bda6e8b2 | E1066: Episode 410: Wahnsinn Erklärt | F1066: 410 | G1066: 3:58-4:01 | H1066: Resolved | I1066: Remark: script error Line from script: "Ravs Gedanken waren nicht weit von ihren entfernt." Note: Ravs = Refs | J1066: VOA | K1066: Script Error | L1066: Script error | M1066: =IFERROR(IF(VLOOKUP(L1066,'Quantification'!$A:$B,2,FALSE)&""="","Unclassified",VLOOKUP(L1066,'Quantification'!$A:$B,2,FALSE)),"Unclassified") -> Major | N1066: frl-carlos.alexander@pocketfm.com | O1066: Issues found in raw | P1066: =IF(OR(O1066="Issues found in master",O1066="Final master"),"Master",IF(OR(O1066="Ready for Master",O1066="Issues found in raw",O1066="Raw under QC",O1066="Issues resolved in raw"),"Raw","-")) -> Raw | Q1066: 46248.151 | R1066: 2026-08 (Aug) | S1066: =IF(M1066="Not an error",0,IF(COUNTIFS($A$2:$A1066,$A1066,$D$2:$D1066,$D1066,$M$2:$M1066,"<>Not an error")=1,1,0)) -> 1 | T1066: =IF(M1066<>"Major",0,IF(COUNTIFS($A$2:$A1066,$A1066,$D$2:$D1066,$D1066,$M$2:$M1066,"Major")=1,1,0)) -> 1 | U1066: =IF(M1066<>"Minor",0,IF(COUNTIFS($A$2:$A1066,$A1066,$D$2:$D1066,$D1066,$M$2:$M1066,"Minor")=1,1,0)) -> 0
A1067: 9540fa0b0f0a4e67296efcd05e977d34ff2d48cc | B1067: Mad Vampire Lord's Bride | C1067: Die Braut Des Wahnsinnigen Vampirfürsten | D1067: c1f4cbc16d0eb993720992519e1499791da827a4 | E1067: Episode 412: Bestrafung in Erinnerung | F1067: 412 | G1067: 1:29-1:32 | H1067: Resolved | I1067: Remark: Script error Line from script: "Und du musst dir keine Sorgen machen, ich könnte schwanger sein." Note: missing "nicht" after "könnte". | J1067: VOA | K1067: Script Error | L1067: Script error | M1067: =IFERROR(IF(VLOOKUP(L1067,'Quantification'!$A:$B,2,FALSE)&""="","Unclassified",VLOOKUP(L1067,'Quantification'!$A:$B,2,FALSE)),"Unclassified") -> Major | N1067: frl-carlos.alexander@pocketfm.com | O1067: Issues found in raw | P1067: =IF(OR(O1067="Issues found in master",O1067="Final master"),"Master",IF(OR(O1067="Ready for Master",O1067="Issues found in raw",O1067="Raw under QC",O1067="Issues resolved in raw"),"Raw","-")) -> Raw | Q1067: 46249.158 | R1067: 2026-08 (Aug) | S1067: =IF(M1067="Not an error",0,IF(COUNTIFS($A$2:$A1067,$A1067,$D$2:$D1067,$D1067,$M$2:$M1067,"<>Not an error")=1,1,0)) -> 1 | T1067: =IF(M1067<>"Major",0,IF(COUNTIFS($A$2:$A1067,$A1067,$D$2:$D1067,$D1067,$M$2:$M1067,"Major")=1,1,0)) -> 1 | U1067: =IF(M1067<>"Minor",0,IF(COUNTIFS($A$2:$A1067,$A1067,$D$2:$D1067,$D1067,$M$2:$M1067,"Minor")=1,1,0)) -> 0
A1068: 9540fa0b0f0a4e67296efcd05e977d34ff2d48cc | B1068: Mad Vampire Lord's Bride | C1068: Die Braut Des Wahnsinnigen Vampirfürsten | D1068: c1f4cbc16d0eb993720992519e1499791da827a4 | E1068: Episode 412: Bestrafung in Erinnerung | F1068: 412 | G1068: 8:44-8:49 | H1068: Resolved | I1068: Remark: script error Line from script: "Sie machte sich auf den Weg zu Ravs Gemach, um ihn zu bitten, nachzusehen, ob es Rohan gut geht. Sie ging den Korridor entlang, erreichte Ravs Zimmer aber nicht einmal." Note: Ravs = Refs | J1068: VOA | K1068: Script Error | L1068: Script error | M1068: =IFERROR(IF(VLOOKUP(L1068,'Quantification'!$A:$B,2,FALSE)&""="","Unclassified",VLOOKUP(L1068,'Quantification'!$A:$B,2,FALSE)),"Unclassified") -> Major | N1068: frl-carlos.alexander@pocketfm.com | O1068: Issues found in raw | P1068: =IF(OR(O1068="Issues found in master",O1068="Final master"),"Master",IF(OR(O1068="Ready for Master",O1068="Issues found in raw",O1068="Raw under QC",O1068="Issues resolved in raw"),"Raw","-")) -> Raw | Q1068: 46249.158 | R1068: 2026-08 (Aug) | S1068: =IF(M1068="Not an error",0,IF(COUNTIFS($A$2:$A1068,$A1068,$D$2:$D1068,$D1068,$M$2:$M1068,"<>Not an error")=1,1,0)) -> 0 | T1068: =IF(M1068<>"Major",0,IF(COUNTIFS($A$2:$A1068,$A1068,$D$2:$D1068,$D1068,$M$2:$M1068,"Major")=1,1,0)) -> 0 | U1068: =IF(M1068<>"Minor",0,IF(COUNTIFS($A$2:$A1068,$A1068,$D$2:$D1068,$D1068,$M$2:$M1068,"Minor")=1,1,0)) -> 0
A1069: 9540fa0b0f0a4e67296efcd05e977d34ff2d48cc | B1069: Mad Vampire Lord's Bride | C1069: Die Braut Des Wahnsinnigen Vampirfürsten | D1069: c1f4cbc16d0eb993720992519e1499791da827a4 | E1069: Episode 412: Bestrafung in Erinnerung | F1069: 412 | G1069: 9:15-9:21 | H1069: Resolved | I1069: Remark: script error Line from script: "Obwohl Evenly selten verlegen war, wurde sie von diesem Gefühl übermannt, als sie dabei erwischt wurde, wie sie Ravs Zimmer verließ." Note: Ravs = Refs | J1069: VOA | K1069: Script Error | L1069: Script error | M1069: =IFERROR(IF(VLOOKUP(L1069,'Quantification'!$A:$B,2,FALSE)&""="","Unclassified",VLOOKUP(L1069,'Quantification'!$A:$B,2,FALSE)),"Unclassified") -> Major | N1069: frl-carlos.alexander@pocketfm.com | O1069: Issues found in raw | P1069: =IF(OR(O1069="Issues found in master",O1069="Final master"),"Master",IF(OR(O1069="Ready for Master",O1069="Issues found in raw",O1069="Raw under QC",O1069="Issues resolved in raw"),"Raw","-")) -> Raw | Q1069: 46249.158 | R1069: 2026-08 (Aug) | S1069: =IF(M1069="Not an error",0,IF(COUNTIFS($A$2:$A1069,$A1069,$D$2:$D1069,$D1069,$M$2:$M1069,"<>Not an error")=1,1,0)) -> 0 | T1069: =IF(M1069<>"Major",0,IF(COUNTIFS($A$2:$A1069,$A1069,$D$2:$D1069,$D1069,$M$2:$M1069,"Major")=1,1,0)) -> 0 | U1069: =IF(M1069<>"Minor",0,IF(COUNTIFS($A$2:$A1069,$A1069,$D$2:$D1069,$D1069,$M$2:$M1069,"Minor")=1,1,0)) -> 0
A1070: 9540fa0b0f0a4e67296efcd05e977d34ff2d48cc | B1070: Mad Vampire Lord's Bride | C1070: Die Braut Des Wahnsinnigen Vampirfürsten | D1070: 3e90f86ead986c97f326ac7589d26a7d591ae781 | E1070: Episode 413: Gefangen Von Lügen | F1070: 413 | G1070: 0:56-1:00 | H1070: Resolved | I1070: Remark: Mispronunciation Line from script: "Mit den Gagern als Wachen fürchte ich, dass er ihm etwas antut.“ Note: gagern French | J1070: VOA | K1070: Mispronunciation | L1070: Mispronunciation | M1070: =IFERROR(IF(VLOOKUP(L1070,'Quantification'!$A:$B,2,FALSE)&""="","Unclassified",VLOOKUP(L1070,'Quantification'!$A:$B,2,FALSE)),"Unclassified") -> Major | N1070: frl-carlos.alexander@pocketfm.com | O1070: Issues found in raw | P1070: =IF(OR(O1070="Issues found in master",O1070="Final master"),"Master",IF(OR(O1070="Ready for Master",O1070="Issues found in raw",O1070="Raw under QC",O1070="Issues resolved in raw"),"Raw","-")) -> Raw | Q1070: 46250.152 | R1070: 2026-08 (Aug) | S1070: =IF(M1070="Not an error",0,IF(COUNTIFS($A$2:$A1070,$A1070,$D$2:$D1070,$D1070,$M$2:$M1070,"<>Not an error")=1,1,0)) -> 1 | T1070: =IF(M1070<>"Major",0,IF(COUNTIFS($A$2:$A1070,$A1070,$D$2:$D1070,$D1070,$M$2:$M1070,"Major")=1,1,0)) -> 1 | U1070: =IF(M1070<>"Minor",0,IF(COUNTIFS($A$2:$A1070,$A1070,$D$2:$D1070,$D1070,$M$2:$M1070,"Minor")=1,1,0)) -> 0
... A1122: 9540fa0b0f0a4e67296efcd05e977d34ff2d48cc | B1122: Mad Vampire Lord's Bride | C1122: Die Braut Des Wahnsinnigen Vampirfürsten | D1122: 709e8a9e05101b31940fe2843ae2d7eb1f26c309 | E1122: Episode 473: Der Preis Des Lebens | F1122: 473 | G1122: 4:04-4:10 | H1122: Resolved | I1122: Remark: script error Line from script: "Bring meinen Sohn hinein, ich kümmere mich um ihn“, befahl er ihr bestimmt und griff nach Ravs Arm." Note: Ravs = Refs | J1122: VOA | K1122: Script Error | L1122: Script error | M1122: =IFERROR(IF(VLOOKUP(L1122,'Quantification'!$A:$B,2,FALSE)&""="","Unclassified",VLOOKUP(L1122,'Quantification'!$A:$B,2,FALSE)),"Unclassified") -> Major | N1122: frl-carlos.alexander@pocketfm.com | O1122: Issues found in raw | P1122: =IF(OR(O1122="Issues found in master",O1122="Final master"),"Master",IF(OR(O1122="Ready for Master",O1122="Issues found in raw",O1122="Raw under QC",O1122="Issues resolved in raw"),"Raw","-")) -> Raw | Q1122: 46280.151 | R1122: 2026-09 (Sept) | S1122: =IF(M1122="Not an error",0,IF(COUNTIFS($A$2:$A1122,$A1122,$D$2:$D1122,$D1122,$M$2:$M1122,"<>Not an error")=1,1,0)) -> 0 | T1122: =IF(M1122<>"Major",0,IF(COUNTIFS($A$2:$A1122,$A1122,$D$2:$D1122,$D1122,$M$2:$M1122,"Major")=1,1,0)) -> 0 | U1122: =IF(M1122<>"Minor",0,IF(COUNTIFS($A$2:$A1122,$A1122,$D$2:$D1122,$D1122,$M$2:$M1122,"Minor")=1,1,0)) -> 0
A1123: 9540fa0b0f0a4e67296efcd05e977d34ff2d48cc | B1123: Mad Vampire Lord's Bride | C1123: Die Braut Des Wahnsinnigen Vampirfürsten | D1123: 709e8a9e05101b31940fe2843ae2d7eb1f26c309 | E1123: Episode 473: Der Preis Des Lebens | F1123: 473 | H1123: Ignore | I1123: Remark: script error Line from script: " Note: Ravs = Refs | J1123: VOA | K1123: Script Error | L1123: Script error | M1123: =IFERROR(IF(VLOOKUP(L1123,'Quantification'!$A:$B,2,FALSE)&""="","Unclassified",VLOOKUP(L1123,'Quantification'!$A:$B,2,FALSE)),"Unclassified") -> Major | N1123: frl-carlos.alexander@pocketfm.com | O1123: Issues found in raw | P1123: =IF(OR(O1123="Issues found in master",O1123="Final master"),"Master",IF(OR(O1123="Ready for Master",O1123="Issues found in raw",O1123="Raw under QC",O1123="Issues resolved in raw"),"Raw","-")) -> Raw | Q1123: 46280.151 | R1123: 2026-09 (Sept) | S1123: =IF(M1123="Not an error",0,IF(COUNTIFS($A$2:$A1123,$A1123,$D$2:$D1123,$D1123,$M$2:$M1123,"<>Not an error")=1,1,0)) -> 0 | T1123: =IF(M1123<>"Major",0,IF(COUNTIFS($A$2:$A1123,$A1123,$D$2:$D1123,$D1123,$M$2:$M1123,"Major")=1,1,0)) -> 0 | U1123: =IF(M1123<>"Minor",0,IF(COUNTIFS($A$2:$A1123,$A1123,$D$2:$D1123,$D1123,$M$2:$M1123,"Minor")=1,1,0)) -> 0
A1124: 9540fa0b0f0a4e67296efcd05e977d34ff2d48cc | B1124: Mad Vampire Lord's Bride | C1124: Die Braut Des Wahnsinnigen Vampirfürsten | D1124: 09367c87c82624405c7f464241717382412e339e | E1124: Episode 477: Eine Stille Rebellion | F1124: 477 | G1124: 2:01-2:10 | H1124: Resolved | I1124: Remark: script error Line from script: "Inzwischen wusste Bella, dass sich Ravs Zustand verschlechtert hatte, denn seine Lebenszeit spielte in ihrer Handfläche verrückt, wann immer sie sich auf seinen Namen konzentrierte." Note: Ravs = Refs | J1124: VOA | K1124: Script Error | L1124: Script error | M1124: =IFERROR(IF(VLOOKUP(L1124,'Quantification'!$A:$B,2,FALSE)&""="","Unclassified",VLOOKUP(L1124,'Quantification'!$A:$B,2,FALSE)),"Unclassified") -> Major | N1124: frl-carlos.alexander@pocketfm.com | O1124: Issues found in raw | P1124: =IF(OR(O1124="Issues found in master",O1124="Final master"),"Master",IF(OR(O1124="Ready for Master",O1124="Issues found in raw",O1124="Raw under QC",O1124="Issues resolved in raw"),"Raw","-")) -> Raw | Q1124: 46282.168 | R1124: 2026-09 (Sept) | S1124: =IF(M1124="Not an error",0,IF(COUNTIFS($A$2:$A1124,$A1124,$D$2:$D1124,$D1124,$M$2:$M1124,"<>Not an error")=1,1,0)) -> 1 | T1124: =IF(M1124<>"Major",0,IF(COUNTIFS($A$2:$A1124,$A1124,$D$2:$D1124,$D1124,$M$2:$M1124,"Major")=1,1,0)) -> 1 | U1124: =IF(M1124<>"Minor",0,IF(COUNTIFS($A$2:$A1124,$A1124,$D$2:$D1124,$D1124,$M$2:$M1124,"Minor")=1,1,0)) -> 0
...

Sheet Quantification
A1: Issue type | B1: Severity
A2: Abrupt cut / Jerk | B2: Major
A3: Acting | B3: Minor
A4: Ambience / SFX placement | B4: Minor
A5: Ambience / SFX selection | B5: Minor
A6: Audio quality | B6: Major
A7: Audio Regenerated | B7: Minor
A8: Background noise | B8: Minor
A9: BGM/SFX
A10: Breathing noise | B10: Minor
A11: Clarity of speech | B11: Minor
A12: Clarity of speech (audio error) | B12: Minor
A13: Distorted sound | B13: Minor
A14: Duration | B14: Minor
A15: Fumble / Mumble | B15: Minor
A16: Gramatically incorrect (voa) | B16: Major
A17: Grammatically incorrect | B17: Major
A18: Incorrect name | B18: Major
A19: Line/ paragraph repetition | B19: Minor
A20: Loud music / SFX | B20: Minor
A21: Loudness & peak levels | B21: Minor
... A41: Wrong Audio | B41: Major

Sheet Show IDs
A1: DE show ID | B1: Show name | C1: DE title | D1: QC'd episodes (Ep Count)
A2: 9a175f97e92a638a5697307799ea3b8b8f419aac | B2: The Miracle Heiress | C2: Die Wundererbin | D2: 304
A3: 819eabfbd96880cd7f6d42202600e24bdb384108 | B3: Primal Partners | C3: Primal Partners (New) | D3: 176
A4: 294cd7d130be8bb0326127c52ff2769fcf9a956d | B4: Zompirewolf | C4: Zompirewolf: Die Geburt Einer Legende | D4: 571
A5: f855eae3dfc9aadc286f38e8d5e70cc6a599f238 | B5: The Silent Rebirth | C5: Wiedergeboren Für Rache | D5: 50
A6: 806152088c4f0f13e40c0788e7bc440106d13b1a | B6: The Secret Life of an Accidental Heiress | C6: The Secret Life of an Accidental Heiress | D6: 42
A7: 60392f2f8a29ae2294a4d279a3033aeaa01affa7 | B7: Thorns and Thrones | C7: Fluch Und Krone | D7: 81
A8: 4baec2ac0f23302985d2ad577e111504bd88c99c | B8: Bride of a dragon | C8: Die Braut Des Drachenkönigs | D8: 71
A9: edb3d0a58ac95f5ef497da24336396e996c6e7e9 | B9: His Secret Fortune | C9: Liebe Nach Vertrag | D9: 200
A10: 2480d4767331b6a7bbbc4f588c705dd813a76a8d | B10: Bride of a dragon - BGM + SFX | C10: Bride of a Dragon (With BGM-SFX) | D10: 100
A11: af2d64963a0b2a4ae6e1645ebec6e6220c089166 | B11: Rise of the Beastmaster | C11: Der Aufstieg Des Beastmasters | D11: 75
A12: 783983a98fe2613f15770fa78630e1d8965712e2 | B12: Ashes to crown | C12: Aus Der Asche Zur Krone | D12: 80
A13: 9540fa0b0f0a4e67296efcd05e977d34ff2d48cc | B13: Mad Vampire Lord's Bride | C13: Die Braut Des Wahnsinnigen Vampirfürsten | D13: 564
... A40: 7b1f3211cfdfae355799078a0b675eb572c9f339 | B40: The Outcast's Rise | C40: Der Aufstieg Des Verstoßenen | D40: 130
A41: ba9a53bc38add9627d366570dfc6c08876f48e4d | B41: Bostons Unterwelt
A42: 493705d33de4385c87a811e8ae8899e76a890fe3 | B42: Twisted Fates
A43: 7e1e5813e7823678b5b6b058c760cb5386024ecb | B43: Her Secret Twins
A44: ad4bfe824b03d3d4e9bbfeed8ce36aede06389f1 | B44: The Awakening of the Hidden Flame
A45: 866a12ddd302f8dc590fbe93b2129202813463a2 | B45: Blood Warlock
A46: a8d57b46e15bc77db724ce0e4a35bdd2b518caee | B46: The Silver Reign
A47: 5dbe70df4bf25983debeb7456e365d7bd4dfa233 | B47: A Luna's Broken Bond
A48: b54740cf347cde192b0349db2b3e296f4969d2b8 | B48: Flameborne
A49: ee4a46c44ce50f74afc76227c255319cc54faf7b | B49: The Seventh Seal
A50: cac0f22e476d85448eef81d1cd1e0ae16acab474 | B50: Dark Magus Returns
A51: 6c68ae6c8a319ab827c6b3c67580f184b8ac0b0b | B51: Unheilige Liebe
A52: a07e882978c5c8324da0caf15dffc973d6bfbc2c | B52: Soul of a warrior
... A73: 9ef11801929b795c04b5aeaa8cdfabda8a3fb241 | B73: Lupin
